Workbook
Name Beginning_Balance: -FV('Map Counties'!Interest_Rate/12,'Map Counties'!Payment_Number-1,-'Map Counties'!Monthly_Payment,'Map Counties'!Loan_Amount)
Name Beginning_Balance: -FV(Interest_Rate/12,'Wealth Creation Calc'!Payment_Number-1,-'Wealth Creation Calc'!Monthly_Payment,Loan_Amount)
Name Beginning_Balance: -FV(Interest_Rate/12,Payment_Number-1,-Monthly_Payment,Loan_Amount)
Name CA: #REF!
Name CaseShiller30: '[1]Case Shiller 30 yr'!$A$4:$R$111
Name CaseShiller30: '[2]Case Shiller 30 yr'!$A$4:$R$111
Name CaseShiller30: #REF!
Name CO: #REF!
Name CO_HomePrices: '[2]CO Home Prices'!$C$2:$J$69
Name CO_HomePrices: #REF!
Name ColumnTitle1: #REF!
Name ColumnTitle1: #REF!
Name ColumnTitle1: [1]!Loan[[#Headers],[No.]]
Name ColumnTitle1: #REF!
Name ColumnTitle1: #REF!
Name ColumnTitle1: [2]!Loan[[#Headers],[No.]]
Name ColumnTitle1: #REF!
Name Delete1: #REF!
Name Delete1: #REF!
Name Delete1: #REF!
Name Delete1: #REF!
Name Delete1: [2]!Loan[[#Headers],[No.]]
Name Delete1: #REF!
Name Delete21: #REF!
Name Delete21: #REF!
Name Delete21: #REF!
Name Delete21: #REF!
Name Delete21: [2]!Loan[[#Headers],[No.]]
Name Delete21: #REF!
Name Ending_Balance: -FV('Map Counties'!Interest_Rate/12,'Map Counties'!Payment_Number,-'Map Counties'!Monthly_Payment,'Map Counties'!Loan_Amount)
Name Ending_Balance: -FV(Interest_Rate/12,'Wealth Creation Calc'!Payment_Number,-'Wealth Creation Calc'!Monthly_Payment,Loan_Amount)
Name Ending_Balance: -FV(Interest_Rate/12,Payment_Number,-Monthly_Payment,Loan_Amount)
Name Full_Print: #REF!
Name Header_Row: ROW(#REF!)
Name Header_Row_Back: ROW('[1]Loan calculator'!$11:$11)
Name Header_Row_Back: ROW('[2]Loan calculator'!$11:$11)
Name Header_Row_Back: ROW(#REF!)
Name HPA: 'Assumptions & Borrower Profiles'!$C$11
Name Interest: -IPMT('Map Counties'!Interest_Rate/12,'Map Counties'!Payment_Number,'Map Counties'!Number_of_Payments,'Map Counties'!Loan_Amount)
Name Interest: -IPMT(Interest_Rate/12,'Wealth Creation Calc'!Payment_Number,Number_of_Payments,Loan_Amount)
Name Interest: -IPMT(Interest_Rate/12,Payment_Number,Number_of_Payments,Loan_Amount)
Name Interest_Rate: #REF!
Name Interest_Rate: #REF!
Name Last_Row: #N/A
Name Last_Row: #N/A
Name Last_Row: IF([3]!Values_Entered,[3]!Header_Row+[3]!Number_of_Payments,[3]!Header_Row)
Name Loan_Amount: #REF!
Name Loan_Amount: #REF!
Name Loan_Not_Paid: IF('Map Counties'!Payment_Number<='Map Counties'!Number_of_Payments,1,0)
Name Loan_Not_Paid: IF('Wealth Creation Calc'!Payment_Number<=Number_of_Payments,1,0)
Name Loan_Not_Paid: IF(Payment_Number<=Number_of_Payments,1,0)
Name Loan_Start: #REF!
Name Loan_Start: #REF!
Name Loan_Years: #REF!
Name Loan_Years: #REF!
Name Model: 'Aggregate Model'!$B$2:$BC$23
Name Model: 'Harper - Aggregate Model'!$B$2:$BC$76
Name Model: 'Remi - Aggregate Model'!$B$2:$BC$76
Name Model: 'Tiana - Aggregate Model'!$B$2:$BC$76
Name Model: '[2]Black & Hispanic Model'!$B$1:$BC$27

Sheet Target Zips List
D3: ## Paste Target Zips below in D4 then flow them thru to Individual Borrowers' Ag Model
D4: Alcona
D5: Alger
D6: Allegan
D7: Alpena
D8: Antrim
D9: Arenac
D10: Baraga
D11: Barry
D12: Bay
D13: Benzie
D14: Berrien
... D86: Wexford

Sheet Assumptions & Borrower Profiles
B1: Assumptions | F1: Hide Cells before Pasting into PPT | K1: Scenario | L1: 1 | M1: 2 | N1: 3
B2: Down Payment % | C2: 0.03 | K2: Name | L2: Cecilia | M2: Adam | N2: Nora
K3: Age | L3: 28 | M3: 32 | N3: 38
B4: Homium SAM % | C4: 0.3 | L4: Registered Nurse | M4: Police Officer | N4: CDL-A Truck Driver
K5: % AMI | L5: 0.8 | M5: 1 | N5: 1.2
B6: Credit Score | C6: 620 | K6: Avg. USD Income | L6: =L5*$C$21 -> 0 | M6: =M5*$C$21 -> 0 | N6: =N5*$C$21 -> 0 | O6: =AVERAGE(L6:N6) -> 0
B7: 1st Mortgage Rate w/o HOM | C7: 0.0625
B8: 1st Mortgage Rate w/ HOM | C8: =C7 -> 0.0625 | K8: % Median Home Price | L8: 1 | M8: 1 | N8: 1.4 | P8: =0.8*L9 -> 0
B9: Mortgage Duration (yrs) | C9: 30 | K9: Home Price | L9: =L8*$C$22 -> 0 | M9: =M8*$C$22 -> 0 | N9: =N8*$C$22 -> 0
B11: Annual HPA % | C11: 0.05 | K11: DP % | L11: =$C$2 -> 0.03 | M11: =$C$2 -> 0.03 | N11: =$C$2 -> 0.03
K12: ="Down Payment ("&C2*100&"%)" -> Down Payment (3%) | L12: =L9*L11 -> 0 | M12: =M9*M11 -> 0 | N12: =N9*N11 -> 0
B13: Closing Costs % | C13: 0.02
K14: Traditional Financing
K15: 1st Mortgage % | L15: =1-L11 -> 0.97 | M15: =1-M11 -> 0.97 | N15: =1-N11 -> 0.97
B16: PMI Rate Est | C16: 0.0117 | K16: ="Conforming 1st Mortgage ("&(1-C2)*100&"%)" -> Conforming 1st Mortgage (97%) | L16: =L15*L9 -> 0 | M16: =M15*M9 -> 0 | N16: =N15*N9 -> 0
B17: Tax/ yr | C17: 0.0135 | K17: Monthly PMT | L17: =PMT($C$7/12,12*$C$9,-L$16) -> 0 | M17: =PMT($C$7/12,12*$C$9,-M$16) -> 0 | N17: =PMT($C$7/12,12*$C$9,-N$16) -> 0
B18: Insurance / yr | C18: 0.004 | K18: Monthly PMI | L18: =L16*$C$16/12 -> 0 | M18: =M16*$C$16/12 -> 0 | N18: =N16*$C$16/12 -> 0
K19: Monthly Tax | L19: =$C$17*L$9/12 -> 0 | M19: =$C$17*M$9/12 -> 0 | N19: =$C$17*N$9/12 -> 0
B20: Median Calc | K20: Monthly Insurance | L20: =$C$18*L9/12 -> 0 | M20: =$C$18*M9/12 -> 0 | N20: =$C$18*N9/12 -> 0
B21: Household Income | C21: ='Aggregate Model'!I25 -> 0 | K21: Total Monthly Payment* | L21: =SUM(L17:L20) -> 0 | M21: =SUM(M17:M20) -> 0 | N21: =SUM(N17:N20) -> 0
B22: Home Value | C22: ='Aggregate Model'!G24 -> 0 | K22: Front Ratio** | L22: =L21/(L6/12) -> #DIV/0! | M22: =M21/(M6/12) -> #DIV/0! | N22: =N21/(N6/12) -> #DIV/0!
B24: Thresholds | K24: With
B25: Front Ratio | C25: 0.35 | K25: 1st Mortgage % | L25: =1-SUM(L27,L11) -> 0.67 | M25: =1-SUM(M27,M11) -> 0.67 | N25: =1-SUM(N27,N11) -> 0.72
K26: ="1st Mortgage with Homium ("&(1-SUM($C$4,$C$2))*100&"%)" -> 1st Mortgage with Homium (67%) | L26: =L25*L9 -> 0 | M26: =M25*M9 -> 0 | N26: =N25*N9 -> 0
K27: Homium % | L27: 0.3 | M27: 0.3 | N27: 0.25
K28: ="2nd Position Homium SAM ("&$C$4*100&"%)" -> 2nd Position Homium SAM (30%) | L28: =L27*L9 -> 0 | M28: =M27*M9 -> 0 | N28: =N27*N9 -> 0 | O28: =AVERAGE(L28:N28) -> 0
K29: Monthly Payment with Homium | L29: =PMT($C$8/12,12*$C$9,-L$26) -> 0 | M29: =PMT($C$8/12,12*$C$9,-M$26) -> 0 | N29: =PMT($C$8/12,12*$C$9,-N$26) -> 0
K30: Total Monthly Payment with Homium* | L30: =L29+SUM(L19:L20) -> 0 | M30: =M29+SUM(M19:M20) -> 0 | N30: =N29+SUM(N19:N20) -> 0
K31: Front Ratio** | L31: =L30/(L$6/12) -> #DIV/0! | M31: =M30/(M$6/12) -> #DIV/0! | N31: =N30/(N$6/12) -> #DIV/0!
K33: Comparison (Traditional vs Homium)
K34: Personal Free Cash Flow*** | L34: =L21-L30 -> 0 | M34: =M21-M30 -> 0 | N34: =N21-N30 -> 0 | O34: =L34*12 -> 0
B36: Program Size | K36: Program Impact
B37: Program Capital | C37: 10000000 | K37: % AMI | L37: =L5 -> 0.8 | M37: =M5 -> 1 | N37: =N5 -> 1.2
A38: 0.05 | B38: Less: Program Fee | C38: =-C37*A38 -> -500000 | K38: Borrower Eligibility w/o Homium | L38: 0.35 | M38: 0.71 | N38: 0.49
B39: Net Capital Invested | C39: =SUM(C37:C38) -> 9500000 | K39: Borrower Eligibility with Homium | L39: 0.84 | M39: 0.94 | N39: 0.84
K40: Increase in Borrower Eligibility | L40: =L39-L38 -> 0.49 | M40: =M39-M38 -> 0.23 | N40: =N39-N38 -> 0.35
K42: # FTHB Homes Created | L42: =$C$39/L28 -> #DIV/0! | M42: =$C$39/M28 -> #DIV/0! | N42: =$C$39/N28 -> #DIV/0!
K44: Total Value of Homes Purchased | L44: =L$42*L9 -> #DIV/0! | M44: =M$42*M9 -> #DIV/0! | N44: =N$42*N9 -> #DIV/0! | O44: =AVERAGE(L44:N44) -> #DIV/0!
K45: Total 1st Mortgage Principal | L45: =L$42*L26 -> #DIV/0! | M45: =M$42*M26 -> #DIV/0! | N45: =N$42*N26 -> #DIV/0! | O45: =AVERAGE(L45:N45) -> #DIV/0!
K46: Total Homeowner Equity created after 10 Years at 5% Home Price Appreciation | L46: =L42*((L9*(1+HPA)^10)-(L28*(1+HPA)^10)-FV($C$8/12,10*12,L29,-L26)) -> #DIV/0! | M46: =M42*((M9*(1+HPA)^10)-(M28*(1+HPA)^10)-FV($C$8/12,10*12,M29,-M26)) -> #DIV/0! | N46: =N42*((N9*(1+HPA)^10)-(N28*(1+HPA)^10)-FV($C$8/12,10*12,N29,-N26)) -> #DIV/0! | O46: =AVERAGE(L46:N46) -> #DIV/0!
K48: Avg. FTHB Homes Created | L48: =AVERAGE(L42:N42) -> #DIV/0!

Sheet Aggregate Model
BS2: Front Ratio | BT2: 0.35
B3: Key Assumptions: | K3: ='Assumptions & Borrower Profiles'!$C$11 -> 0.05 | L3: 1 | M3: 1 | Q3: 0.3 | R3: 1 | X3: ='Assumptions & Borrower Profiles'!L11 -> 0.03 | Y3: ='Assumptions & Borrower Profiles'!$C$7 -> 0.0625 | AA3: ='Assumptions & Borrower Profiles'!$C$6 -> 620 | AC3: ='Assumptions & Borrower Profiles'!$C$18 -> 0.004 | AF3: ='Assumptions & Borrower Profiles'!$C$25 -> 0.35 | AG3: =AF3+0.1 -> 0.45 | AH3: =Q3 -> 0.3 | AI3: ='Assumptions & Borrower Profiles'!C7-'Assumptions & Borrower Profiles'!C8 -> 0 | AK3: 0 | AM3: =AC3 -> 0.004 | AP3: =AF3 -> 0.35 | AQ3: =AG3 -> 0.45 | AR3: 0 | AS3: ='Assumptions & Borrower Profiles'!$C$13 -> 0.02 | AT3: 0.03 | AU3: 0 | BN3: Homium needed | CA3: Affordability Test (Without Homium) | CG3: Homium Needed
B4: County | C4: Code | D4: Population | E4: % African American | F4: Area Median Household Income | G4: Median Home Values | H4: Median Contract Rent | I4: DTI Avg | J4: Estimated Household Debt (incl mortgage) | K4: 30 Year Case Shiller Return / ann | L4: % AMI for calc | M4: % Median Home Value | N4: Passed DTI without HOM? | O4: Passed DTI with HOM? | P4: Threshold? | Q4: HOM Investment | R4: Grant for Fees/PMI | S4: Annual PMI | T4: Homeowner Equity after 10 Years | U4: % Gain from Downpayment | V4: HOM Investment after 10 Years | W4: % Gain on HOM Investment | X4: Downpayment | Y4: 30 Year Fixed Rate for 640 | Z4: 1st Principal Without Homium | AA4: PMI / Month | AB4: Tax / mo | AC4: Insurance / mo | AD4: Household Debt Service / mo | AE4: Monthly Payment | AF4: Front Ratio | AG4: Back Ratio | AH4: SAN Principal | AI4: 30 Year Fixed Rate for 640 WITH HOMIUM | AJ4: 1st Principal WITH Homium | AK4: PMI / Month | AL4: Tax / mo | AM4: Insurance / mo | AN4: Household Debt Service / mo | AO4: New Monthly Payment on 1st | AP4: Front Ratio with HOM | AQ4: Back Ratio with HOM | AR4: PMI Total (yrs) | AS4: Closing Fees | AT4: Origination Fees | AU4: Total Grant | AV4: % Total Grant of Home Value | AW4: Home Value after 10 years at X apprec | AX4: Homium SAN Value after 10 years | AY4: % Gain on HOM investment | AZ4: Homeowner Equity after 10 years | BA4: % Gain from Downpayment | BE4: Max Monthly Payment (PITI) | BF4: Max PI without Hom | BG4: Monthly Rate | BH4: Payment Factor | BI4: Affordable 1st Mortgage Balance without HOM | BK4: Max PI with Hom | BL4: Affordable 1st Mortgage Balance w HOM | BN4: Affordability Gap without Hom | BO4: Hom % | BP4: residual gap after homium (Check) | BS4: State | BT4: AMI | BU4: MHV | BV4: Median Rent | BW4: PMI | BX4: Tax | BY4: Insurance | BZ4: Max Monthly Housing Budget | CA4: Max Principal + Interest Without Hom | CB4: Monthly 1st Mortgage Rate | CC4: Affordable Home Price @ 35% DTI | CD4: Affordability Gap (Problem) | CE4: Affordable 1st Mortgage Without Hom | CG4: Max Principal + Interest With Homium | CH4: Affordable 1st Mortgage with Homium | CI4: Down Payment (3%) | CJ4: Homium Needed ($) | CK4: Homium % | CM4: Affordable Home Price PITI | CN4: 1% Monthly Maintenance | CO4: Total Monthly Ownership Cost | CP4: Median Contract Rent | CQ4: Monthly Delta
B5: Delaware | D5: =_xlfn.XLOOKUP($B5,'Paste Snowflake Data Here'!$B$3:$B$1048576,'Paste Snowflake Data Here'!$D$3:$D$1048576) -> 1043909 | F5: =_xlfn.XLOOKUP($B5,'Paste Snowflake Data Here'!$B$3:$B$1048576,'Paste Snowflake Data Here'!$I$3:$I$1048576) -> 84523 | G5: =_xlfn.XLOOKUP($B5,'Paste Snowflake Data Here'!$B$3:$B$1048576,'Paste Snowflake Data Here'!$J$3:$J$1048576) -> 389964 | H5: =_xlfn.XLOOKUP($B5,'Paste Snowflake Data Here'!$B$3:$B$1048576,'Paste Snowflake Data Here'!$K$3:$K$1048576) -> 1322 | K5: =IFERROR(VLOOKUP(LEFT(B5,FIND("County",B5)-2),CaseShiller30,5,0)*0.01,$K$3) -> 0.05 | L5: =$F5*$L$3 -> 84523 | M5: =$G5*$M$3 -> 389964 | N5: =AND(AF5<$AF$3,AG5<$AG$3) -> FALSE | O5: =AND(AP5<$AP$3,AQ5<$AQ$3) -> TRUE | P5: =AND(N5=FALSE,O5) -> TRUE | Q5: =AH5 -> 116989.2 | R5: =AU5 -> 0 | S5: =AR5 -> 0 | T5: =AZ5 -> 224554.36 | U5: =BA5 -> 19.194452 | V5: =AX5 -> 190563.08 | W5: =AY5 -> 1.6288946 | X5: =$X$3*M5 -> 11698.92 | Y5: =$Y$3 -> 0.0625 | Z5: =M5-X5 -> 378265.08 | AA5: =Z5*'PMI Rate Est'!$J$6/12 -> 368.80845 | AB5: ='Taxes & Ins by State'!B9*M5/12 -> 162.485 | AC5: ='Taxes & Ins by State'!M2*M5/12 -> 80.333333 | AD5: =MAX(J5*Y5/12,0) -> 0 | AE5: =-PMT(Y5/12,360,Z5) -> 2329.0432 | AF5: =SUM(AE5,AC5,AB5,AA5)/(L5/12) -> 0.4174963 | AG5: =SUM(AE5,AC5,AB5,AA5,AD5)/(L5/12) -> 0.4174963 | AH5: =M5*$AH$3 -> 116989.2 | AI5: =Y5+$AI$3 -> 0.0625 | AJ5: =M5-X5-AH5 -> 261275.88 | AK5: =AH5*$AK$3/12 -> 0 | AL5: =AB5 -> 162.485 | AM5: =AC5 -> 80.333333 | AN5: =MAX(J5*Y5/12,0) -> 0 | AO5: =-PMT(AI5/12,360,AJ5) -> 1608.7205 | AP5: =SUM(AO5,AM5,AL5)/(L5/12) -> 0.26286888 | AQ5: =SUM(AO5,AM5,AL5,AK5,AN5)/(L5/12) -> 0.26286888 | AR5: =$AR$3*AK5*12 -> 0 | AS5: =$AS$3*(M5-X5) -> 7565.3016 | AT5: =$AT$3*(AH5) -> 3509.676 | AU5: =$AU$3*SUM(AR5,AS5,AT5) -> 0 | AV5: =AU5/M5 -> 0 | AW5: =POWER(1+K5,10)*M5 -> 635210.26 | AX5: =POWER(1+K5,10)*AH5 -> 190563.08 | AY5: =AX5/AH5 -> 1.6288946 | AZ5: =AW5-AX5-FV(AI5/12,(10*12),AO5,-AJ5) -> 224554.36 | BA5: =AZ5/X5 -> 19.194452 | BE5: =(L5/12)*35% -> 2465.2542 | BF5: =BE5-AC5-AB5-AA5 -> 1853.6274 | BG5: =$Y$3/12 -> 0.0052083333 | BH5: =(BG5*(1+BG5)^360) / (((1+BG5)^360)-1) -> 0.006157172 | BI5: =PV(BG5, 360, -BF5) -> 301051.75 | BK5: =BE5-AB5-AC5 -> 2222.4358 | BL5: =BK5/BH5 -> 360950.75 | BN5: =M5-BI5-X5 -> 77213.334 | BO5: =BN5/M5 -> 0.19800119 | BP5: =M5-BL5-X5 -> 17314.333 | BS5: =B5 -> Delaware | BT5: =L5 -> 84523 | BU5: =M5 -> 389964 | BV5: =H5 -> 1322 | BW5: =AA5 -> 368.80845 | BX5: =AB5 -> 162.485 | BY5: =AC5 -> 80.333333 | BZ5: =(BT5/12)*$BT$2 -> 2465.2542 | CA5: =BZ5-BW5-BX5-BY5 -> 1853.6274 | CB5: =6.25%/12 -> 0.0052083333 | CC5: =CE5/0.97 -> 310362.62 | CD5: =BU5-CC5 -> 79601.376 | CE5: =PV(CB5,360,-CA5) -> 301051.75 | CG5: =BZ5-BY5-BX5 -> 2222.4358 | CH5: =PV(CB5,360,-CG5) -> 360950.75 | CI5: =BU5*0.03 -> 11698.92 | CJ5: =BU5-CI5-CH5 -> 17314.333 | CK5: =CJ5/BU5 -> 0.044399825 | CM5: =CA5 -> 1853.6274 | CN5: =(CC5*1%)/12 -> 258.63552 | CO5: =CM5+CN5+BX5+BY5 -> 2355.0812 | CP5: =VLOOKUP(BS5,'Paste Snowflake Data Here'!$B$2:$K$21,10,FALSE) -> 1322 | CQ5: =CP5-CO5 -> -1033.0812
B6: Hawaii | D6: =_xlfn.XLOOKUP($B6,'Paste Snowflake Data Here'!$B$3:$B$1048576,'Paste Snowflake Data Here'!$D$3:$D$1048576) -> 1480456 | F6: =_xlfn.XLOOKUP($B6,'Paste Snowflake Data Here'!$B$3:$B$1048576,'Paste Snowflake Data Here'!$I$3:$I$1048576) -> 101529 | G6: =_xlfn.XLOOKUP($B6,'Paste Snowflake Data Here'!$B$3:$B$1048576,'Paste Snowflake Data Here'!$J$3:$J$1048576) -> 924013 | H6: =_xlfn.XLOOKUP($B6,'Paste Snowflake Data Here'!$B$3:$B$1048576,'Paste Snowflake Data Here'!$K$3:$K$1048576) -> 1807 | K6: =IFERROR(VLOOKUP(LEFT(B6,FIND("County",B6)-2),CaseShiller30,5,0)*0.01,$K$3) -> 0.05 | L6: =$F6*$L$3 -> 101529 | M6: =$G6*$M$3 -> 924013 | N6: =AND(AF6<$AF$3,AG6<$AG$3) -> FALSE | O6: =AND(AP6<$AP$3,AQ6<$AQ$3) -> FALSE | P6: =AND(N6=FALSE,O6) -> FALSE | Q6: =AH6 -> 277203.9 | R6: =AU6 -> 0 | S6: =AR6 -> 0 | T6: =AZ6 -> 532077.7 | U6: =BA6 -> 19.194452 | V6: =AX6 -> 451535.94 | W6: =AY6 -> 1.6288946 | X6: =$X$3*M6 -> 27720.39 | Y6: =$Y$3 -> 0.0625 | Z6: =M6-X6 -> 896292.61 | AA6: =Z6*'PMI Rate Est'!$J$6/12 -> 873.88529 | AB6: ='Taxes & Ins by State'!B12*M6/12 -> 246.40347 | AC6: ='Taxes & Ins by State'!M3*M6/12 -> 102 | AD6: =MAX(J6*Y6/12,0) -> 0 | AE6: =-PMT(Y6/12,360,Z6) -> 5518.6278 | AF6: =SUM(AE6,AC6,AB6,AA6)/(L6/12) -> 0.79672801 | AG6: =SUM(AE6,AC6,AB6,AA6,AD6)/(L6/12) -> 0.79672801 | AH6: =M6*$AH$3 -> 277203.9 | AI6: =Y6+$AI$3 -> 0.0625 | AJ6: =M6-X6-AH6 -> 619088.71 | AK6: =AH6*$AK$3/12 -> 0 | AL6: =AB6 -> 246.40347 | AM6: =AC6 -> 102 | AN6: =MAX(J6*Y6/12,0) -> 0 | AO6: =-PMT(AI6/12,360,AJ6) -> 3811.8357 | AP6: =SUM(AO6,AM6,AL6)/(L6/12) -> 0.49171044 | AQ6: =SUM(AO6,AM6,AL6,AK6,AN6)/(L6/12) -> 0.49171044 | AR6: =$AR$3*AK6*12 -> 0 | AS6: =$AS$3*(M6-X6) -> 17925.852 | AT6: =$AT$3*(AH6) -> 8316.117 | AU6: =$AU$3*SUM(AR6,AS6,AT6) -> 0 | AV6: =AU6/M6 -> 0 | AW6: =POWER(1+K6,10)*M6 -> 1505119.8 | AX6: =POWER(1+K6,10)*AH6 -> 451535.94 | AY6: =AX6/AH6 -> 1.6288946 | AZ6: =AW6-AX6-FV(AI6/12,(10*12),AO6,-AJ6) -> 532077.7 | BA6: =AZ6/X6 -> 19.194452 | BE6: =(L6/12)*35% -> 2961.2625 | BF6: =BE6-AC6-AB6-AA6 -> 1738.9737 | BG6: =$Y$3/12 -> 0.0052083333 | BH6: =(BG6*(1+BG6)^360) / (((1+BG6)^360)-1) -> 0.006157172 | BI6: =PV(BG6, 360, -BF6) -> 282430.59 | BK6: =BE6-AB6-AC6 -> 2612.859 | BL6: =BK6/BH6 -> 424360.25 | BN6: =M6-BI6-X6 -> 613862.02 | BO6: =BN6/M6 -> 0.66434349 | BP6: =M6-BL6-X6 -> 471932.36 | BS6: =B6 -> Hawaii | BT6: =L6 -> 101529 | BU6: =M6 -> 924013 | BV6: =H6 -> 1807 | BW6: =AA6 -> 873.88529 | BX6: =AB6 -> 246.40347 | BY6: =AC6 -> 102 | BZ6: =(BT6/12)*$BT$2 -> 2961.2625 | CA6: =BZ6-BW6-BX6-BY6 -> 1738.9737 | CB6: =6.25%/12 -> 0.0052083333 | CC6: =CE6/0.97 -> 291165.56 | CD6: =BU6-CC6 -> 632847.44 | CE6: =PV(CB6,360,-CA6) -> 282430.59 | CG6: =BZ6-BY6-BX6 -> 2612.859 | CH6: =PV(CB6,360,-CG6) -> 424360.25 | CI6: =BU6*0.03 -> 27720.39 | CJ6: =BU6-CI6-CH6 -> 471932.36 | CK6: =CJ6/BU6 -> 0.51074212 | CM6: =CA6 -> 1738.9737 | CN6: =(CC6*1%)/12 -> 242.63797 | CO6: =CM6+CN6+BX6+BY6 -> 2330.0152 | CP6: =VLOOKUP(BS6,'Paste Snowflake Data Here'!$B$2:$K$21,10,FALSE) -> 1807 | CQ6: =CP6-CO6 -> -523.01517
B7: Illinois | D7: =_xlfn.XLOOKUP($B7,'Paste Snowflake Data Here'!$B$3:$B$1048576,'Paste Snowflake Data Here'!$D$3:$D$1048576) -> 12439592 | F7: =_xlfn.XLOOKUP($B7,'Paste Snowflake Data Here'!$B$3:$B$1048576,'Paste Snowflake Data Here'!$I$3:$I$1048576) -> 84176 | G7: =_xlfn.XLOOKUP($B7,'Paste Snowflake Data Here'!$B$3:$B$1048576,'Paste Snowflake Data Here'!$J$3:$J$1048576) -> 286497 | H7: =_xlfn.XLOOKUP($B7,'Paste Snowflake Data Here'!$B$3:$B$1048576,'Paste Snowflake Data Here'!$K$3:$K$1048576) -> 1205 | K7: =IFERROR(VLOOKUP(LEFT(B7,FIND("County",B7)-2),CaseShiller30,5,0)*0.01,$K$3) -> 0.05 | L7: =$F7*$L$3 -> 84176 | M7: =$G7*$M$3 -> 286497 | N7: =AND(AF7<$AF$3,AG7<$AG$3) -> FALSE | O7: =AND(AP7<$AP$3,AQ7<$AQ$3) -> TRUE | P7: =AND(N7=FALSE,O7) -> TRUE | Q7: =AH7 -> 85949.1 | R7: =AU7 -> 0 | S7: =AR7 -> 0 | T7: =AZ7 -> 164974.59 | U7: =BA7 -> 19.194452 | V7: =AX7 -> 140002.03 | W7: =AY7 -> 1.6288946 | X7: =$X$3*M7 -> 8594.91 | Y7: =$Y$3 -> 0.0625 | Z7: =M7-X7 -> 277902.09 | AA7: =Z7*'PMI Rate Est'!$J$6/12 -> 270.95454 | AB7: ='Taxes & Ins by State'!B14*M7/12 -> 436.90792 | AC7: ='Taxes & Ins by State'!M4*M7/12 -> 188.75 | AD7: =MAX(J7*Y7/12,0) -> 0 | AE7: =-PMT(Y7/12,360,Z7) -> 1711.091 | AF7: =SUM(AE7,AC7,AB7,AA7)/(L7/12) -> 0.37175016 | AG7: =SUM(AE7,AC7,AB7,AA7,AD7)/(L7/12) -> 0.37175016 | AH7: =M7*$AH$3 -> 85949.1 | AI7: =Y7+$AI$3 -> 0.0625 | AJ7: =M7-X7-AH7 -> 191952.99 | AK7: =AH7*$AK$3/12 -> 0 | AL7: =AB7 -> 436.90792 | AM7: =AC7 -> 188.75 | AN7: =MAX(J7*Y7/12,0) -> 0 | AO7: =-PMT(AI7/12,360,AJ7) -> 1181.8876 | AP7: =SUM(AO7,AM7,AL7)/(L7/12) -> 0.25768088 | AQ7: =SUM(AO7,AM7,AL7,AK7,AN7)/(L7/12) -> 0.25768088 | AR7: =$AR$3*AK7*12 -> 0 | AS7: =$AS$3*(M7-X7) -> 5558.0418 | AT7: =$AT$3*(AH7) -> 2578.473 | AU7: =$AU$3*SUM(AR7,AS7,AT7) -> 0 | AV7: =AU7/M7 -> 0 | AW7: =POWER(1+K7,10)*M7 -> 466673.42 | AX7: =POWER(1+K7,10)*AH7 -> 140002.03 | AY7: =AX7/AH7 -> 1.6288946 | AZ7: =AW7-AX7-FV(AI7/12,(10*12),AO7,-AJ7) -> 164974.59 | BA7: =AZ7/X7 -> 19.194452 | BE7: =(L7/12)*35% -> 2455.1333 | BF7: =BE7-AC7-AB7-AA7 -> 1558.5209 | BG7: =$Y$3/12 -> 0.0052083333 | BH7: =(BG7*(1+BG7)^360) / (((1+BG7)^360)-1) -> 0.006157172 | BI7: =PV(BG7, 360, -BF7) -> 253122.84 | BK7: =BE7-AB7-AC7 -> 1829.4754 | BL7: =BK7/BH7 -> 297129.17 | BN7: =M7-BI7-X7 -> 24779.249 | BO7: =BN7/M7 -> 0.086490431 | BP7: =M7-BL7-X7 -> -19227.08 | BS7: =B7 -> Illinois | BT7: =L7 -> 84176 | BU7: =M7 -> 286497 | BV7: =H7 -> 1205 | BW7: =AA7 -> 270.95454 | BX7: =AB7 -> 436.90792 | BY7: =AC7 -> 188.75 | BZ7: =(BT7/12)*$BT$2 -> 2455.1333 | CA7: =BZ7-BW7-BX7-BY7 -> 1558.5209 | CB7: =6.25%/12 -> 0.0052083333 | CC7: =CE7/0.97 -> 260951.38 | CD7: =BU7-CC7 -> 25545.617 | CE7: =PV(CB7,360,-CA7) -> 253122.84 | CG7: =BZ7-BY7-BX7 -> 1829.4754 | CH7: =PV(CB7,360,-CG7) -> 297129.17 | CI7: =BU7*0.03 -> 8594.91 | CJ7: =BU7-CI7-CH7 -> -19227.08 | CK7: =CJ7/BU7 -> -0.06711093 | CM7: =CA7 -> 1558.5209 | CN7: =(CC7*1%)/12 -> 217.45949 | CO7: =CM7+CN7+BX7+BY7 -> 2401.6383 | CP7: =VLOOKUP(BS7,'Paste Snowflake Data Here'!$B$2:$K$21,10,FALSE) -> 1205 | CQ7: =CP7-CO7 -> -1196.6383
B8: Maryland | D8: =_xlfn.XLOOKUP($B8,'Paste Snowflake Data Here'!$B$3:$B$1048576,'Paste Snowflake Data Here'!$D$3:$D$1048576) -> 6270068 | F8: =_xlfn.XLOOKUP($B8,'Paste Snowflake Data Here'!$B$3:$B$1048576,'Paste Snowflake Data Here'!$I$3:$I$1048576) -> 103503 | G8: =_xlfn.XLOOKUP($B8,'Paste Snowflake Data Here'!$B$3:$B$1048576,'Paste Snowflake Data Here'!$J$3:$J$1048576) -> 468044 | H8: =_xlfn.XLOOKUP($B8,'Paste Snowflake Data Here'!$B$3:$B$1048576,'Paste Snowflake Data Here'!$K$3:$K$1048576) -> 1654 | K8: =IFERROR(VLOOKUP(LEFT(B8,FIND("County",B8)-2),CaseShiller30,5,0)*0.01,$K$3) -> 0.05 | L8: =$F8*$L$3 -> 103503 | M8: =$G8*$M$3 -> 468044 | N8: =AND(AF8<$AF$3,AG8<$AG$3) -> FALSE | O8: =AND(AP8<$AP$3,AQ8<$AQ$3) -> TRUE | P8: =AND(N8=FALSE,O8) -> TRUE | Q8: =AH8 -> 140413.2 | R8: =AU8 -> 0 | S8: =AR8 -> 0 | T8: =AZ8 -> 269515.44 | U8: =BA8 -> 19.194452 | V8: =AX8 -> 228718.31 | W8: =AY8 -> 1.6288946 | X8: =$X$3*M8 -> 14041.32 | Y8: =$Y$3 -> 0.0625 | Z8: =M8-X8 -> 454002.68 | AA8: =Z8*'PMI Rate Est'!$J$6/12 -> 442.65261 | AB8: ='Taxes & Ins by State'!B21*M8/12 -> 351.033 | AC8: ='Taxes & Ins by State'!M5*M8/12 -> 139.25 | AD8: =MAX(J8*Y8/12,0) -> 0 | AE8: =-PMT(Y8/12,360,Z8) -> 2795.3726 | AF8: =SUM(AE8,AC8,AB8,AA8)/(L8/12) -> 0.43225509 | AG8: =SUM(AE8,AC8,AB8,AA8,AD8)/(L8/12) -> 0.43225509 | AH8: =M8*$AH$3 -> 140413.2 | AI8: =Y8+$AI$3 -> 0.0625 | AJ8: =M8-X8-AH8 -> 313589.48 | AK8: =AH8*$AK$3/12 -> 0 | AL8: =AB8 -> 351.033 | AM8: =AC8 -> 139.25 | AN8: =MAX(J8*Y8/12,0) -> 0 | AO8: =-PMT(AI8/12,360,AJ8) -> 1930.8244 | AP8: =SUM(AO8,AM8,AL8)/(L8/12) -> 0.28069996 | AQ8: =SUM(AO8,AM8,AL8,AK8,AN8)/(L8/12) -> 0.28069996 | AR8: =$AR$3*AK8*12 -> 0 | AS8: =$AS$3*(M8-X8) -> 9080.0536 | AT8: =$AT$3*(AH8) -> 4212.396 | AU8: =$AU$3*SUM(AR8,AS8,AT8) -> 0 | AV8: =AU8/M8 -> 0 | AW8: =POWER(1+K8,10)*M8 -> 762394.36 | AX8: =POWER(1+K8,10)*AH8 -> 228718.31 | AY8: =AX8/AH8 -> 1.6288946 | AZ8: =AW8-AX8-FV(AI8/12,(10*12),AO8,-AJ8) -> 269515.44 | BA8: =AZ8/X8 -> 19.194452 | BE8: =(L8/12)*35% -> 3018.8375 | BF8: =BE8-AC8-AB8-AA8 -> 2085.9019 | BG8: =$Y$3/12 -> 0.0052083333 | BH8: =(BG8*(1+BG8)^360) / (((1+BG8)^360)-1) -> 0.006157172 | BI8: =PV(BG8, 360, -BF8) -> 338775.96 | BK8: =BE8-AB8-AC8 -> 2528.5545 | BL8: =BK8/BH8 -> 410668.16 | BN8: =M8-BI8-X8 -> 115226.72 | BO8: =BN8/M8 -> 0.24618778 | BP8: =M8-BL8-X8 -> 43334.52 | BS8: =B8 -> Maryland | BT8: =L8 -> 103503 | BU8: =M8 -> 468044 | BV8: =H8 -> 1654 | BW8: =AA8 -> 442.65261 | BX8: =AB8 -> 351.033 | BY8: =AC8 -> 139.25 | BZ8: =(BT8/12)*$BT$2 -> 3018.8375 | CA8: =BZ8-BW8-BX8-BY8 -> 2085.9019 | CB8: =6.25%/12 -> 0.0052083333 | CC8: =CE8/0.97 -> 349253.57 | CD8: =BU8-CC8 -> 118790.43 | CE8: =PV(CB8,360,-CA8) -> 338775.96 | CG8: =BZ8-BY8-BX8 -> 2528.5545 | CH8: =PV(CB8,360,-CG8) -> 410668.16 | CI8: =BU8*0.03 -> 14041.32 | CJ8: =BU8-CI8-CH8 -> 43334.52 | CK8: =CJ8/BU8 -> 0.092586423 | CM8: =CA8 -> 2085.9019 | CN8: =(CC8*1%)/12 -> 291.04464 | CO8: =CM8+CN8+BX8+BY8 -> 2867.2295 | CP8: =VLOOKUP(BS8,'Paste Snowflake Data Here'!$B$2:$K$21,10,FALSE) -> 1654 | CQ8: =CP8-CO8 -> -1213.2295
B9: Massachusetts | D9: =_xlfn.XLOOKUP($B9,'Paste Snowflake Data Here'!$B$3:$B$1048576,'Paste Snowflake Data Here'!$D$3:$D$1048576) -> 7069210 | F9: =_xlfn.XLOOKUP($B9,'Paste Snowflake Data Here'!$B$3:$B$1048576,'Paste Snowflake Data Here'!$I$3:$I$1048576) -> 105410 | G9: =_xlfn.XLOOKUP($B9,'Paste Snowflake Data Here'!$B$3:$B$1048576,'Paste Snowflake Data Here'!$J$3:$J$1048576) -> 637329 | H9: =_xlfn.XLOOKUP($B9,'Paste Snowflake Data Here'!$B$3:$B$1048576,'Paste Snowflake Data Here'!$K$3:$K$1048576) -> 1763 | K9: =IFERROR(VLOOKUP(LEFT(B9,FIND("County",B9)-2),CaseShiller30,5,0)*0.01,$K$3) -> 0.05 | L9: =$F9*$L$3 -> 105410 | M9: =$G9*$M$3 -> 637329 | N9: =AND(AF9<$AF$3,AG9<$AG$3) -> FALSE | O9: =AND(AP9<$AP$3,AQ9<$AQ$3) -> FALSE | P9: =AND(N9=FALSE,O9) -> FALSE | Q9: =AH9 -> 191198.7 | R9: =AU9 -> 0 | S9: =AR9 -> 0 | T9: =AZ9 -> 366995.43 | U9: =BA9 -> 19.194452 | V9: =AX9 -> 311442.54 | W9: =AY9 -> 1.6288946 | X9: =$X$3*M9 -> 19119.87 | Y9: =$Y$3 -> 0.0625 | Z9: =M9-X9 -> 618209.13 | AA9: =Z9*'PMI Rate Est'!$J$6/12 -> 602.7539 | AB9: ='Taxes & Ins by State'!B22*M9/12 -> 515.17427 | AC9: ='Taxes & Ins by State'!M6*M9/12 -> 141.91667 | AD9: =MAX(J9*Y9/12,0) -> 0 | AE9: =-PMT(Y9/12,360,Z9) -> 3806.4199 | AF9: =SUM(AE9,AC9,AB9,AA9)/(L9/12) -> 0.57674962 | AG9: =SUM(AE9,AC9,AB9,AA9,AD9)/(L9/12) -> 0.57674962 | AH9: =M9*$AH$3 -> 191198.7 | AI9: =Y9+$AI$3 -> 0.0625 | AJ9: =M9-X9-AH9 -> 427010.43 | AK9: =AH9*$AK$3/12 -> 0 | AL9: =AB9 -> 515.17427 | AM9: =AC9 -> 141.91667 | AN9: =MAX(J9*Y9/12,0) -> 0 | AO9: =-PMT(AI9/12,360,AJ9) -> 2629.1767 | AP9: =SUM(AO9,AM9,AL9)/(L9/12) -> 0.37411262 | AQ9: =SUM(AO9,AM9,AL9,AK9,AN9)/(L9/12) -> 0.37411262 | AR9: =$AR$3*AK9*12 -> 0 | AS9: =$AS$3*(M9-X9) -> 12364.183 | AT9: =$AT$3*(AH9) -> 5735.961 | AU9: =$AU$3*SUM(AR9,AS9,AT9) -> 0 | AV9: =AU9/M9 -> 0 | AW9: =POWER(1+K9,10)*M9 -> 1038141.8 | AX9: =POWER(1+K9,10)*AH9 -> 311442.54 | AY9: =AX9/AH9 -> 1.6288946 | AZ9: =AW9-AX9-FV(AI9/12,(10*12),AO9,-AJ9) -> 366995.43 | BA9: =AZ9/X9 -> 19.194452 | BE9: =(L9/12)*35% -> 3074.4583 | BF9: =BE9-AC9-AB9-AA9 -> 1814.6135 | BG9: =$Y$3/12 -> 0.0052083333 | BH9: =(BG9*(1+BG9)^360) / (((1+BG9)^360)-1) -> 0.006157172 | BI9: =PV(BG9, 360, -BF9) -> 294715.41 | BK9: =BE9-AB9-AC9 -> 2417.3674 | BL9: =BK9/BH9 -> 392610.01 | BN9: =M9-BI9-X9 -> 323493.72 | BO9: =BN9/M9 -> 0.50757727 | BP9: =M9-BL9-X9 -> 225599.12 | BS9: =B9 -> Massachusetts | BT9: =L9 -> 105410 | BU9: =M9 -> 637329 | BV9: =H9 -> 1763 | BW9: =AA9 -> 602.7539 | BX9: =AB9 -> 515.17427 | BY9: =AC9 -> 141.91667 | BZ9: =(BT9/12)*$BT$2 -> 3074.4583 | CA9: =BZ9-BW9-BX9-BY9 -> 1814.6135 | CB9: =6.25%/12 -> 0.0052083333 | CC9: =CE9/0.97 -> 303830.32 | CD9: =BU9-CC9 -> 333498.68 | CE9: =PV(CB9,360,-CA9) -> 294715.41 | CG9: =BZ9-BY9-BX9 -> 2417.3674 | CH9: =PV(CB9,360,-CG9) -> 392610.01 | CI9: =BU9*0.03 -> 19119.87 | CJ9: =BU9-CI9-CH9 -> 225599.12 | CK9: =CJ9/BU9 -> 0.35397591 | CM9: =CA9 -> 1814.6135 | CN9: =(CC9*1%)/12 -> 253.19194 | CO9: =CM9+CN9+BX9+BY9 -> 2724.8964 | CP9: =VLOOKUP(BS9,'Paste Snowflake Data Here'!$B$2:$K$21,10,FALSE) -> 1763 | CQ9: =CP9-CO9 -> -961.89637
B10: New Jersey | D10: =_xlfn.XLOOKUP($B10,'Paste Snowflake Data Here'!$B$3:$B$1048576,'Paste Snowflake Data Here'!$D$3:$D$1048576) -> 9425430 | F10: =_xlfn.XLOOKUP($B10,'Paste Snowflake Data Here'!$B$3:$B$1048576,'Paste Snowflake Data Here'!$I$3:$I$1048576) -> 104287 | G10: =_xlfn.XLOOKUP($B10,'Paste Snowflake Data Here'!$B$3:$B$1048576,'Paste Snowflake Data Here'!$J$3:$J$1048576) -> 513938 | H10: =_xlfn.XLOOKUP($B10,'Paste Snowflake Data Here'!$B$3:$B$1048576,'Paste Snowflake Data Here'!$K$3:$K$1048576) -> 1679 | K10: =IFERROR(VLOOKUP(LEFT(B10,FIND("County",B10)-2),CaseShiller30,5,0)*0.01,$K$3) -> 0.05 | L10: =$F10*$L$3 -> 104287 | M10: =$G10*$M$3 -> 513938 | N10: =AND(AF10<$AF$3,AG10<$AG$3) -> FALSE | O10: =AND(AP10<$AP$3,AQ10<$AQ$3) -> TRUE | P10: =AND(N10=FALSE,O10) -> TRUE | Q10: =AH10 -> 154181.4 | R10: =AU10 -> 0 | S10: =AR10 -> 0 | T10: =AZ10 -> 295942.75 | U10: =BA10 -> 19.194452 | V10: =AX10 -> 251145.25 | W10: =AY10 -> 1.6288946 | X10: =$X$3*M10 -> 15418.14 | Y10: =$Y$3 -> 0.0625 | Z10: =M10-X10 -> 498519.86 | AA10: =Z10*'PMI Rate Est'!$J$6/12 -> 486.05686 | AB10: ='Taxes & Ins by State'!B31*M10/12 -> 758.05855 | AC10: ='Taxes & Ins by State'!M7*M10/12 -> 99.5 | AD10: =MAX(J10*Y10/12,0) -> 0 | AE10: =-PMT(Y10/12,360,Z10) -> 3069.4725 | AF10: =SUM(AE10,AC10,AB10,AA10)/(L10/12) -> 0.50780112 | AG10: =SUM(AE10,AC10,AB10,AA10,AD10)/(L10/12) -> 0.50780112 | AH10: =M10*$AH$3 -> 154181.4 | AI10: =Y10+$AI$3 -> 0.0625 | AJ10: =M10-X10-AH10 -> 344338.46 | AK10: =AH10*$AK$3/12 -> 0 | AL10: =AB10 -> 758.05855 | AM10: =AC10 -> 99.5 | AN10: =MAX(J10*Y10/12,0) -> 0 | AO10: =-PMT(AI10/12,360,AJ10) -> 2120.1511 | AP10: =SUM(AO10,AM10,AL10)/(L10/12) -> 0.34263634 | AQ10: =SUM(AO10,AM10,AL10,AK10,AN10)/(L10/12) -> 0.34263634 | AR10: =$AR$3*AK10*12 -> 0 | AS10: =$AS$3*(M10-X10) -> 9970.3972 | AT10: =$AT$3*(AH10) -> 4625.442 | AU10: =$AU$3*SUM(AR10,AS10,AT10) -> 0 | AV10: =AU10/M10 -> 0 | AW10: =POWER(1+K10,10)*M10 -> 837150.85 | AX10: =POWER(1+K10,10)*AH10 -> 251145.25 | AY10: =AX10/AH10 -> 1.6288946 | AZ10: =AW10-AX10-FV(AI10/12,(10*12),AO10,-AJ10) -> 295942.75 | BA10: =AZ10/X10 -> 19.194452 | BE10: =(L10/12)*35% -> 3041.7042 | BF10: =BE10-AC10-AB10-AA10 -> 1698.0888 | BG10: =$Y$3/12 -> 0.0052083333 | BH10: =(BG10*(1+BG10)^360) / (((1+BG10)^360)-1) -> 0.006157172 | BI10: =PV(BG10, 360, -BF10) -> 275790.37 | BK10: =BE10-AB10-AC10 -> 2184.1456 | BL10: =BK10/BH10 -> 354731.95 | BN10: =M10-BI10-X10 -> 222729.49 | BO10: =BN10/M10 -> 0.43337813 | BP10: =M10-BL10-X10 -> 143787.91 | BS10: =B10 -> New Jersey | BT10: =L10 -> 104287 | BU10: =M10 -> 513938 | BV10: =H10 -> 1679 | BW10: =AA10 -> 486.05686 | BX10: =AB10 -> 758.05855 | BY10: =AC10 -> 99.5 | BZ10: =(BT10/12)*$BT$2 -> 3041.7042 | CA10: =BZ10-BW10-BX10-BY10 -> 1698.0888 | CB10: =6.25%/12 -> 0.0052083333 | CC10: =CE10/0.97 -> 284319.97 | CD10: =BU10-CC10 -> 229618.03 | CE10: =PV(CB10,360,-CA10) -> 275790.37 | CG10: =BZ10-BY10-BX10 -> 2184.1456 | CH10: =PV(CB10,360,-CG10) -> 354731.95 | CI10: =BU10*0.03 -> 15418.14 | CJ10: =BU10-CI10-CH10 -> 143787.91 | CK10: =CJ10/BU10 -> 0.27977677 | CM10: =CA10 -> 1698.0888 | CN10: =(CC10*1%)/12 -> 236.93331 | CO10: =CM10+CN10+BX10+BY10 -> 2792.5806 | CP10: =VLOOKUP(BS10,'Paste Snowflake Data Here'!$B$2:$K$21,10,FALSE) -> 1679 | CQ10: =CP10-CO10 -> -1113.5806
B11: New York | D11: =_xlfn.XLOOKUP($B11,'Paste Snowflake Data Here'!$B$3:$B$1048576,'Paste Snowflake Data Here'!$D$3:$D$1048576) -> 19998175 | F11: =_xlfn.XLOOKUP($B11,'Paste Snowflake Data Here'!$B$3:$B$1048576,'Paste Snowflake Data Here'!$I$3:$I$1048576) -> 85744 | G11: =_xlfn.XLOOKUP($B11,'Paste Snowflake Data Here'!$B$3:$B$1048576,'Paste Snowflake Data Here'!$J$3:$J$1048576) -> 485429 | H11: =_xlfn.XLOOKUP($B11,'Paste Snowflake Data Here'!$B$3:$B$1048576,'Paste Snowflake Data Here'!$K$3:$K$1048576) -> 1617 | K11: =IFERROR(VLOOKUP(LEFT(B11,FIND("County",B11)-2),CaseShiller30,5,0)*0.01,$K$3) -> 0.05 | L11: =$F11*$L$3 -> 85744 | M11: =$G11*$M$3 -> 485429 | N11: =AND(AF11<$AF$3,AG11<$AG$3) -> FALSE | O11: =AND(AP11<$AP$3,AQ11<$AQ$3) -> FALSE | P11: =AND(N11=FALSE,O11) -> FALSE | Q11: =AH11 -> 145628.7 | R11: =AU11 -> 0 | S11: =AR11 -> 0 | T11: =AZ11 -> 279526.31 | U11: =BA11 -> 19.194452 | V11: =AX11 -> 237213.81 | W11: =AY11 -> 1.6288946 | X11: =$X$3*M11 -> 14562.87 | Y11: =$Y$3 -> 0.0625 | Z11: =M11-X11 -> 470866.13 | AA11: =Z11*'PMI Rate Est'!$J$6/12 -> 459.09448 | AB11: ='Taxes & Ins by State'!B33*M11/12 -> 509.70045 | AC11: ='Taxes & Ins by State'!M8*M11/12 -> 146 | AD11: =MAX(J11*Y11/12,0) -> 0 | AE11: =-PMT(Y11/12,360,Z11) -> 2899.2038 | AF11: =SUM(AE11,AC11,AB11,AA11)/(L11/12) -> 0.56176507 | AG11: =SUM(AE11,AC11,AB11,AA11,AD11)/(L11/12) -> 0.56176507 | AH11: =M11*$AH$3 -> 145628.7 | AI11: =Y11+$AI$3 -> 0.0625 | AJ11: =M11-X11-AH11 -> 325237.43 | AK11: =AH11*$AK$3/12 -> 0 | AL11: =AB11 -> 509.70045 | AM11: =AC11 -> 146 | AN11: =MAX(J11*Y11/12,0) -> 0 | AO11: =-PMT(AI11/12,360,AJ11) -> 2002.5428 | AP11: =SUM(AO11,AM11,AL11)/(L11/12) -> 0.37202509 | AQ11: =SUM(AO11,AM11,AL11,AK11,AN11)/(L11/12) -> 0.37202509 | AR11: =$AR$3*AK11*12 -> 0 | AS11: =$AS$3*(M11-X11) -> 9417.3226 | AT11: =$AT$3*(AH11) -> 4368.861 | AU11: =$AU$3*SUM(AR11,AS11,AT11) -> 0 | AV11: =AU11/M11 -> 0 | AW11: =POWER(1+K11,10)*M11 -> 790712.69 | AX11: =POWER(1+K11,10)*AH11 -> 237213.81 | AY11: =AX11/AH11 -> 1.6288946 | AZ11: =AW11-AX11-FV(AI11/12,(10*12),AO11,-AJ11) -> 279526.31 | BA11: =AZ11/X11 -> 19.194452 | BE11: =(L11/12)*35% -> 2500.8667 | BF11: =BE11-AC11-AB11-AA11 -> 1386.0717 | BG11: =$Y$3/12 -> 0.0052083333 | BH11: =(BG11*(1+BG11)^360) / (((1+BG11)^360)-1) -> 0.006157172 | BI11: =PV(BG11, 360, -BF11) -> 225114.99 | BK11: =BE11-AB11-AC11 -> 1845.1662 | BL11: =BK11/BH11 -> 299677.55 | BN11: =M11-BI11-X11 -> 245751.14 | BO11: =BN11/M11 -> 0.50625557 | BP11: =M11-BL11-X11 -> 171188.58 | BS11: =B11 -> New York | BT11: =L11 -> 85744 | BU11: =M11 -> 485429 | BV11: =H11 -> 1617 | BW11: =AA11 -> 459.09448 | BX11: =AB11 -> 509.70045 | BY11: =AC11 -> 146 | BZ11: =(BT11/12)*$BT$2 -> 2500.8667 | CA11: =BZ11-BW11-BX11-BY11 -> 1386.0717 | CB11: =6.25%/12 -> 0.0052083333 | CC11: =CE11/0.97 -> 232077.31 | CD11: =BU11-CC11 -> 253351.69 | CE11: =PV(CB11,360,-CA11) -> 225114.99 | CG11: =BZ11-BY11-BX11 -> 1845.1662 | CH11: =PV(CB11,360,-CG11) -> 299677.55 | CI11: =BU11*0.03 -> 14562.87 | CJ11: =BU11-CI11-CH11 -> 171188.58 | CK11: =CJ11/BU11 -> 0.35265421 | CM11: =CA11 -> 1386.0717 | CN11: =(CC11*1%)/12 -> 193.39776 | CO11: =CM11+CN11+BX11+BY11 -> 2235.17 | CP11: =VLOOKUP(BS11,'Paste Snowflake Data Here'!$B$2:$K$21,10,FALSE) -> 1617 | CQ11: =CP11-CO11 -> -618.16995
B12: North Carolina | D12: =_xlfn.XLOOKUP($B12,'Paste Snowflake Data Here'!$B$3:$B$1048576,'Paste Snowflake Data Here'!$D$3:$D$1048576) -> 10995758 | F12: =_xlfn.XLOOKUP($B12,'Paste Snowflake Data Here'!$B$3:$B$1048576,'Paste Snowflake Data Here'!$I$3:$I$1048576) -> 74690 | G12: =_xlfn.XLOOKUP($B12,'Paste Snowflake Data Here'!$B$3:$B$1048576,'Paste Snowflake Data Here'!$J$3:$J$1048576) -> 334561 | H12: =_xlfn.XLOOKUP($B12,'Paste Snowflake Data Here'!$B$3:$B$1048576,'Paste Snowflake Data Here'!$K$3:$K$1048576) -> 1180 | K12: =IFERROR(VLOOKUP(LEFT(B12,FIND("County",B12)-2),CaseShiller30,5,0)*0.01,$K$3) -> 0.05 | L12: =$F12*$L$3 -> 74690 | M12: =$G12*$M$3 -> 334561 | N12: =AND(AF12<$AF$3,AG12<$AG$3) -> FALSE | O12: =AND(AP12<$AP$3,AQ12<$AQ$3) -> TRUE | P12: =AND(N12=FALSE,O12) -> TRUE | Q12: =AH12 -> 100368.3 | R12: =AU12 -> 0 | S12: =AR12 -> 0 | T12: =AZ12 -> 192651.45 | U12: =BA12 -> 19.194452 | V12: =AX12 -> 163489.38 | W12: =AY12 -> 1.6288946 | X12: =$X$3*M12 -> 10036.83 | Y12: =$Y$3 -> 0.0625 | Z12: =M12-X12 -> 324524.17 | AA12: =Z12*'PMI Rate Est'!$J$6/12 -> 316.41107 | AB12: ='Taxes & Ins by State'!B34*M12/12 -> 172.85652 | AC12: ='Taxes & Ins by State'!M9*M12/12 -> 171.25 | AD12: =MAX(J12*Y12/12,0) -> 0 | AE12: =-PMT(Y12/12,360,Z12) -> 1998.1511 | AF12: =SUM(AE12,AC12,AB12,AA12)/(L12/12) -> 0.42715256 | AG12: =SUM(AE12,AC12,AB12,AA12,AD12)/(L12/12) -> 0.42715256 | AH12: =M12*$AH$3 -> 100368.3 | AI12: =Y12+$AI$3 -> 0.0625 | AJ12: =M12-X12-AH12 -> 224155.87 | AK12: =AH12*$AK$3/12 -> 0 | AL12: =AB12 -> 172.85652 | AM12: =AC12 -> 171.25 | AN12: =MAX(J12*Y12/12,0) -> 0 | AO12: =-PMT(AI12/12,360,AJ12) -> 1380.1662 | AP12: =SUM(AO12,AM12,AL12)/(L12/12) -> 0.27702869 | AQ12: =SUM(AO12,AM12,AL12,AK12,AN12)/(L12/12) -> 0.27702869 | AR12: =$AR$3*AK12*12 -> 0 | AS12: =$AS$3*(M12-X12) -> 6490.4834 | AT12: =$AT$3*(AH12) -> 3011.049 | AU12: =$AU$3*SUM(AR12,AS12,AT12) -> 0 | AV12: =AU12/M12 -> 0 | AW12: =POWER(1+K12,10)*M12 -> 544964.62 | AX12: =POWER(1+K12,10)*AH12 -> 163489.38 | AY12: =AX12/AH12 -> 1.6288946 | AZ12: =AW12-AX12-FV(AI12/12,(10*12),AO12,-AJ12) -> 192651.45 | BA12: =AZ12/X12 -> 19.194452 | BE12: =(L12/12)*35% -> 2178.4583 | BF12: =BE12-AC12-AB12-AA12 -> 1517.9408 | BG12: =$Y$3/12 -> 0.0052083333 | BH12: =(BG12*(1+BG12)^360) / (((1+BG12)^360)-1) -> 0.006157172 | BI12: =PV(BG12, 360, -BF12) -> 246532.13 | BK12: =BE12-AB12-AC12 -> 1834.3518 | BL12: =BK12/BH12 -> 297921.16 | BN12: =M12-BI12-X12 -> 77992.036 | BO12: =BN12/M12 -> 0.23311754 | BP12: =M12-BL12-X12 -> 26603.011 | BS12: =B12 -> North Carolina | BT12: =L12 -> 74690 | BU12: =M12 -> 334561 | BV12: =H12 -> 1180 | BW12: =AA12 -> 316.41107 | BX12: =AB12 -> 172.85652 | BY12: =AC12 -> 171.25 | BZ12: =(BT12/12)*$BT$2 -> 2178.4583 | CA12: =BZ12-BW12-BX12-BY12 -> 1517.9408 | CB12: =6.25%/12 -> 0.0052083333 | CC12: =CE12/0.97 -> 254156.84 | CD12: =BU12-CC12 -> 80404.161 | CE12: =PV(CB12,360,-CA12) -> 246532.13 | CG12: =BZ12-BY12-BX12 -> 1834.3518 | CH12: =PV(CB12,360,-CG12) -> 297921.16 | CI12: =BU12*0.03 -> 10036.83 | CJ12: =BU12-CI12-CH12 -> 26603.011 | CK12: =CJ12/BU12 -> 0.079516176 | CM12: =CA12 -> 1517.9408 | CN12: =(CC12*1%)/12 -> 211.79737 | CO12: =CM12+CN12+BX12+BY12 -> 2073.8446 | CP12: =VLOOKUP(BS12,'Paste Snowflake Data Here'!$B$2:$K$21,10,FALSE) -> 1180 | CQ12: =CP12-CO12 -> -893.84463
B13: Oregon | D13: =_xlfn.XLOOKUP($B13,'Paste Snowflake Data Here'!$B$3:$B$1048576,'Paste Snowflake Data Here'!$D$3:$D$1048576) -> 4365325 | F13: =_xlfn.XLOOKUP($B13,'Paste Snowflake Data Here'!$B$3:$B$1048576,'Paste Snowflake Data Here'!$I$3:$I$1048576) -> 84398 | G13: =_xlfn.XLOOKUP($B13,'Paste Snowflake Data Here'!$B$3:$B$1048576,'Paste Snowflake Data Here'!$J$3:$J$1048576) -> 549301 | H13: =_xlfn.XLOOKUP($B13,'Paste Snowflake Data Here'!$B$3:$B$1048576,'Paste Snowflake Data Here'!$K$3:$K$1048576) -> 1477 | K13: =IFERROR(VLOOKUP(LEFT(B13,FIND("County",B13)-2),CaseShiller30,5,0)*0.01,$K$3) -> 0.05 | L13: =$F13*$L$3 -> 84398 | M13: =$G13*$M$3 -> 549301 | N13: =AND(AF13<$AF$3,AG13<$AG$3) -> FALSE | O13: =AND(AP13<$AP$3,AQ13<$AQ$3) -> FALSE | P13: =AND(N13=FALSE,O13) -> FALSE | Q13: =AH13 -> 164790.3 | R13: =AU13 -> 0 | S13: =AR13 -> 0 | T13: =AZ13 -> 316305.95 | U13: =BA13 -> 19.194452 | V13: =AX13 -> 268426.03 | W13: =AY13 -> 1.6288946 | X13: =$X$3*M13 -> 16479.03 | Y13: =$Y$3 -> 0.0625 | Z13: =M13-X13 -> 532821.97 | AA13: =Z13*'PMI Rate Est'!$J$6/12 -> 519.50142 | AB13: ='Taxes & Ins by State'!B38*M13/12 -> 357.04565 | AC13: ='Taxes & Ins by State'!M10*M13/12 -> 84.25 | AD13: =MAX(J13*Y13/12,0) -> 0 | AE13: =-PMT(Y13/12,360,Z13) -> 3280.6765 | AF13: =SUM(AE13,AC13,AB13,AA13)/(L13/12) -> 0.60306741 | AG13: =SUM(AE13,AC13,AB13,AA13,AD13)/(L13/12) -> 0.60306741 | AH13: =M13*$AH$3 -> 164790.3 | AI13: =Y13+$AI$3 -> 0.0625 | AJ13: =M13-X13-AH13 -> 368031.67 | AK13: =AH13*$AK$3/12 -> 0 | AL13: =AB13 -> 357.04565 | AM13: =AC13 -> 84.25 | AN13: =MAX(J13*Y13/12,0) -> 0 | AO13: =-PMT(AI13/12,360,AJ13) -> 2266.0343 | AP13: =SUM(AO13,AM13,AL13)/(L13/12) -> 0.38493755 | AQ13: =SUM(AO13,AM13,AL13,AK13,AN13)/(L13/12) -> 0.38493755 | AR13: =$AR$3*AK13*12 -> 0 | AS13: =$AS$3*(M13-X13) -> 10656.439 | AT13: =$AT$3*(AH13) -> 4943.709 | AU13: =$AU$3*SUM(AR13,AS13,AT13) -> 0 | AV13: =AU13/M13 -> 0 | AW13: =POWER(1+K13,10)*M13 -> 894753.45 | AX13: =POWER(1+K13,10)*AH13 -> 268426.03 | AY13: =AX13/AH13 -> 1.6288946 | AZ13: =AW13-AX13-FV(AI13/12,(10*12),AO13,-AJ13) -> 316305.95 | BA13: =AZ13/X13 -> 19.194452 | BE13: =(L13/12)*35% -> 2461.6083 | BF13: =BE13-AC13-AB13-AA13 -> 1500.8113 | BG13: =$Y$3/12 -> 0.0052083333 | BH13: =(BG13*(1+BG13)^360) / (((1+BG13)^360)-1) -> 0.006157172 | BI13: =PV(BG13, 360, -BF13) -> 243750.1 | BK13: =BE13-AB13-AC13 -> 2020.3127 | BL13: =BK13/BH13 -> 328123.48 | BN13: =M13-BI13-X13 -> 289071.87 | BO13: =BN13/M13 -> 0.52625405 | BP13: =M13-BL13-X13 -> 204698.49 | BS13: =B13 -> Oregon | BT13: =L13 -> 84398 | BU13: =M13 -> 549301 | BV13: =H13 -> 1477 | BW13: =AA13 -> 519.50142 | BX13: =AB13 -> 357.04565 | BY13: =AC13 -> 84.25 | BZ13: =(BT13/12)*$BT$2 -> 2461.6083 | CA13: =BZ13-BW13-BX13-BY13 -> 1500.8113 | CB13: =6.25%/12 -> 0.0052083333 | CC13: =CE13/0.97 -> 251288.76 | CD13: =BU13-CC13 -> 298012.24 | CE13: =PV(CB13,360,-CA13) -> 243750.1 | CG13: =BZ13-BY13-BX13 -> 2020.3127 | CH13: =PV(CB13,360,-CG13) -> 328123.48 | CI13: =BU13*0.03 -> 16479.03 | CJ13: =BU13-CI13-CH13 -> 204698.49 | CK13: =CJ13/BU13 -> 0.37265269 | CM13: =CA13 -> 1500.8113 | CN13: =(CC13*1%)/12 -> 209.4073 | CO13: =CM13+CN13+BX13+BY13 -> 2151.5142 | CP13: =VLOOKUP(BS13,'Paste Snowflake Data Here'!$B$2:$K$21,10,FALSE) -> 1477 | CQ13: =CP13-CO13 -> -674.51421
B14: Pennsylvania | D14: =_xlfn.XLOOKUP($B14,'Paste Snowflake Data Here'!$B$3:$B$1048576,'Paste Snowflake Data Here'!$D$3:$D$1048576) -> 13074028 | F14: =_xlfn.XLOOKUP($B14,'Paste Snowflake Data Here'!$B$3:$B$1048576,'Paste Snowflake Data Here'!$I$3:$I$1048576) -> 77579 | G14: =_xlfn.XLOOKUP($B14,'Paste Snowflake Data Here'!$B$3:$B$1048576,'Paste Snowflake Data Here'!$J$3:$J$1048576) -> 303362 | H14: =_xlfn.XLOOKUP($B14,'Paste Snowflake Data Here'!$B$3:$B$1048576,'Paste Snowflake Data Here'!$K$3:$K$1048576) -> 1159 | K14: =IFERROR(VLOOKUP(LEFT(B14,FIND("County",B14)-2),CaseShiller30,5,0)*0.01,$K$3) -> 0.05 | L14: =$F14*$L$3 -> 77579 | M14: =$G14*$M$3 -> 303362 | N14: =AND(AF14<$AF$3,AG14<$AG$3) -> FALSE | O14: =AND(AP14<$AP$3,AQ14<$AQ$3) -> TRUE | P14: =AND(N14=FALSE,O14) -> TRUE | Q14: =AH14 -> 91008.6 | R14: =AU14 -> 0 | S14: =AR14 -> 0 | T14: =AZ14 -> 174686.02 | U14: =BA14 -> 19.194452 | V14: =AX14 -> 148243.42 | W14: =AY14 -> 1.6288946 | X14: =$X$3*M14 -> 9100.86 | Y14: =$Y$3 -> 0.0625 | Z14: =M14-X14 -> 294261.14 | AA14: =Z14*'PMI Rate Est'!$J$6/12 -> 286.90461 | AB14: ='Taxes & Ins by State'!B39*M14/12 -> 300.83398 | AC14: ='Taxes & Ins by State'!M11*M14/12 -> 103.75 | AD14: =MAX(J14*Y14/12,0) -> 0 | AE14: =-PMT(Y14/12,360,Z14) -> 1811.8165 | AF14: =SUM(AE14,AC14,AB14,AA14)/(L14/12) -> 0.38721382 | AG14: =SUM(AE14,AC14,AB14,AA14,AD14)/(L14/12) -> 0.38721382 | AH14: =M14*$AH$3 -> 91008.6 | AI14: =Y14+$AI$3 -> 0.0625 | AJ14: =M14-X14-AH14 -> 203252.54 | AK14: =AH14*$AK$3/12 -> 0 | AL14: =AB14 -> 300.83398 | AM14: =AC14 -> 103.75 | AN14: =MAX(J14*Y14/12,0) -> 0 | AO14: =-PMT(AI14/12,360,AJ14) -> 1251.4608 | AP14: =SUM(AO14,AM14,AL14)/(L14/12) -> 0.25615873 | AQ14: =SUM(AO14,AM14,AL14,AK14,AN14)/(L14/12) -> 0.25615873 | AR14: =$AR$3*AK14*12 -> 0 | AS14: =$AS$3*(M14-X14) -> 5885.2228 | AT14: =$AT$3*(AH14) -> 2730.258 | AU14: =$AU$3*SUM(AR14,AS14,AT14) -> 0 | AV14: =AU14/M14 -> 0 | AW14: =POWER(1+K14,10)*M14 -> 494144.73 | AX14: =POWER(1+K14,10)*AH14 -> 148243.42 | AY14: =AX14/AH14 -> 1.6288946 | AZ14: =AW14-AX14-FV(AI14/12,(10*12),AO14,-AJ14) -> 174686.02 | BA14: =AZ14/X14 -> 19.194452 | BE14: =(L14/12)*35% -> 2262.7208 | BF14: =BE14-AC14-AB14-AA14 -> 1571.2322 | BG14: =$Y$3/12 -> 0.0052083333 | BH14: =(BG14*(1+BG14)^360) / (((1+BG14)^360)-1) -> 0.006157172 | BI14: =PV(BG14, 360, -BF14) -> 255187.32 | BK14: =BE14-AB14-AC14 -> 1858.1368 | BL14: =BK14/BH14 -> 301784.14 | BN14: =M14-BI14-X14 -> 39073.817 | BO14: =BN14/M14 -> 0.12880261 | BP14: =M14-BL14-X14 -> -7522.9987 | BS14: =B14 -> Pennsylvania | BT14: =L14 -> 77579 | BU14: =M14 -> 303362 | BV14: =H14 -> 1159 | BW14: =AA14 -> 286.90461 | BX14: =AB14 -> 300.83398 | BY14: =AC14 -> 103.75 | BZ14: =(BT14/12)*$BT$2 -> 2262.7208 | CA14: =BZ14-BW14-BX14-BY14 -> 1571.2322 | CB14: =6.25%/12 -> 0.0052083333 | CC14: =CE14/0.97 -> 263079.71 | CD14: =BU14-CC14 -> 40282.286 | CE14: =PV(CB14,360,-CA14) -> 255187.32 | CG14: =BZ14-BY14-BX14 -> 1858.1368 | CH14: =PV(CB14,360,-CG14) -> 301784.14 | CI14: =BU14*0.03 -> 9100.86 | CJ14: =BU14-CI14-CH14 -> -7522.9987 | CK14: =CJ14/BU14 -> -0.024798751 | CM14: =CA14 -> 1571.2322 | CN14: =(CC14*1%)/12 -> 219.2331 | CO14: =CM14+CN14+BX14+BY14 -> 2195.0493 | CP14: =VLOOKUP(BS14,'Paste Snowflake Data Here'!$B$2:$K$21,10,FALSE) -> 1159 | CQ14: =CP14-CO14 -> -1036.0493
B15: Rhode Island | D15: =_xlfn.XLOOKUP($B15,'Paste Snowflake Data Here'!$B$3:$B$1048576,'Paste Snowflake Data Here'!$D$3:$D$1048576) -> 1101918 | F15: =_xlfn.XLOOKUP($B15,'Paste Snowflake Data Here'!$B$3:$B$1048576,'Paste Snowflake Data Here'!$I$3:$I$1048576) -> 88514 | G15: =_xlfn.XLOOKUP($B15,'Paste Snowflake Data Here'!$B$3:$B$1048576,'Paste Snowflake Data Here'!$J$3:$J$1048576) -> 447602 | H15: =_xlfn.XLOOKUP($B15,'Paste Snowflake Data Here'!$B$3:$B$1048576,'Paste Snowflake Data Here'!$K$3:$K$1048576) -> 1303 | K15: =IFERROR(VLOOKUP(LEFT(B15,FIND("County",B15)-2),CaseShiller30,5,0)*0.01,$K$3) -> 0.05 | L15: =$F15*$L$3 -> 88514 | M15: =$G15*$M$3 -> 447602 | N15: =AND(AF15<$AF$3,AG15<$AG$3) -> FALSE | O15: =AND(AP15<$AP$3,AQ15<$AQ$3) -> TRUE | P15: =AND(N15=FALSE,O15) -> TRUE | Q15: =AH15 -> 134280.6 | R15: =AU15 -> 0 | S15: =AR15 -> 0 | T15: =AZ15 -> 257744.25 | U15: =BA15 -> 19.194452 | V15: =AX15 -> 218728.95 | W15: =AY15 -> 1.6288946 | X15: =$X$3*M15 -> 13428.06 | Y15: =$Y$3 -> 0.0625 | Z15: =M15-X15 -> 434173.94 | AA15: =Z15*'PMI Rate Est'!$J$6/12 -> 423.31959 | AB15: ='Taxes & Ins by State'!B40*M15/12 -> 391.65175 | AC15: ='Taxes & Ins by State'!M12*M15/12 -> 193.66667 | AD15: =MAX(J15*Y15/12,0) -> 0 | AE15: =-PMT(Y15/12,360,Z15) -> 2673.2836 | AF15: =SUM(AE15,AC15,AB15,AA15)/(L15/12) -> 0.49916465 | AG15: =SUM(AE15,AC15,AB15,AA15,AD15)/(L15/12) -> 0.49916465 | AH15: =M15*$AH$3 -> 134280.6 | AI15: =Y15+$AI$3 -> 0.0625 | AJ15: =M15-X15-AH15 -> 299893.34 | AK15: =AH15*$AK$3/12 -> 0 | AL15: =AB15 -> 391.65175 | AM15: =AC15 -> 193.66667 | AN15: =MAX(J15*Y15/12,0) -> 0 | AO15: =-PMT(AI15/12,360,AJ15) -> 1846.4949 | AP15: =SUM(AO15,AM15,AL15)/(L15/12) -> 0.32968524 | AQ15: =SUM(AO15,AM15,AL15,AK15,AN15)/(L15/12) -> 0.32968524 | AR15: =$AR$3*AK15*12 -> 0 | AS15: =$AS$3*(M15-X15) -> 8683.4788 | AT15: =$AT$3*(AH15) -> 4028.418 | AU15: =$AU$3*SUM(AR15,AS15,AT15) -> 0 | AV15: =AU15/M15 -> 0 | AW15: =POWER(1+K15,10)*M15 -> 729096.49 | AX15: =POWER(1+K15,10)*AH15 -> 218728.95 | AY15: =AX15/AH15 -> 1.6288946 | AZ15: =AW15-AX15-FV(AI15/12,(10*12),AO15,-AJ15) -> 257744.25 | BA15: =AZ15/X15 -> 19.194452 | BE15: =(L15/12)*35% -> 2581.6583 | BF15: =BE15-AC15-AB15-AA15 -> 1573.0203 | BG15: =$Y$3/12 -> 0.0052083333 | BH15: =(BG15*(1+BG15)^360) / (((1+BG15)^360)-1) -> 0.006157172 | BI15: =PV(BG15, 360, -BF15) -> 255477.73 | BK15: =BE15-AB15-AC15 -> 1996.3399 | BL15: =BK15/BH15 -> 324230.01 | BN15: =M15-BI15-X15 -> 178696.21 | BO15: =BN15/M15 -> 0.39923014 | BP15: =M15-BL15-X15 -> 109943.93 | BS15: =B15 -> Rhode Island | BT15: =L15 -> 88514 | BU15: =M15 -> 447602 | BV15: =H15 -> 1303 | BW15: =AA15 -> 423.31959 | BX15: =AB15 -> 391.65175 | BY15: =AC15 -> 193.66667 | BZ15: =(BT15/12)*$BT$2 -> 2581.6583 | CA15: =BZ15-BW15-BX15-BY15 -> 1573.0203 | CB15: =6.25%/12 -> 0.0052083333 | CC15: =CE15/0.97 -> 263379.1 | CD15: =BU15-CC15 -> 184222.9 | CE15: =PV(CB15,360,-CA15) -> 255477.73 | CG15: =BZ15-BY15-BX15 -> 1996.3399 | CH15: =PV(CB15,360,-CG15) -> 324230.01 | CI15: =BU15*0.03 -> 13428.06 | CJ15: =BU15-CI15-CH15 -> 109943.93 | CK15: =CJ15/BU15 -> 0.24562878 | CM15: =CA15 -> 1573.0203 | CN15: =(CC15*1%)/12 -> 219.48259 | CO15: =CM15+CN15+BX15+BY15 -> 2377.8213 | CP15: =VLOOKUP(BS15,'Paste Snowflake Data Here'!$B$2:$K$21,10,FALSE) -> 1303 | CQ15: =CP15-CO15 -> -1074.8213
B16: Washington | D16: =_xlfn.XLOOKUP($B16,'Paste Snowflake Data Here'!$B$3:$B$1048576,'Paste Snowflake Data Here'!$D$3:$D$1048576) -> 8076991 | F16: =_xlfn.XLOOKUP($B16,'Paste Snowflake Data Here'!$B$3:$B$1048576,'Paste Snowflake Data Here'!$I$3:$I$1048576) -> 100361 | G16: =_xlfn.XLOOKUP($B16,'Paste Snowflake Data Here'!$B$3:$B$1048576,'Paste Snowflake Data Here'!$J$3:$J$1048576) -> 641336 | H16: =_xlfn.XLOOKUP($B16,'Paste Snowflake Data Here'!$B$3:$B$1048576,'Paste Snowflake Data Here'!$K$3:$K$1048576) -> 1701 | K16: =IFERROR(VLOOKUP(LEFT(B16,FIND("County",B16)-2),CaseShiller30,5,0)*0.01,$K$3) -> 0.05 | L16: =$F16*$L$3 -> 100361 | M16: =$G16*$M$3 -> 641336 | N16: =AND(AF16<$AF$3,AG16<$AG$3) -> FALSE | O16: =AND(AP16<$AP$3,AQ16<$AQ$3) -> FALSE | P16: =AND(N16=FALSE,O16) -> FALSE | Q16: =AH16 -> 192400.8 | R16: =AU16 -> 0 | S16: =AR16 -> 0 | T16: =AZ16 -> 369302.79 | U16: =BA16 -> 19.194452 | V16: =AX16 -> 313400.63 | W16: =AY16 -> 1.6288946 | X16: =$X$3*M16 -> 19240.08 | Y16: =$Y$3 -> 0.0625 | Z16: =M16-X16 -> 622095.92 | AA16: =Z16*'PMI Rate Est'!$J$6/12 -> 606.54352 | AB16: ='Taxes & Ins by State'!B48*M16/12 -> 400.835 | AC16: ='Taxes & Ins by State'!M13*M16/12 -> 126.08333 | AD16: =MAX(J16*Y16/12,0) -> 0 | AE16: =-PMT(Y16/12,360,Z16) -> 3830.3516 | AF16: =SUM(AE16,AC16,AB16,AA16)/(L16/12) -> 0.59351502 | AG16: =SUM(AE16,AC16,AB16,AA16,AD16)/(L16/12) -> 0.59351502 | AH16: =M16*$AH$3 -> 192400.8 | AI16: =Y16+$AI$3 -> 0.0625 | AJ16: =M16-X16-AH16 -> 429695.12 | AK16: =AH16*$AK$3/12 -> 0 | AL16: =AB16 -> 400.835 | AM16: =AC16 -> 126.08333 | AN16: =MAX(J16*Y16/12,0) -> 0 | AO16: =-PMT(AI16/12,360,AJ16) -> 2645.7068 | AP16: =SUM(AO16,AM16,AL16)/(L16/12) -> 0.37934557 | AQ16: =SUM(AO16,AM16,AL16,AK16,AN16)/(L16/12) -> 0.37934557 | AR16: =$AR$3*AK16*12 -> 0 | AS16: =$AS$3*(M16-X16) -> 12441.918 | AT16: =$AT$3*(AH16) -> 5772.024 | AU16: =$AU$3*SUM(AR16,AS16,AT16) -> 0 | AV16: =AU16/M16 -> 0 | AW16: =POWER(1+K16,10)*M16 -> 1044668.8 | AX16: =POWER(1+K16,10)*AH16 -> 313400.63 | AY16: =AX16/AH16 -> 1.6288946 | AZ16: =AW16-AX16-FV(AI16/12,(10*12),AO16,-AJ16) -> 369302.79 | BA16: =AZ16/X16 -> 19.194452 | BE16: =(L16/12)*35% -> 2927.1958 | BF16: =BE16-AC16-AB16-AA16 -> 1793.734 | BG16: =$Y$3/12 -> 0.0052083333 | BH16: =(BG16*(1+BG16)^360) / (((1+BG16)^360)-1) -> 0.006157172 | BI16: =PV(BG16, 360, -BF16) -> 291324.32 | BK16: =BE16-AB16-AC16 -> 2400.2775 | BL16: =BK16/BH16 -> 389834.41 | BN16: =M16-BI16-X16 -> 330771.6 | BO16: =BN16/M16 -> 0.51575398 | BP16: =M16-BL16-X16 -> 232261.51 | BS16: =B16 -> Washington | BT16: =L16 -> 100361 | BU16: =M16 -> 641336 | BV16: =H16 -> 1701 | BW16: =AA16 -> 606.54352 | BX16: =AB16 -> 400.835 | BY16: =AC16 -> 126.08333 | BZ16: =(BT16/12)*$BT$2 -> 2927.1958 | CA16: =BZ16-BW16-BX16-BY16 -> 1793.734 | CB16: =6.25%/12 -> 0.0052083333 | CC16: =CE16/0.97 -> 300334.36 | CD16: =BU16-CC16 -> 341001.64 | CE16: =PV(CB16,360,-CA16) -> 291324.32 | CG16: =BZ16-BY16-BX16 -> 2400.2775 | CH16: =PV(CB16,360,-CG16) -> 389834.41 | CI16: =BU16*0.03 -> 19240.08 | CJ16: =BU16-CI16-CH16 -> 232261.51 | CK16: =CJ16/BU16 -> 0.36215262 | CM16: =CA16 -> 1793.734 | CN16: =(CC16*1%)/12 -> 250.27863 | CO16: =CM16+CN16+BX16+BY16 -> 2570.9309 | CP16: =VLOOKUP(BS16,'Paste Snowflake Data Here'!$B$2:$K$21,10,FALSE) -> 1701 | CQ16: =CP16-CO16 -> -869.93094
B17: Arizona | D17: =_xlfn.XLOOKUP($B17,'Paste Snowflake Data Here'!$B$3:$B$1048576,'Paste Snowflake Data Here'!$D$3:$D$1048576) -> 7598046 | F17: =_xlfn.XLOOKUP($B17,'Paste Snowflake Data Here'!$B$3:$B$1048576,'Paste Snowflake Data Here'!$I$3:$I$1048576) -> 82768 | G17: =_xlfn.XLOOKUP($B17,'Paste Snowflake Data Here'!$B$3:$B$1048576,'Paste Snowflake Data Here'!$J$3:$J$1048576) -> 429848 | H17: =_xlfn.XLOOKUP($B17,'Paste Snowflake Data Here'!$B$3:$B$1048576,'Paste Snowflake Data Here'!$K$3:$K$1048576) -> 1509 | K17: =IFERROR(VLOOKUP(LEFT(B17,FIND("County",B17)-2),CaseShiller30,5,0)*0.01,$K$3) -> 0.05 | L17: =$F17*$L$3 -> 82768 | M17: =$G17*$M$3 -> 429848 | N17: =AND(AF17<$AF$3,AG17<$AG$3) -> FALSE | O17: =AND(AP17<$AP$3,AQ17<$AQ$3) -> TRUE | P17: =AND(N17=FALSE,O17) -> TRUE | Q17: =AH17 -> 128954.4 | R17: =AU17 -> 0 | S17: =AR17 -> 0 | T17: =AZ17 -> 247520.91 | U17: =BA17 -> 19.194452 | V17: =AX17 -> 210053.13 | W17: =AY17 -> 1.6288946 | X17: =$X$3*M17 -> 12895.44 | Y17: =$Y$3 -> 0.0625 | Z17: =M17-X17 -> 416952.56 | AA17: =Z17*'PMI Rate Est'!$J$6/12 -> 406.52875 | AB17: ='Taxes & Ins by State'!B4*M17/12 -> 157.61093 | AC17: ='Taxes & Ins by State'!M14*M17/12 -> 187.08333 | AD17: =MAX(J17*Y17/12,0) -> 0 | AE17: =-PMT(Y17/12,360,Z17) -> 2567.2486 | AF17: =SUM(AE17,AC17,AB17,AA17)/(L17/12) -> 0.48112386 | AG17: =SUM(AE17,AC17,AB17,AA17,AD17)/(L17/12) -> 0.48112386 | AH17: =M17*$AH$3 -> 128954.4 | AI17: =Y17+$AI$3 -> 0.0625 | AJ17: =M17-X17-AH17 -> 287998.16 | AK17: =AH17*$AK$3/12 -> 0 | AL17: =AB17 -> 157.61093 | AM17: =AC17 -> 187.08333 | AN17: =MAX(J17*Y17/12,0) -> 0 | AO17: =-PMT(AI17/12,360,AJ17) -> 1773.2542 | AP17: =SUM(AO17,AM17,AL17)/(L17/12) -> 0.30706773 | AQ17: =SUM(AO17,AM17,AL17,AK17,AN17)/(L17/12) -> 0.30706773 | AR17: =$AR$3*AK17*12 -> 0 | AS17: =$AS$3*(M17-X17) -> 8339.0512 | AT17: =$AT$3*(AH17) -> 3868.632 | AU17: =$AU$3*SUM(AR17,AS17,AT17) -> 0 | AV17: =AU17/M17 -> 0 | AW17: =POWER(1+K17,10)*M17 -> 700177.1 | AX17: =POWER(1+K17,10)*AH17 -> 210053.13 | AY17: =AX17/AH17 -> 1.6288946 | AZ17: =AW17-AX17-FV(AI17/12,(10*12),AO17,-AJ17) -> 247520.91 | BA17: =AZ17/X17 -> 19.194452 | BE17: =(L17/12)*35% -> 2414.0667 | BF17: =BE17-AC17-AB17-AA17 -> 1662.8437 | BG17: =$Y$3/12 -> 0.0052083333 | BH17: =(BG17*(1+BG17)^360) / (((1+BG17)^360)-1) -> 0.006157172 | BI17: =PV(BG17, 360, -BF17) -> 270066.14 | BK17: =BE17-AB17-AC17 -> 2069.3724 | BL17: =BK17/BH17 -> 336091.37 | BN17: =M17-BI17-X17 -> 146886.42 | BO17: =BN17/M17 -> 0.34171713 | BP17: =M17-BL17-X17 -> 80861.186 | BS17: =B17 -> Arizona | BT17: =L17 -> 82768 | BU17: =M17 -> 429848 | BV17: =H17 -> 1509 | BW17: =AA17 -> 406.52875 | BX17: =AB17 -> 157.61093 | BY17: =AC17 -> 187.08333 | BZ17: =(BT17/12)*$BT$2 -> 2414.0667 | CA17: =BZ17-BW17-BX17-BY17 -> 1662.8437 | CB17: =6.25%/12 -> 0.0052083333 | CC17: =CE17/0.97 -> 278418.7 | CD17: =BU17-CC17 -> 151429.3 | CE17: =PV(CB17,360,-CA17) -> 270066.14 | CG17: =BZ17-BY17-BX17 -> 2069.3724 | CH17: =PV(CB17,360,-CG17) -> 336091.37 | CI17: =BU17*0.03 -> 12895.44 | CJ17: =BU17-CI17-CH17 -> 80861.186 | CK17: =CJ17/BU17 -> 0.18811577 | CM17: =CA17 -> 1662.8437 | CN17: =(CC17*1%)/12 -> 232.01558 | CO17: =CM17+CN17+BX17+BY17 -> 2239.5535 | CP17: =VLOOKUP(BS17,'Paste Snowflake Data Here'!$B$2:$K$21,10,FALSE) -> 1509 | CQ17: =CP17-CO17 -> -730.5535
B18: Kansas | D18: =_xlfn.XLOOKUP($B18,'Paste Snowflake Data Here'!$B$3:$B$1048576,'Paste Snowflake Data Here'!$D$3:$D$1048576) -> 2967337 | F18: =_xlfn.XLOOKUP($B18,'Paste Snowflake Data Here'!$B$3:$B$1048576,'Paste Snowflake Data Here'!$I$3:$I$1048576) -> 72975 | G18: =_xlfn.XLOOKUP($B18,'Paste Snowflake Data Here'!$B$3:$B$1048576,'Paste Snowflake Data Here'!$J$3:$J$1048576) -> 243477 | H18: =_xlfn.XLOOKUP($B18,'Paste Snowflake Data Here'!$B$3:$B$1048576,'Paste Snowflake Data Here'!$K$3:$K$1048576) -> 899 | K18: =IFERROR(VLOOKUP(LEFT(B18,FIND("County",B18)-2),CaseShiller30,5,0)*0.01,$K$3) -> 0.05 | L18: =$F18*$L$3 -> 72975 | M18: =$G18*$M$3 -> 243477 | N18: =AND(AF18<$AF$3,AG18<$AG$3) -> FALSE | O18: =AND(AP18<$AP$3,AQ18<$AQ$3) -> TRUE | P18: =AND(N18=FALSE,O18) -> TRUE | Q18: =AH18 -> 73043.1 | R18: =AU18 -> 0 | S18: =AR18 -> 0 | T18: =AZ18 -> 140202.23 | U18: =BA18 -> 19.194452 | V18: =AX18 -> 118979.51 | W18: =AY18 -> 1.6288946 | X18: =$X$3*M18 -> 7304.31 | Y18: =$Y$3 -> 0.0625 | Z18: =M18-X18 -> 236172.69 | AA18: =Z18*'PMI Rate Est'!$J$6/12 -> 230.26837 | AB18: ='Taxes & Ins by State'!B17*M18/12 -> 241.44803 | AC18: ='Taxes & Ins by State'!M17*M18/12 -> 357.25 | AD18: =MAX(J18*Y18/12,0) -> 0 | AE18: =-PMT(Y18/12,360,Z18) -> 1454.1559 | AF18: =SUM(AE18,AC18,AB18,AA18)/(L18/12) -> 0.37543634 | AG18: =SUM(AE18,AC18,AB18,AA18,AD18)/(L18/12) -> 0.37543634 | AH18: =M18*$AH$3 -> 73043.1 | AI18: =Y18+$AI$3 -> 0.0625 | AJ18: =M18-X18-AH18 -> 163129.59 | AK18: =AH18*$AK$3/12 -> 0 | AL18: =AB18 -> 241.44803 | AM18: =AC18 -> 357.25 | AN18: =MAX(J18*Y18/12,0) -> 0 | AO18: =-PMT(AI18/12,360,AJ18) -> 1004.4169 | AP18: =SUM(AO18,AM18,AL18)/(L18/12) -> 0.26361603 | AQ18: =SUM(AO18,AM18,AL18,AK18,AN18)/(L18/12) -> 0.26361603 | AR18: =$AR$3*AK18*12 -> 0 | AS18: =$AS$3*(M18-X18) -> 4723.4538 | AT18: =$AT$3*(AH18) -> 2191.293 | AU18: =$AU$3*SUM(AR18,AS18,AT18) -> 0 | AV18: =AU18/M18 -> 0 | AW18: =POWER(1+K18,10)*M18 -> 396598.38 | AX18: =POWER(1+K18,10)*AH18 -> 118979.51 | AY18: =AX18/AH18 -> 1.6288946 | AZ18: =AW18-AX18-FV(AI18/12,(10*12),AO18,-AJ18) -> 140202.23 | BA18: =AZ18/X18 -> 19.194452 | BE18: =(L18/12)*35% -> 2128.4375 | BF18: =BE18-AC18-AB18-AA18 -> 1299.4711 | BG18: =$Y$3/12 -> 0.0052083333 | BH18: =(BG18*(1+BG18)^360) / (((1+BG18)^360)-1) -> 0.006157172 | BI18: =PV(BG18, 360, -BF18) -> 211049.99 | BK18: =BE18-AB18-AC18 -> 1529.7395 | BL18: =BK18/BH18 -> 248448.39 | BN18: =M18-BI18-X18 -> 25122.698 | BO18: =BN18/M18 -> 0.10318304 | BP18: =M18-BL18-X18 -> -12275.701 | BS18: =B18 -> Kansas | BT18: =L18 -> 72975 | BU18: =M18 -> 243477 | BV18: =H18 -> 899 | BW18: =AA18 -> 230.26837 | BX18: =AB18 -> 241.44803 | BY18: =AC18 -> 357.25 | BZ18: =(BT18/12)*$BT$2 -> 2128.4375 | CA18: =BZ18-BW18-BX18-BY18 -> 1299.4711 | CB18: =6.25%/12 -> 0.0052083333 | CC18: =CE18/0.97 -> 217577.31 | CD18: =BU18-CC18 -> 25899.689 | CE18: =PV(CB18,360,-CA18) -> 211049.99 | CG18: =BZ18-BY18-BX18 -> 1529.7395 | CH18: =PV(CB18,360,-CG18) -> 248448.39 | CI18: =BU18*0.03 -> 7304.31 | CJ18: =BU18-CI18-CH18 -> -12275.701 | CK18: =CJ18/BU18 -> -0.050418317 | CM18: =CA18 -> 1299.4711 | CN18: =(CC18*1%)/12 -> 181.31443 | CO18: =CM18+CN18+BX18+BY18 -> 2079.4836 | CP18: =VLOOKUP(BS18,'Paste Snowflake Data Here'!$B$2:$K$21,10,FALSE) -> 899 | CQ18: =CP18-CO18 -> -1180.4836
B19: Michigan | D19: =_xlfn.XLOOKUP($B19,'Paste Snowflake Data Here'!$B$3:$B$1048576,'Paste Snowflake Data Here'!$D$3:$D$1048576) -> 10042188 | F19: =_xlfn.XLOOKUP($B19,'Paste Snowflake Data Here'!$B$3:$B$1048576,'Paste Snowflake Data Here'!$I$3:$I$1048576) -> 72645 | G19: =_xlfn.XLOOKUP($B19,'Paste Snowflake Data Here'!$B$3:$B$1048576,'Paste Snowflake Data Here'!$J$3:$J$1048576) -> 259246 | H19: =_xlfn.XLOOKUP($B19,'Paste Snowflake Data Here'!$B$3:$B$1048576,'Paste Snowflake Data Here'!$K$3:$K$1048576) -> 1004 | K19: =IFERROR(VLOOKUP(LEFT(B19,FIND("County",B19)-2),CaseShiller30,5,0)*0.01,$K$3) -> 0.05 | L19: =$F19*$L$3 -> 72645 | M19: =$G19*$M$3 -> 259246 | N19: =AND(AF19<$AF$3,AG19<$AG$3) -> FALSE | O19: =AND(AP19<$AP$3,AQ19<$AQ$3) -> TRUE | P19: =AND(N19=FALSE,O19) -> TRUE | Q19: =AH19 -> 77773.8 | R19: =AU19 -> 0 | S19: =AR19 -> 0 | T19: =AZ19 -> 149282.55 | U19: =BA19 -> 19.194452 | V19: =AX19 -> 126685.32 | W19: =AY19 -> 1.6288946 | X19: =$X$3*M19 -> 7777.38 | Y19: =$Y$3 -> 0.0625 | Z19: =M19-X19 -> 251468.62 | AA19: =Z19*'PMI Rate Est'!$J$6/12 -> 245.1819 | AB19: ='Taxes & Ins by State'!B23*M19/12 -> 248.44408 | AC19: ='Taxes & Ins by State'!M19*M19/12 -> 176.41667 | AD19: =MAX(J19*Y19/12,0) -> 0 | AE19: =-PMT(Y19/12,360,Z19) -> 1548.3355 | AF19: =SUM(AE19,AC19,AB19,AA19)/(L19/12) -> 0.36644695 | AG19: =SUM(AE19,AC19,AB19,AA19,AD19)/(L19/12) -> 0.36644695 | AH19: =M19*$AH$3 -> 77773.8 | AI19: =Y19+$AI$3 -> 0.0625 | AJ19: =M19-X19-AH19 -> 173694.82 | AK19: =AH19*$AK$3/12 -> 0 | AL19: =AB19 -> 248.44408 | AM19: =AC19 -> 176.41667 | AN19: =MAX(J19*Y19/12,0) -> 0 | AO19: =-PMT(AI19/12,360,AJ19) -> 1069.4689 | AP19: =SUM(AO19,AM19,AL19)/(L19/12) -> 0.24684363 | AQ19: =SUM(AO19,AM19,AL19,AK19,AN19)/(L19/12) -> 0.24684363 | AR19: =$AR$3*AK19*12 -> 0 | AS19: =$AS$3*(M19-X19) -> 5029.3724 | AT19: =$AT$3*(AH19) -> 2333.214 | AU19: =$AU$3*SUM(AR19,AS19,AT19) -> 0 | AV19: =AU19/M19 -> 0 | AW19: =POWER(1+K19,10)*M19 -> 422284.42 | AX19: =POWER(1+K19,10)*AH19 -> 126685.32 | AY19: =AX19/AH19 -> 1.6288946 | AZ19: =AW19-AX19-FV(AI19/12,(10*12),AO19,-AJ19) -> 149282.55 | BA19: =AZ19/X19 -> 19.194452 | BE19: =(L19/12)*35% -> 2118.8125 | BF19: =BE19-AC19-AB19-AA19 -> 1448.7698 | BG19: =$Y$3/12 -> 0.0052083333 | BH19: =(BG19*(1+BG19)^360) / (((1+BG19)^360)-1) -> 0.006157172 | BI19: =PV(BG19, 360, -BF19) -> 235297.93 | BK19: =BE19-AB19-AC19 -> 1693.9517 | BL19: =BK19/BH19 -> 275118.47 | BN19: =M19-BI19-X19 -> 16170.687 | BO19: =BN19/M19 -> 0.06237584 | BP19: =M19-BL19-X19 -> -23649.851 | BS19: =B19 -> Michigan | BT19: =L19 -> 72645 | BU19: =M19 -> 259246 | BV19: =H19 -> 1004 | BW19: =AA19 -> 245.1819 | BX19: =AB19 -> 248.44408 | BY19: =AC19 -> 176.41667 | BZ19: =(BT19/12)*$BT$2 -> 2118.8125 | CA19: =BZ19-BW19-BX19-BY19 -> 1448.7698 | CB19: =6.25%/12 -> 0.0052083333 | CC19: =CE19/0.97 -> 242575.19 | CD19: =BU19-CC19 -> 16670.811 | CE19: =PV(CB19,360,-CA19) -> 235297.93 | CG19: =BZ19-BY19-BX19 -> 1693.9517 | CH19: =PV(CB19,360,-CG19) -> 275118.47 | CI19: =BU19*0.03 -> 7777.38 | CJ19: =BU19-CI19-CH19 -> -23649.851 | CK19: =CJ19/BU19 -> -0.091225521 | CM19: =CA19 -> 1448.7698 | CN19: =(CC19*1%)/12 -> 202.14599 | CO19: =CM19+CN19+BX19+BY19 -> 2075.7766 | CP19: =VLOOKUP(BS19,'Paste Snowflake Data Here'!$B$2:$K$21,10,FALSE) -> 1004 | CQ19: =CP19-CO19 -> -1071.7766
B20: Minnesota | D20: =_xlfn.XLOOKUP($B20,'Paste Snowflake Data Here'!$B$3:$B$1048576,'Paste Snowflake Data Here'!$D$3:$D$1048576) -> 5852943 | F20: =_xlfn.XLOOKUP($B20,'Paste Snowflake Data Here'!$B$3:$B$1048576,'Paste Snowflake Data Here'!$I$3:$I$1048576) -> 88297 | G20: =_xlfn.XLOOKUP($B20,'Paste Snowflake Data Here'!$B$3:$B$1048576,'Paste Snowflake Data Here'!$J$3:$J$1048576) -> 370277 | H20: =_xlfn.XLOOKUP($B20,'Paste Snowflake Data Here'!$B$3:$B$1048576,'Paste Snowflake Data Here'!$K$3:$K$1048576) -> 1315 | K20: =IFERROR(VLOOKUP(LEFT(B20,FIND("County",B20)-2),CaseShiller30,5,0)*0.01,$K$3) -> 0.05 | L20: =$F20*$L$3 -> 88297 | M20: =$G20*$M$3 -> 370277 | N20: =AND(AF20<$AF$3,AG20<$AG$3) -> FALSE | O20: =AND(AP20<$AP$3,AQ20<$AQ$3) -> TRUE | P20: =AND(N20=FALSE,O20) -> TRUE | Q20: =AH20 -> 111083.1 | R20: =AU20 -> 0 | S20: =AR20 -> 0 | T20: =AZ20 -> 213217.92 | U20: =BA20 -> 19.194452 | V20: =AX20 -> 180942.66 | W20: =AY20 -> 1.6288946 | X20: =$X$3*M20 -> 11108.31 | Y20: =$Y$3 -> 0.0625 | Z20: =M20-X20 -> 359168.69 | AA20: =Z20*'PMI Rate Est'!$J$6/12 -> 350.18947 | AB20: ='Taxes & Ins by State'!B24*M20/12 -> 305.47852 | AC20: ='Taxes & Ins by State'!M20*M20/12 -> 219 | AD20: =MAX(J20*Y20/12,0) -> 0 | AE20: =-PMT(Y20/12,360,Z20) -> 2211.4634 | AF20: =SUM(AE20,AC20,AB20,AA20)/(L20/12) -> 0.41942056 | AG20: =SUM(AE20,AC20,AB20,AA20,AD20)/(L20/12) -> 0.41942056 | AH20: =M20*$AH$3 -> 111083.1 | AI20: =Y20+$AI$3 -> 0.0625 | AJ20: =M20-X20-AH20 -> 248085.59 | AK20: =AH20*$AK$3/12 -> 0 | AL20: =AB20 -> 305.47852 | AM20: =AC20 -> 219 | AN20: =MAX(J20*Y20/12,0) -> 0 | AO20: =-PMT(AI20/12,360,AJ20) -> 1527.5056 | AP20: =SUM(AO20,AM20,AL20)/(L20/12) -> 0.27887482 | AQ20: =SUM(AO20,AM20,AL20,AK20,AN20)/(L20/12) -> 0.27887482 | AR20: =$AR$3*AK20*12 -> 0 | AS20: =$AS$3*(M20-X20) -> 7183.3738 | AT20: =$AT$3*(AH20) -> 3332.493 | AU20: =$AU$3*SUM(AR20,AS20,AT20) -> 0 | AV20: =AU20/M20 -> 0 | AW20: =POWER(1+K20,10)*M20 -> 603142.22 | AX20: =POWER(1+K20,10)*AH20 -> 180942.66 | AY20: =AX20/AH20 -> 1.6288946 | AZ20: =AW20-AX20-FV(AI20/12,(10*12),AO20,-AJ20) -> 213217.92 | BA20: =AZ20/X20 -> 19.194452 | BE20: =(L20/12)*35% -> 2575.3292 | BF20: =BE20-AC20-AB20-AA20 -> 1700.6612 | BG20: =$Y$3/12 -> 0.0052083333 | BH20: =(BG20*(1+BG20)^360) / (((1+BG20)^360)-1) -> 0.006157172 | BI20: =PV(BG20, 360, -BF20) -> 276208.16 | BK20: =BE20-AB20-AC20 -> 2050.8506 | BL20: =BK20/BH20 -> 333083.21 | BN20: =M20-BI20-X20 -> 82960.527 | BO20: =BN20/M20 -> 0.22404991 | BP20: =M20-BL20-X20 -> 26085.476 | BS20: =B20 -> Minnesota | BT20: =L20 -> 88297 | BU20: =M20 -> 370277 | BV20: =H20 -> 1315 | BW20: =AA20 -> 350.18947 | BX20: =AB20 -> 305.47852 | BY20: =AC20 -> 219 | BZ20: =(BT20/12)*$BT$2 -> 2575.3292 | CA20: =BZ20-BW20-BX20-BY20 -> 1700.6612 | CB20: =6.25%/12 -> 0.0052083333 | CC20: =CE20/0.97 -> 284750.68 | CD20: =BU20-CC20 -> 85526.316 | CE20: =PV(CB20,360,-CA20) -> 276208.16 | CG20: =BZ20-BY20-BX20 -> 2050.8506 | CH20: =PV(CB20,360,-CG20) -> 333083.21 | CI20: =BU20*0.03 -> 11108.31 | CJ20: =BU20-CI20-CH20 -> 26085.476 | CK20: =CJ20/BU20 -> 0.070448545 | CM20: =CA20 -> 1700.6612 | CN20: =(CC20*1%)/12 -> 237.29224 | CO20: =CM20+CN20+BX20+BY20 -> 2462.4319 | CP20: =VLOOKUP(BS20,'Paste Snowflake Data Here'!$B$2:$K$21,10,FALSE) -> 1315 | CQ20: =CP20-CO20 -> -1147.4319
B21: Kentucky | D21: =_xlfn.XLOOKUP($B21,'Paste Snowflake Data Here'!$B$3:$B$1048576,'Paste Snowflake Data Here'!$D$3:$D$1048576) -> 4584322 | F21: =_xlfn.XLOOKUP($B21,'Paste Snowflake Data Here'!$B$3:$B$1048576,'Paste Snowflake Data Here'!$I$3:$I$1048576) -> 63706 | G21: =_xlfn.XLOOKUP($B21,'Paste Snowflake Data Here'!$B$3:$B$1048576,'Paste Snowflake Data Here'!$J$3:$J$1048576) -> 227462 | H21: =_xlfn.XLOOKUP($B21,'Paste Snowflake Data Here'!$B$3:$B$1048576,'Paste Snowflake Data Here'!$K$3:$K$1048576) -> 809 | K21: =IFERROR(VLOOKUP(LEFT(B21,FIND("County",B21)-2),CaseShiller30,5,0)*0.01,$K$3) -> 0.05 | L21: =$F21*$L$3 -> 63706 | M21: =$G21*$M$3 -> 227462 | N21: =AND(AF21<$AF$3,AG21<$AG$3) -> FALSE | O21: =AND(AP21<$AP$3,AQ21<$AQ$3) -> TRUE | P21: =AND(N21=FALSE,O21) -> TRUE | Q21: =AH21 -> 68238.6 | R21: =AU21 -> 0 | S21: =AR21 -> 0 | T21: =AZ21 -> 130980.25 | U21: =BA21 -> 19.194452 | V21: =AX21 -> 111153.49 | W21: =AY21 -> 1.6288946 | X21: =$X$3*M21 -> 6823.86 | Y21: =$Y$3 -> 0.0625 | Z21: =M21-X21 -> 220638.14 | AA21: =Z21*'PMI Rate Est'!$J$6/12 -> 215.12219 | AB21: ='Taxes & Ins by State'!B18*M21/12 -> 138.37272 | AC21: ='Taxes & Ins by State'!M18*M21/12 -> 279.5 | AD21: =MAX(J21*Y21/12,0) -> 0 | AE21: =-PMT(Y21/12,360,Z21) -> 1358.507 | AF21: =SUM(AE21,AC21,AB21,AA21)/(L21/12) -> 0.37512986 | AG21: =SUM(AE21,AC21,AB21,AA21,AD21)/(L21/12) -> 0.37512986 | AH21: =M21*$AH$3 -> 68238.6 | AI21: =Y21+$AI$3 -> 0.0625 | AJ21: =M21-X21-AH21 -> 152399.54 | AK21: =AH21*$AK$3/12 -> 0 | AL21: =AB21 -> 138.37272 | AM21: =AC21 -> 279.5 | AN21: =MAX(J21*Y21/12,0) -> 0 | AO21: =-PMT(AI21/12,360,AJ21) -> 938.35018 | AP21: =SUM(AO21,AM21,AL21)/(L21/12) -> 0.25546534 | AQ21: =SUM(AO21,AM21,AL21,AK21,AN21)/(L21/12) -> 0.25546534 | AR21: =$AR$3*AK21*12 -> 0 | AS21: =$AS$3*(M21-X21) -> 4412.7628 | AT21: =$AT$3*(AH21) -> 2047.158 | AU21: =$AU$3*SUM(AR21,AS21,AT21) -> 0 | AV21: =AU21/M21 -> 0 | AW21: =POWER(1+K21,10)*M21 -> 370511.63 | AX21: =POWER(1+K21,10)*AH21 -> 111153.49 | AY21: =AX21/AH21 -> 1.6288946 | AZ21: =AW21-AX21-FV(AI21/12,(10*12),AO21,-AJ21) -> 130980.25 | BA21: =AZ21/X21 -> 19.194452 | BE21: =(L21/12)*35% -> 1858.0917 | BF21: =BE21-AC21-AB21-AA21 -> 1225.0968 | BG21: =$Y$3/12 -> 0.0052083333 | BH21: =(BG21*(1+BG21)^360) / (((1+BG21)^360)-1) -> 0.006157172 | BI21: =PV(BG21, 360, -BF21) -> 198970.69 | BK21: =BE21-AB21-AC21 -> 1440.2189 | BL21: =BK21/BH21 -> 233909.16 | BN21: =M21-BI21-X21 -> 21667.45 | BO21: =BN21/M21 -> 0.095257449 | BP21: =M21-BL21-X21 -> -13271.023 | BS21: =B21 -> Kentucky | BT21: =L21 -> 63706 | BU21: =M21 -> 227462 | BV21: =H21 -> 809 | BW21: =AA21 -> 215.12219 | BX21: =AB21 -> 138.37272 | BY21: =AC21 -> 279.5 | BZ21: =(BT21/12)*$BT$2 -> 1858.0917 | CA21: =BZ21-BW21-BX21-BY21 -> 1225.0968 | CB21: =6.25%/12 -> 0.0052083333 | CC21: =CE21/0.97 -> 205124.42 | CD21: =BU21-CC21 -> 22337.577 | CE21: =PV(CB21,360,-CA21) -> 198970.69 | CG21: =BZ21-BY21-BX21 -> 1440.2189 | CH21: =PV(CB21,360,-CG21) -> 233909.16 | CI21: =BU21*0.03 -> 6823.86 | CJ21: =BU21-CI21-CH21 -> -13271.023 | CK21: =CJ21/BU21 -> -0.058343912 | CM21: =CA21 -> 1225.0968 | CN21: =(CC21*1%)/12 -> 170.93702 | CO21: =CM21+CN21+BX21+BY21 -> 1813.9065 | CP21: =VLOOKUP(BS21,'Paste Snowflake Data Here'!$B$2:$K$21,10,FALSE) -> 809 | CQ21: =CP21-CO21 -> -1004.9065
B22: California | D22: =_xlfn.XLOOKUP($B22,'Paste Snowflake Data Here'!$B$3:$B$1048576,'Paste Snowflake Data Here'!$D$3:$D$1048576) -> 39563914 | F22: =_xlfn.XLOOKUP($B22,'Paste Snowflake Data Here'!$B$3:$B$1048576,'Paste Snowflake Data Here'!$I$3:$I$1048576) -> 101136 | G22: =_xlfn.XLOOKUP($B22,'Paste Snowflake Data Here'!$B$3:$B$1048576,'Paste Snowflake Data Here'!$J$3:$J$1048576) -> 773228 | H22: =_xlfn.XLOOKUP($B22,'Paste Snowflake Data Here'!$B$3:$B$1048576,'Paste Snowflake Data Here'!$K$3:$K$1048576) -> 1988 | K22: =IFERROR(VLOOKUP(LEFT(B22,FIND("County",B22)-2),CaseShiller30,5,0)*0.01,$K$3) -> 0.05 | L22: =$F22*$L$3 -> 101136 | M22: =$G22*$M$3 -> 773228 | N22: =AND(AF22<$AF$3,AG22<$AG$3) -> FALSE | O22: =AND(AP22<$AP$3,AQ22<$AQ$3) -> FALSE | P22: =AND(N22=FALSE,O22) -> FALSE | Q22: =AH22 -> 231968.4 | R22: =AU22 -> 0 | S22: =AR22 -> 0 | T22: =AZ22 -> 445250.63 | U22: =BA22 -> 19.194452 | V22: =AX22 -> 377852.08 | W22: =AY22 -> 1.6288946 | X22: =$X$3*M22 -> 23196.84 | Y22: =$Y$3 -> 0.0625 | Z22: =M22-X22 -> 750031.16 | AA22: =Z22*'PMI Rate Est'!$J$6/12 -> 731.28038 | AB22: ='Taxes & Ins by State'!B22*M22/12 -> 625.02597 | AC22: ='Taxes & Ins by State'!M16*M22/12 -> 119.08333 | AD22: =MAX(J22*Y22/12,0) -> 0 | AE22: =-PMT(Y22/12,360,Z22) -> 4618.0709 | AF22: =SUM(AE22,AC22,AB22,AA22)/(L22/12) -> 0.72300196 | AG22: =SUM(AE22,AC22,AB22,AA22,AD22)/(L22/12) -> 0.72300196 | AH22: =M22*$AH$3 -> 231968.4 | AI22: =Y22+$AI$3 -> 0.0625 | AJ22: =M22-X22-AH22 -> 518062.76 | AK22: =AH22*$AK$3/12 -> 0 | AL22: =AB22 -> 625.02597 | AM22: =AC22 -> 119.08333 | AN22: =MAX(J22*Y22/12,0) -> 0 | AO22: =-PMT(AI22/12,360,AJ22) -> 3189.8015 | AP22: =SUM(AO22,AM22,AL22)/(L22/12) -> 0.46676683 | AQ22: =SUM(AO22,AM22,AL22,AK22,AN22)/(L22/12) -> 0.46676683 | AR22: =$AR$3*AK22*12 -> 0 | AS22: =$AS$3*(M22-X22) -> 15000.623 | AT22: =$AT$3*(AH22) -> 6959.052 | AU22: =$AU$3*SUM(AR22,AS22,AT22) -> 0 | AV22: =AU22/M22 -> 0 | AW22: =POWER(1+K22,10)*M22 -> 1259506.9 | AX22: =POWER(1+K22,10)*AH22 -> 377852.08 | AY22: =AX22/AH22 -> 1.6288946 | AZ22: =AW22-AX22-FV(AI22/12,(10*12),AO22,-AJ22) -> 445250.63 | BA22: =AZ22/X22 -> 19.194452 | BE22: =(L22/12)*35% -> 2949.8 | BF22: =BE22-AC22-AB22-AA22 -> 1474.4103 | BG22: =$Y$3/12 -> 0.0052083333 | BH22: =(BG22*(1+BG22)^360) / (((1+BG22)^360)-1) -> 0.006157172 | BI22: =PV(BG22, 360, -BF22) -> 239462.26 | BK22: =BE22-AB22-AC22 -> 2205.6907 | BL22: =BK22/BH22 -> 358231.13 | BN22: =M22-BI22-X22 -> 510568.9 | BO22: =BN22/M22 -> 0.66030834 | BP22: =M22-BL22-X22 -> 391800.03 | BS22: =B22 -> California | BT22: =L22 -> 101136 | BU22: =M22 -> 773228 | BV22: =H22 -> 1988 | BW22: =AA22 -> 731.28038 | BX22: =AB22 -> 625.02597 | BY22: =AC22 -> 119.08333 | BZ22: =(BT22/12)*$BT$2 -> 2949.8 | CA22: =BZ22-BW22-BX22-BY22 -> 1474.4103 | CB22: =6.25%/12 -> 0.0052083333 | CC22: =CE22/0.97 -> 246868.31 | CD22: =BU22-CC22 -> 526359.69 | CE22: =PV(CB22,360,-CA22) -> 239462.26 | CG22: =BZ22-BY22-BX22 -> 2205.6907 | CH22: =PV(CB22,360,-CG22) -> 358231.13 | CI22: =BU22*0.03 -> 23196.84 | CJ22: =BU22-CI22-CH22 -> 391800.03 | CK22: =CJ22/BU22 -> 0.50670698 | CM22: =CA22 -> 1474.4103 | CN22: =(CC22*1%)/12 -> 205.72359 | CO22: =CM22+CN22+BX22+BY22 -> 2424.2432 | CP22: =VLOOKUP(BS22,'Paste Snowflake Data Here'!$B$2:$K$21,10,FALSE) -> 1988 | CQ22: =CP22-CO22 -> -436.24321
B23: Connecticut | D23: =_xlfn.XLOOKUP($B23,'Paste Snowflake Data Here'!$B$3:$B$1048576,'Paste Snowflake Data Here'!$D$3:$D$1048576) -> 3608872 | F23: =_xlfn.XLOOKUP($B23,'Paste Snowflake Data Here'!$B$3:$B$1048576,'Paste Snowflake Data Here'!$I$3:$I$1048576) -> 95275 | G23: =_xlfn.XLOOKUP($B23,'Paste Snowflake Data Here'!$B$3:$B$1048576,'Paste Snowflake Data Here'!$J$3:$J$1048576) -> 407234 | H23: =_xlfn.XLOOKUP($B23,'Paste Snowflake Data Here'!$B$3:$B$1048576,'Paste Snowflake Data Here'!$K$3:$K$1048576) -> 1394 | K23: =IFERROR(VLOOKUP(LEFT(B23,FIND("County",B23)-2),CaseShiller30,5,0)*0.01,$K$3) -> 0.05 | L23: =$F23*$L$3 -> 95275 | M23: =$G23*$M$3 -> 407234 | N23: =AND(AF23<$AF$3,AG23<$AG$3) -> FALSE | O23: =AND(AP23<$AP$3,AQ23<$AQ$3) -> TRUE | P23: =AND(N23=FALSE,O23) -> TRUE | Q23: =AH23 -> 122170.2 | R23: =AU23 -> 0 | S23: =AR23 -> 0 | T23: =AZ23 -> 234499 | U23: =BA23 -> 19.194452 | V23: =AX23 -> 199002.38 | W23: =AY23 -> 1.6288946 | X23: =$X$3*M23 -> 12217.02 | Y23: =$Y$3 -> 0.0625 | Z23: =M23-X23 -> 395016.98 | AA23: =Z23*'PMI Rate Est'!$J$6/12 -> 385.14156 | AB23: ='Taxes & Ins by State'!B8*M23/12 -> 502.25527 | AC23: ='Taxes & Ins by State'!M15*M23/12 -> 138.33333 | AD23: =MAX(J23*Y23/12,0) -> 0 | AE23: =-PMT(Y23/12,360,Z23) -> 2432.1875 | AF23: =SUM(AE23,AC23,AB23,AA23)/(L23/12) -> 0.43552886 | AG23: =SUM(AE23,AC23,AB23,AA23,AD23)/(L23/12) -> 0.43552886 | AH23: =M23*$AH$3 -> 122170.2 | AI23: =Y23+$AI$3 -> 0.0625 | AJ23: =M23-X23-AH23 -> 272846.78 | AK23: =AH23*$AK$3/12 -> 0 | AL23: =AB23 -> 502.25527 | AM23: =AC23 -> 138.33333 | AN23: =MAX(J23*Y23/12,0) -> 0 | AO23: =-PMT(AI23/12,360,AJ23) -> 1679.9646 | AP23: =SUM(AO23,AM23,AL23)/(L23/12) -> 0.29227644 | AQ23: =SUM(AO23,AM23,AL23,AK23,AN23)/(L23/12) -> 0.29227644 | AR23: =$AR$3*AK23*12 -> 0 | AS23: =$AS$3*(M23-X23) -> 7900.3396 | AT23: =$AT$3*(AH23) -> 3665.106 | AU23: =$AU$3*SUM(AR23,AS23,AT23) -> 0 | AV23: =AU23/M23 -> 0 | AW23: =POWER(1+K23,10)*M23 -> 663341.27 | AX23: =POWER(1+K23,10)*AH23 -> 199002.38 | AY23: =AX23/AH23 -> 1.6288946 | AZ23: =AW23-AX23-FV(AI23/12,(10*12),AO23,-AJ23) -> 234499 | BA23: =AZ23/X23 -> 19.194452 | BE23: =(L23/12)*35% -> 2778.8542 | BF23: =BE23-AC23-AB23-AA23 -> 1753.124 | BG23: =$Y$3/12 -> 0.0052083333 | BH23: =(BG23*(1+BG23)^360) / (((1+BG23)^360)-1) -> 0.006157172 | BI23: =PV(BG23, 360, -BF23) -> 284728.77 | BK23: =BE23-AB23-AC23 -> 2138.2656 | BL23: =BK23/BH23 -> 347280.47 | BN23: =M23-BI23-X23 -> 110288.21 | BO23: =BN23/M23 -> 0.2708227 | BP23: =M23-BL23-X23 -> 47736.513 | BS23: =B23 -> Connecticut | BT23: =L23 -> 95275 | BU23: =M23 -> 407234 | BV23: =H23 -> 1394 | BW23: =AA23 -> 385.14156 | BX23: =AB23 -> 502.25527 | BY23: =AC23 -> 138.33333 | BZ23: =(BT23/12)*$BT$2 -> 2778.8542 | CA23: =BZ23-BW23-BX23-BY23 -> 1753.124 | CB23: =6.25%/12 -> 0.0052083333 | CC23: =CE23/0.97 -> 293534.81 | CD23: =BU23-CC23 -> 113699.19 | CE23: =PV(CB23,360,-CA23) -> 284728.77 | CG23: =BZ23-BY23-BX23 -> 2138.2656 | CH23: =PV(CB23,360,-CG23) -> 347280.47 | CI23: =BU23*0.03 -> 12217.02 | CJ23: =BU23-CI23-CH23 -> 47736.513 | CK23: =CJ23/BU23 -> 0.11722134 | CM23: =CA23 -> 1753.124 | CN23: =(CC23*1%)/12 -> 244.61235 | CO23: =CM23+CN23+BX23+BY23 -> 2638.325 | CP23: =VLOOKUP(BS23,'Paste Snowflake Data Here'!$B$2:$K$21,10,FALSE) -> 1394 | CQ23: =CP23-CO23 -> -1244.325
X24: =AVERAGE(X5:X23) -> 13724.444 | AE24: =AVERAGE(AE5:AE23) -> 2732.2884 | AF24: =AVERAGE(AF5:AF23) -> 0.49214459 | AO24: =AVERAGE(AO5:AO23) -> 1887.2507 | AP24: =AVERAGE(AP5:AP23) -> 0.32209478 | BZ24: 1) How much can family afford per month? | CA24: 2) Amount that goes to mortgage principal + interest | CC24: 4) Affordable 1st mortgage + 3% down | CD24: 5) Affordable home price vs. median home price | CE24: 3) Monthly payment translated into 1st mortgage size | CG24: 6) Remove PMI and more monthly funds available for mortgage | CH24: 7) Affordable loan size increased | CJ24: 8) Amount of capital to close the gap
I25: =F24 -> 0 | M25: TRUE | N25: =COUNTIF(N5:N23,"true") -> 0 | O25: =COUNTIF(O5:O23,"true") -> 13 | P25: =COUNTIF(P5:P23,"true") -> 13 | BI25: =BI23/0.97 -> 293534.81 | CD25: How far off is the market?
N26: =N25/(COUNTA(N5:N23)) -> 0 | O26: =O25/(COUNTA(O5:O23)) -> 0.68421053 | P26: =P25/(COUNTA(P5:P23)) -> 0.68421053 | Q26: % Converted
M28: FALSE | N28: =COUNTA(N5:N23)-N25 -> 19 | O28: =COUNTA(O5:O23)-O25 -> 6
N29: =N28/COUNTA(N5:N23) -> 1 | O29: =O28/COUNTA(O5:O23) -> 0.31578947
G36: Affordability Gap | H36: How much the LTV on the 1st mortgage needs to decrease to achieve 35% DTI Max. assuming 3% DP and same 1st mortgage rate. 35% max front ratio. What is the amount of HOM needed on a median priced home for a median income earner.
M1701: =AVERAGE(M5:M1700) -> 457481.47 | N1701: =COUNTIF(N5:N1700,"true") -> 0 | O1701: =COUNTIF(O5:O1700,"true") -> 13 | P1701: =COUNTIF(P5:P1700,"true") -> 13
K1702: 87000 | N1702: 1730
N1703: =N1701/N1702 -> 0 | O1703: =O1701/N1702 -> 0.0075144509 | P1703: =P1701/N1702 -> 0.0075144509

Sheet Taxes & Ins by State
A1: State | B1: Effective Tax Rate (2023) | C1: https://taxfoundation.org/data/all/state/property-taxes-by-state-county/ | J1: State | K1: Avg Annual Insurance (2025 est) | L1: Median Home Value (2025 est) | M1: % of Home Value | N1: https://www.ramseysolutions.com/insurance/home-insurance-rates-by-state?srsltid=AfmBOor11m9ccj5xQGJveaIOgs0_zXz4pvDN6-xr1RHnJjc8as4HkzMz
A2: Alabama | B2: 0.0036 | J2: Delaware | K2: 964 | L2: =VLOOKUP(J2,'Paste Snowflake Data Here'!$B$2:$K$21,9,FALSE) -> 389964 | M2: =K2/L2 -> 0.0024720231 | N2: https://www.bankrate.com/real-estate/median-home-price/
A3: Alaska | B3: 0.0091 | J3: Hawaii | K3: 1224 | L3: =VLOOKUP(J3,'Paste Snowflake Data Here'!$B$2:$K$21,9,FALSE) -> 924013 | M3: =K3/L3 -> 0.0013246567
A4: Arizona | B4: 0.0044 | J4: Illinois | K4: 2265 | L4: =VLOOKUP(J4,'Paste Snowflake Data Here'!$B$2:$K$21,9,FALSE) -> 286497 | M4: =K4/L4 -> 0.0079058419
A5: Arkansas | B5: 0.0053 | J5: Maryland | K5: 1671 | L5: =VLOOKUP(J5,'Paste Snowflake Data Here'!$B$2:$K$21,9,FALSE) -> 468044 | M5: =K5/L5 -> 0.0035701772
A6: California | B6: 0.007 | J6: Massachusetts | K6: 1703 | L6: =VLOOKUP(J6,'Paste Snowflake Data Here'!$B$2:$K$21,9,FALSE) -> 637329 | M6: =K6/L6 -> 0.0026720893
A7: Colorado | B7: 0.005 | J7: New Jersey | K7: 1194 | L7: =VLOOKUP(J7,'Paste Snowflake Data Here'!$B$2:$K$21,9,FALSE) -> 513938 | M7: =K7/L7 -> 0.0023232374
A8: Connecticut | B8: 0.0148 | J8: New York | K8: 1752 | L8: =VLOOKUP(J8,'Paste Snowflake Data Here'!$B$2:$K$21,9,FALSE) -> 485429 | M8: =K8/L8 -> 0.0036091787
A9: Delaware | B9: 0.005 | J9: North Carolina | K9: 2055 | L9: =VLOOKUP(J9,'Paste Snowflake Data Here'!$B$2:$K$21,9,FALSE) -> 334561 | M9: =K9/L9 -> 0.0061423776
A10: Florida | B10: 0.0074 | J10: Oregon | K10: 1011 | L10: =VLOOKUP(J10,'Paste Snowflake Data Here'!$B$2:$K$21,9,FALSE) -> 549301 | M10: =K10/L10 -> 0.001840521
A11: Georgia | B11: 0.0077 | J11: Pennsylvania | K11: 1245 | L11: =VLOOKUP(J11,'Paste Snowflake Data Here'!$B$2:$K$21,9,FALSE) -> 303362 | M11: =K11/L11 -> 0.0041040078
A12: Hawaii | B12: 0.0032 | J12: Rhode Island | K12: 2324 | L12: =VLOOKUP(J12,'Paste Snowflake Data Here'!$B$2:$K$21,9,FALSE) -> 447602 | M12: =K12/L12 -> 0.0051921126
A13: Idaho | B13: 0.0048 | J13: Washington | K13: 1513 | L13: =VLOOKUP(J13,'Paste Snowflake Data Here'!$B$2:$K$21,9,FALSE) -> 641336 | M13: =K13/L13 -> 0.0023591378
A14: Illinois | B14: 0.0183 | J14: Arizona | K14: 2245 | L14: =VLOOKUP(J14,'Paste Snowflake Data Here'!$B$2:$K$21,9,FALSE) -> 429848 | M14: =K14/L14 -> 0.0052227764
... A20: Maine | B20: 0.0094 | J20: Minnesota | K20: 2628 | L20: =VLOOKUP(J20,'Paste Snowflake Data Here'!$B$2:$K$21,9,FALSE) -> 370277 | M20: =K20/L20 -> 0.0070973893
A21: Maryland | B21: 0.009
A22: Massachusetts | B22: 0.0097
A23: Michigan | B23: 0.0115
A24: Minnesota | B24: 0.0099
A25: Mississippi | B25: 0.0058
A26: Missouri | B26: 0.0088
A27: Montana | B27: 0.006
A28: Nebraska | B28: 0.0143
A29: Nevada | B29: 0.0049
A30: New Hampshire | B30: 0.0141
A31: New Jersey | B31: 0.0177
A32: New Mexico | B32: 0.0061
... A52: District of Columbia | B52: 0.0061

Sheet Debt
A1: State | B1: Avg. Nonmortgage Debt Q3 2025 | C1: Monthly Nonmortgage Debt
A2: West Virginia | B2: 38850 | C2: =B2/12 -> 3237.5
A3: New Hampshire | B3: 37264 | C3: =B3/12 -> 3105.3333
A4: Nevada | B4: 37867 | C4: =B4/12 -> 3155.5833
A5: Minnesota | B5: 34962 | C5: =B5/12 -> 2913.5
A6: Washington | B6: 34318 | C6: =B6/12 -> 2859.8333
A7: Hawaii | B7: 35831 | C7: =B7/12 -> 2985.9167
A8: Vermont | B8: 37005 | C8: =B8/12 -> 3083.75
A9: Indiana | B9: 34182 | C9: =B9/12 -> 2848.5
A10: Wyoming | B10: 36560 | C10: =B10/12 -> 3046.6667
A11: Idaho | B11: 34252 | C11: =B11/12 -> 2854.3333
A12: Maryland | B12: 41806 | C12: =B12/12 -> 3483.8333
A13: Colorado | B13: 37808 | C13: =B13/12 -> 3150.6667
... A51: Nebraska | B51: 33626 | C51: =B51/12 -> 2802.1667

Sheet Tiana - Aggregate Model
B3: Key Assumptions: | K3: ='Assumptions & Borrower Profiles'!$C$11 -> 0.05 | L3: ='Assumptions & Borrower Profiles'!M5 -> 1 | M3: ='Assumptions & Borrower Profiles'!M8 -> 1 | Q3: ='Assumptions & Borrower Profiles'!M27 -> 0.3 | R3: 1 | X3: ='Assumptions & Borrower Profiles'!M11 -> 0.03 | Y3: ='Assumptions & Borrower Profiles'!$C$7 -> 0.0625 | AA3: ='Assumptions & Borrower Profiles'!$C$6 -> 620 | AB3: ='Assumptions & Borrower Profiles'!$C$17 -> 0.0135 | AC3: ='Assumptions & Borrower Profiles'!$C$18 -> 0.004 | AF3: ='Assumptions & Borrower Profiles'!$C$25 -> 0.35 | AG3: =AF3+0.1 -> 0.45 | AH3: =Q3 -> 0.3 | AI3: ='Assumptions & Borrower Profiles'!C7-'Assumptions & Borrower Profiles'!C8 -> 0 | AK3: 0 | AL3: =AB3 -> 0.0135 | AM3: =AC3 -> 0.004 | AP3: =AF3 -> 0.35 | AQ3: =AG3 -> 0.45 | AR3: 0 | AS3: ='Assumptions & Borrower Profiles'!$C$13 -> 0.02 | AT3: 0.03 | AU3: 0
B4: ZIP Code | C4: Code | D4: Population | E4: % African American | F4: Area Median Household Income | G4: Median Home Values | H4: Median Contract Rent | I4: DTI Avg | J4: Estimated Household Debt (incl mortgage) | K4: 30 Year Case Shiller Return / ann | L4: % AMI for calc | M4: % Median Home Value | N4: Passed DTI without HOM? | O4: Passed DTI with HOM? | P4: Threshold? | Q4: HOM Investment | R4: Grant for Fees/PMI | S4: Annual PMI | T4: Homeowner Equity after 10 Years | U4: % Gain from Downpayment | V4: HOM Investment after 10 Years | W4: % Gain on HOM Investment | X4: Downpayment | Y4: 30 Year Fixed Rate for 640 | Z4: 1st Principal Without Homium | AA4: PMI / Month | AB4: Tax / mo | AC4: Insurance / mo | AD4: Household Debt Service / mo | AE4: Monthly Payment | AF4: Front Ratio | AG4: Back Ratio | AH4: SAN Principal | AI4: 30 Year Fixed Rate for 640 WITH HOMIUM | AJ4: 1st Principal WITH Homium | AK4: PMI / Month | AL4: Tax / mo | AM4: Insurance / mo | AN4: Household Debt Service / mo | AO4: New Monthly Payment on 1st | AP4: Front Ratio with HOM | AQ4: Back Ratio with HOM | AR4: PMI Total (yrs) | AS4: Closing Fees | AT4: Origination Fees | AU4: Total Grant | AV4: % Total Grant of Home Value | AW4: Home Value after 10 years at X apprec | AX4: Homium SAN Value after 10 years | AY4: % Gain on HOM investment | AZ4: Homeowner Equity after 10 years | BA4: % Gain from Downpayment
B5: 90001 | C5: =IFERROR(VLOOKUP(LEFT(B5,FIND("County",B5)-2),CaseShiller30,2,0),"No Data") -> No Data | D5: =_xlfn.XLOOKUP($B5,'Paste Snowflake Data Here'!$B$3:$B$1048576,'Paste Snowflake Data Here'!$D$3:$D$1048576) -> #N/A | F5: =_xlfn.XLOOKUP($B5,'Paste Snowflake Data Here'!$B$3:$B$1048576,'Paste Snowflake Data Here'!$I$3:$I$1048576) -> #N/A | G5: =_xlfn.XLOOKUP($B5,'Paste Snowflake Data Here'!$B$3:$B$1048576,'Paste Snowflake Data Here'!$J$3:$J$1048576) -> #N/A | K5: =IFERROR(VLOOKUP(LEFT(B5,FIND("County",B5)-2),CaseShiller30,5,0)*0.01,$K$3) -> 0.05 | L5: =$F5*$L$3 -> #N/A | M5: =$G5*$M$3 -> #N/A | N5: =AND(AF5<$AF$3,AG5<$AG$3) -> #N/A | O5: =AND(AP5<$AP$3,AQ5<$AQ$3) -> #N/A | P5: =AND(N5=FALSE,O5) -> #N/A | Q5: =AH5 -> #N/A | R5: =AU5 -> #N/A | S5: =AR5 -> #N/A | T5: =AZ5 -> #N/A | U5: =BA5 -> #N/A | V5: =AX5 -> #N/A | W5: =AY5 -> #N/A | X5: =$X$3*M5 -> #N/A | Y5: =$Y$3 -> 0.0625 | Z5: =M5-X5 -> #N/A | AA5: =Z5*'PMI Rate Est'!$J$6/12 -> #N/A | AB5: =$AB$3*M5/12 -> #N/A | AC5: =$AC$3*M5/12 -> #N/A | AD5: =MAX(J5*Y5/12,0) -> 0 | AE5: =-PMT(Y5/12,360,Z5) -> #N/A | AF5: =SUM(AE5,AC5,AB5,AA5)/(L5/12) -> #N/A | AG5: =SUM(AE5,AC5,AB5,AA5,AD5)/(L5/12) -> #N/A | AH5: =M5*$AH$3 -> #N/A | AI5: =Y5+$AI$3 -> 0.0625 | AJ5: =M5-X5-AH5 -> #N/A | AK5: =AH5*$AK$3/12 -> #N/A | AL5: =$AL$3*M5/12 -> #N/A | AM5: =$AM$3*M5/12 -> #N/A | AN5: =MAX(J5*Y5/12,0) -> 0 | AO5: =-PMT(AI5/12,360,AJ5) -> #N/A | AP5: =SUM(AO5,AM5,AL5)/(L5/12) -> #N/A | AQ5: =SUM(AO5,AM5,AL5,AK5,AN5)/(L5/12) -> #N/A | AR5: =$AR$3*AK5*12 -> #N/A | AS5: =$AS$3*(M5-X5) -> #N/A | AT5: =$AT$3*(AH5) -> #N/A | AU5: =$AU$3*SUM(AR5,AS5,AT5) -> #N/A | AV5: =AU5/M5 -> #N/A | AW5: =POWER(1+K5,10)*M5 -> #N/A | AX5: =POWER(1+K5,10)*AH5 -> #N/A | AY5: =AX5/AH5 -> #N/A | AZ5: =AW5-AX5-FV(AI5/12,(10*12),AO5,-AJ5) -> #N/A | BA5: =AZ5/X5 -> #N/A
B6: 90002 | C6: =IFERROR(VLOOKUP(LEFT(B6,FIND("County",B6)-2),CaseShiller30,2,0),"No Data") -> No Data | D6: =_xlfn.XLOOKUP($B6,'Paste Snowflake Data Here'!$B$3:$B$1048576,'Paste Snowflake Data Here'!$D$3:$D$1048576) -> #N/A | F6: =_xlfn.XLOOKUP($B6,'Paste Snowflake Data Here'!$B$3:$B$1048576,'Paste Snowflake Data Here'!$I$3:$I$1048576) -> #N/A | G6: =_xlfn.XLOOKUP($B6,'Paste Snowflake Data Here'!$B$3:$B$1048576,'Paste Snowflake Data Here'!$J$3:$J$1048576) -> #N/A | K6: =IFERROR(VLOOKUP(LEFT(B6,FIND("County",B6)-2),CaseShiller30,5,0)*0.01,$K$3) -> 0.05 | L6: =$F6*$L$3 -> #N/A | M6: =$G6*$M$3 -> #N/A | N6: =AND(AF6<$AF$3,AG6<$AG$3) -> #N/A | O6: =AND(AP6<$AP$3,AQ6<$AQ$3) -> #N/A | P6: =AND(N6=FALSE,O6) -> #N/A | Q6: =AH6 -> #N/A | R6: =AU6 -> #N/A | S6: =AR6 -> #N/A | T6: =AZ6 -> #N/A | U6: =BA6 -> #N/A | V6: =AX6 -> #N/A | W6: =AY6 -> #N/A | X6: =$X$3*M6 -> #N/A | Y6: =$Y$3 -> 0.0625 | Z6: =M6-X6 -> #N/A | AA6: =Z6*'PMI Rate Est'!$J$6/12 -> #N/A | AB6: =$AB$3*M6/12 -> #N/A | AC6: =$AC$3*M6/12 -> #N/A | AD6: =MAX(J6*Y6/12,0) -> 0 | AE6: =-PMT(Y6/12,360,Z6) -> #N/A | AF6: =SUM(AE6,AC6,AB6,AA6)/(L6/12) -> #N/A | AG6: =SUM(AE6,AC6,AB6,AA6,AD6)/(L6/12) -> #N/A | AH6: =M6*$AH$3 -> #N/A | AI6: =Y6+$AI$3 -> 0.0625 | AJ6: =M6-X6-AH6 -> #N/A | AK6: =AH6*$AK$3/12 -> #N/A | AL6: =$AL$3*M6/12 -> #N/A | AM6: =$AM$3*M6/12 -> #N/A | AN6: =MAX(J6*Y6/12,0) -> 0 | AO6: =-PMT(AI6/12,360,AJ6) -> #N/A | AP6: =SUM(AO6,AM6,AL6)/(L6/12) -> #N/A | AQ6: =SUM(AO6,AM6,AL6,AK6,AN6)/(L6/12) -> #N/A | AR6: =$AR$3*AK6*12 -> #N/A | AS6: =$AS$3*(M6-X6) -> #N/A | AT6: =$AT$3*(AH6) -> #N/A | AU6: =$AU$3*SUM(AR6,AS6,AT6) -> #N/A | AV6: =AU6/M6 -> #N/A | AW6: =POWER(1+K6,10)*M6 -> #N/A | AX6: =POWER(1+K6,10)*AH6 -> #N/A | AY6: =AX6/AH6 -> #N/A | AZ6: =AW6-AX6-FV(AI6/12,(10*12),AO6,-AJ6) -> #N/A | BA6: =AZ6/X6 -> #N/A
B7: 90003 | C7: =IFERROR(VLOOKUP(LEFT(B7,FIND("County",B7)-2),CaseShiller30,2,0),"No Data") -> No Data | D7: =_xlfn.XLOOKUP($B7,'Paste Snowflake Data Here'!$B$3:$B$1048576,'Paste Snowflake Data Here'!$D$3:$D$1048576) -> #N/A | F7: =_xlfn.XLOOKUP($B7,'Paste Snowflake Data Here'!$B$3:$B$1048576,'Paste Snowflake Data Here'!$I$3:$I$1048576) -> #N/A | G7: =_xlfn.XLOOKUP($B7,'Paste Snowflake Data Here'!$B$3:$B$1048576,'Paste Snowflake Data Here'!$J$3:$J$1048576) -> #N/A | K7: =IFERROR(VLOOKUP(LEFT(B7,FIND("County",B7)-2),CaseShiller30,5,0)*0.01,$K$3) -> 0.05 | L7: =$F7*$L$3 -> #N/A | M7: =$G7*$M$3 -> #N/A | N7: =AND(AF7<$AF$3,AG7<$AG$3) -> #N/A | O7: =AND(AP7<$AP$3,AQ7<$AQ$3) -> #N/A | P7: =AND(N7=FALSE,O7) -> #N/A | Q7: =AH7 -> #N/A | R7: =AU7 -> #N/A | S7: =AR7 -> #N/A | T7: =AZ7 -> #N/A | U7: =BA7 -> #N/A | V7: =AX7 -> #N/A | W7: =AY7 -> #N/A | X7: =$X$3*M7 -> #N/A | Y7: =$Y$3 -> 0.0625 | Z7: =M7-X7 -> #N/A | AA7: =Z7*'PMI Rate Est'!$J$6/12 -> #N/A | AB7: =$AB$3*M7/12 -> #N/A | AC7: =$AC$3*M7/12 -> #N/A | AD7: =MAX(J7*Y7/12,0) -> 0 | AE7: =-PMT(Y7/12,360,Z7) -> #N/A | AF7: =SUM(AE7,AC7,AB7,AA7)/(L7/12) -> #N/A | AG7: =SUM(AE7,AC7,AB7,AA7,AD7)/(L7/12) -> #N/A | AH7: =M7*$AH$3 -> #N/A | AI7: =Y7+$AI$3 -> 0.0625 | AJ7: =M7-X7-AH7 -> #N/A | AK7: =AH7*$AK$3/12 -> #N/A | AL7: =$AL$3*M7/12 -> #N/A | AM7: =$AM$3*M7/12 -> #N/A | AN7: =MAX(J7*Y7/12,0) -> 0 | AO7: =-PMT(AI7/12,360,AJ7) -> #N/A | AP7: =SUM(AO7,AM7,AL7)/(L7/12) -> #N/A | AQ7: =SUM(AO7,AM7,AL7,AK7,AN7)/(L7/12) -> #N/A | AR7: =$AR$3*AK7*12 -> #N/A | AS7: =$AS$3*(M7-X7) -> #N/A | AT7: =$AT$3*(AH7) -> #N/A | AU7: =$AU$3*SUM(AR7,AS7,AT7) -> #N/A | AV7: =AU7/M7 -> #N/A | AW7: =POWER(1+K7,10)*M7 -> #N/A | AX7: =POWER(1+K7,10)*AH7 -> #N/A | AY7: =AX7/AH7 -> #N/A | AZ7: =AW7-AX7-FV(AI7/12,(10*12),AO7,-AJ7) -> #N/A | BA7: =AZ7/X7 -> #N/A
B8: 90004 | C8: =IFERROR(VLOOKUP(LEFT(B8,FIND("County",B8)-2),CaseShiller30,2,0),"No Data") -> No Data | D8: =_xlfn.XLOOKUP($B8,'Paste Snowflake Data Here'!$B$3:$B$1048576,'Paste Snowflake Data Here'!$D$3:$D$1048576) -> #N/A | F8: =_xlfn.XLOOKUP($B8,'Paste Snowflake Data Here'!$B$3:$B$1048576,'Paste Snowflake Data Here'!$I$3:$I$1048576) -> #N/A | G8: =_xlfn.XLOOKUP($B8,'Paste Snowflake Data Here'!$B$3:$B$1048576,'Paste Snowflake Data Here'!$J$3:$J$1048576) -> #N/A | K8: =IFERROR(VLOOKUP(LEFT(B8,FIND("County",B8)-2),CaseShiller30,5,0)*0.01,$K$3) -> 0.05 | L8: =$F8*$L$3 -> #N/A | M8: =$G8*$M$3 -> #N/A | N8: =AND(AF8<$AF$3,AG8<$AG$3) -> #N/A | O8: =AND(AP8<$AP$3,AQ8<$AQ$3) -> #N/A | P8: =AND(N8=FALSE,O8) -> #N/A | Q8: =AH8 -> #N/A | R8: =AU8 -> #N/A | S8: =AR8 -> #N/A | T8: =AZ8 -> #N/A | U8: =BA8 -> #N/A | V8: =AX8 -> #N/A | W8: =AY8 -> #N/A | X8: =$X$3*M8 -> #N/A | Y8: =$Y$3 -> 0.0625 | Z8: =M8-X8 -> #N/A | AA8: =Z8*'PMI Rate Est'!$J$6/12 -> #N/A | AB8: =$AB$3*M8/12 -> #N/A | AC8: =$AC$3*M8/12 -> #N/A | AD8: =MAX(J8*Y8/12,0) -> 0 | AE8: =-PMT(Y8/12,360,Z8) -> #N/A | AF8: =SUM(AE8,AC8,AB8,AA8)/(L8/12) -> #N/A | AG8: =SUM(AE8,AC8,AB8,AA8,AD8)/(L8/12) -> #N/A | AH8: =M8*$AH$3 -> #N/A | AI8: =Y8+$AI$3 -> 0.0625 | AJ8: =M8-X8-AH8 -> #N/A | AK8: =AH8*$AK$3/12 -> #N/A | AL8: =$AL$3*M8/12 -> #N/A | AM8: =$AM$3*M8/12 -> #N/A | AN8: =MAX(J8*Y8/12,0) -> 0 | AO8: =-PMT(AI8/12,360,AJ8) -> #N/A | AP8: =SUM(AO8,AM8,AL8)/(L8/12) -> #N/A | AQ8: =SUM(AO8,AM8,AL8,AK8,AN8)/(L8/12) -> #N/A | AR8: =$AR$3*AK8*12 -> #N/A | AS8: =$AS$3*(M8-X8) -> #N/A | AT8: =$AT$3*(AH8) -> #N/A | AU8: =$AU$3*SUM(AR8,AS8,AT8) -> #N/A | AV8: =AU8/M8 -> #N/A | AW8: =POWER(1+K8,10)*M8 -> #N/A | AX8: =POWER(1+K8,10)*AH8 -> #N/A | AY8: =AX8/AH8 -> #N/A | AZ8: =AW8-AX8-FV(AI8/12,(10*12),AO8,-AJ8) -> #N/A | BA8: =AZ8/X8 -> #N/A
B9: 90005 | C9: =IFERROR(VLOOKUP(LEFT(B9,FIND("County",B9)-2),CaseShiller30,2,0),"No Data") -> No Data | D9: =_xlfn.XLOOKUP($B9,'Paste Snowflake Data Here'!$B$3:$B$1048576,'Paste Snowflake Data Here'!$D$3:$D$1048576) -> #N/A | F9: =_xlfn.XLOOKUP($B9,'Paste Snowflake Data Here'!$B$3:$B$1048576,'Paste Snowflake Data Here'!$I$3:$I$1048576) -> #N/A | G9: =_xlfn.XLOOKUP($B9,'Paste Snowflake Data Here'!$B$3:$B$1048576,'Paste Snowflake Data Here'!$J$3:$J$1048576) -> #N/A | K9: =IFERROR(VLOOKUP(LEFT(B9,FIND("County",B9)-2),CaseShiller30,5,0)*0.01,$K$3) -> 0.05 | L9: =$F9*$L$3 -> #N/A | M9: =$G9*$M$3 -> #N/A | N9: =AND(AF9<$AF$3,AG9<$AG$3) -> #N/A | O9: =AND(AP9<$AP$3,AQ9<$AQ$3) -> #N/A | P9: =AND(N9=FALSE,O9) -> #N/A | Q9: =AH9 -> #N/A | R9: =AU9 -> #N/A | S9: =AR9 -> #N/A | T9: =AZ9 -> #N/A | U9: =BA9 -> #N/A | V9: =AX9 -> #N/A | W9: =AY9 -> #N/A | X9: =$X$3*M9 -> #N/A | Y9: =$Y$3 -> 0.0625 | Z9: =M9-X9 -> #N/A | AA9: =Z9*'PMI Rate Est'!$J$6/12 -> #N/A | AB9: =$AB$3*M9/12 -> #N/A | AC9: =$AC$3*M9/12 -> #N/A | AD9: =MAX(J9*Y9/12,0) -> 0 | AE9: =-PMT(Y9/12,360,Z9) -> #N/A | AF9: =SUM(AE9,AC9,AB9,AA9)/(L9/12) -> #N/A | AG9: =SUM(AE9,AC9,AB9,AA9,AD9)/(L9/12) -> #N/A | AH9: =M9*$AH$3 -> #N/A | AI9: =Y9+$AI$3 -> 0.0625 | AJ9: =M9-X9-AH9 -> #N/A | AK9: =AH9*$AK$3/12 -> #N/A | AL9: =$AL$3*M9/12 -> #N/A | AM9: =$AM$3*M9/12 -> #N/A | AN9: =MAX(J9*Y9/12,0) -> 0 | AO9: =-PMT(AI9/12,360,AJ9) -> #N/A | AP9: =SUM(AO9,AM9,AL9)/(L9/12) -> #N/A | AQ9: =SUM(AO9,AM9,AL9,AK9,AN9)/(L9/12) -> #N/A | AR9: =$AR$3*AK9*12 -> #N/A | AS9: =$AS$3*(M9-X9) -> #N/A | AT9: =$AT$3*(AH9) -> #N/A | AU9: =$AU$3*SUM(AR9,AS9,AT9) -> #N/A | AV9: =AU9/M9 -> #N/A | AW9: =POWER(1+K9,10)*M9 -> #N/A | AX9: =POWER(1+K9,10)*AH9 -> #N/A | AY9: =AX9/AH9 -> #N/A | AZ9: =AW9-AX9-FV(AI9/12,(10*12),AO9,-AJ9) -> #N/A | BA9: =AZ9/X9 -> #N/A
B10: 90006 | C10: =IFERROR(VLOOKUP(LEFT(B10,FIND("County",B10)-2),CaseShiller30,2,0),"No Data") -> No Data | D10: =_xlfn.XLOOKUP($B10,'Paste Snowflake Data Here'!$B$3:$B$1048576,'Paste Snowflake Data Here'!$D$3:$D$1048576) -> #N/A | F10: =_xlfn.XLOOKUP($B10,'Paste Snowflake Data Here'!$B$3:$B$1048576,'Paste Snowflake Data Here'!$I$3:$I$1048576) -> #N/A | G10: =_xlfn.XLOOKUP($B10,'Paste Snowflake Data Here'!$B$3:$B$1048576,'Paste Snowflake Data Here'!$J$3:$J$1048576) -> #N/A | K10: =IFERROR(VLOOKUP(LEFT(B10,FIND("County",B10)-2),CaseShiller30,5,0)*0.01,$K$3) -> 0.05 | L10: =$F10*$L$3 -> #N/A | M10: =$G10*$M$3 -> #N/A | N10: =AND(AF10<$AF$3,AG10<$AG$3) -> #N/A | O10: =AND(AP10<$AP$3,AQ10<$AQ$3) -> #N/A | P10: =AND(N10=FALSE,O10) -> #N/A | Q10: =AH10 -> #N/A | R10: =AU10 -> #N/A | S10: =AR10 -> #N/A | T10: =AZ10 -> #N/A | U10: =BA10 -> #N/A | V10: =AX10 -> #N/A | W10: =AY10 -> #N/A | X10: =$X$3*M10 -> #N/A | Y10: =$Y$3 -> 0.0625 | Z10: =M10-X10 -> #N/A | AA10: =Z10*'PMI Rate Est'!$J$6/12 -> #N/A | AB10: =$AB$3*M10/12 -> #N/A | AC10: =$AC$3*M10/12 -> #N/A | AD10: =MAX(J10*Y10/12,0) -> 0 | AE10: =-PMT(Y10/12,360,Z10) -> #N/A | AF10: =SUM(AE10,AC10,AB10,AA10)/(L10/12) -> #N/A | AG10: =SUM(AE10,AC10,AB10,AA10,AD10)/(L10/12) -> #N/A | AH10: =M10*$AH$3 -> #N/A | AI10: =Y10+$AI$3 -> 0.0625 | AJ10: =M10-X10-AH10 -> #N/A | AK10: =AH10*$AK$3/12 -> #N/A | AL10: =$AL$3*M10/12 -> #N/A | AM10: =$AM$3*M10/12 -> #N/A | AN10: =MAX(J10*Y10/12,0) -> 0 | AO10: =-PMT(AI10/12,360,AJ10) -> #N/A | AP10: =SUM(AO10,AM10,AL10)/(L10/12) -> #N/A | AQ10: =SUM(AO10,AM10,AL10,AK10,AN10)/(L10/12) -> #N/A | AR10: =$AR$3*AK10*12 -> #N/A | AS10: =$AS$3*(M10-X10) -> #N/A | AT10: =$AT$3*(AH10) -> #N/A | AU10: =$AU$3*SUM(AR10,AS10,AT10) -> #N/A | AV10: =AU10/M10 -> #N/A | AW10: =POWER(1+K10,10)*M10 -> #N/A | AX10: =POWER(1+K10,10)*AH10 -> #N/A | AY10: =AX10/AH10 -> #N/A | AZ10: =AW10-AX10-FV(AI10/12,(10*12),AO10,-AJ10) -> #N/A | BA10: =AZ10/X10 -> #N/A
B11: 90007 | C11: =IFERROR(VLOOKUP(LEFT(B11,FIND("County",B11)-2),CaseShiller30,2,0),"No Data") -> No Data | D11: =_xlfn.XLOOKUP($B11,'Paste Snowflake Data Here'!$B$3:$B$1048576,'Paste Snowflake Data Here'!$D$3:$D$1048576) -> #N/A | F11: =_xlfn.XLOOKUP($B11,'Paste Snowflake Data Here'!$B$3:$B$1048576,'Paste Snowflake Data Here'!$I$3:$I$1048576) -> #N/A | G11: =_xlfn.XLOOKUP($B11,'Paste Snowflake Data Here'!$B$3:$B$1048576,'Paste Snowflake Data Here'!$J$3:$J$1048576) -> #N/A | K11: =IFERROR(VLOOKUP(LEFT(B11,FIND("County",B11)-2),CaseShiller30,5,0)*0.01,$K$3) -> 0.05 | L11: =$F11*$L$3 -> #N/A | M11: =$G11*$M$3 -> #N/A | N11: =AND(AF11<$AF$3,AG11<$AG$3) -> #N/A | O11: =AND(AP11<$AP$3,AQ11<$AQ$3) -> #N/A | P11: =AND(N11=FALSE,O11) -> #N/A | Q11: =AH11 -> #N/A | R11: =AU11 -> #N/A | S11: =AR11 -> #N/A | T11: =AZ11 -> #N/A | U11: =BA11 -> #N/A | V11: =AX11 -> #N/A | W11: =AY11 -> #N/A | X11: =$X$3*M11 -> #N/A | Y11: =$Y$3 -> 0.0625 | Z11: =M11-X11 -> #N/A | AA11: =Z11*'PMI Rate Est'!$J$6/12 -> #N/A | AB11: =$AB$3*M11/12 -> #N/A | AC11: =$AC$3*M11/12 -> #N/A | AD11: =MAX(J11*Y11/12,0) -> 0 | AE11: =-PMT(Y11/12,360,Z11) -> #N/A | AF11: =SUM(AE11,AC11,AB11,AA11)/(L11/12) -> #N/A | AG11: =SUM(AE11,AC11,AB11,AA11,AD11)/(L11/12) -> #N/A | AH11: =M11*$AH$3 -> #N/A | AI11: =Y11+$AI$3 -> 0.0625 | AJ11: =M11-X11-AH11 -> #N/A | AK11: =AH11*$AK$3/12 -> #N/A | AL11: =$AL$3*M11/12 -> #N/A | AM11: =$AM$3*M11/12 -> #N/A | AN11: =MAX(J11*Y11/12,0) -> 0 | AO11: =-PMT(AI11/12,360,AJ11) -> #N/A | AP11: =SUM(AO11,AM11,AL11)/(L11/12) -> #N/A | AQ11: =SUM(AO11,AM11,AL11,AK11,AN11)/(L11/12) -> #N/A | AR11: =$AR$3*AK11*12 -> #N/A | AS11: =$AS$3*(M11-X11) -> #N/A | AT11: =$AT$3*(AH11) -> #N/A | AU11: =$AU$3*SUM(AR11,AS11,AT11) -> #N/A | AV11: =AU11/M11 -> #N/A | AW11: =POWER(1+K11,10)*M11 -> #N/A | AX11: =POWER(1+K11,10)*AH11 -> #N/A | AY11: =AX11/AH11 -> #N/A | AZ11: =AW11-AX11-FV(AI11/12,(10*12),AO11,-AJ11) -> #N/A | BA11: =AZ11/X11 -> #N/A
B12: 90008 | C12: =IFERROR(VLOOKUP(LEFT(B12,FIND("County",B12)-2),CaseShiller30,2,0),"No Data") -> No Data | D12: =_xlfn.XLOOKUP($B12,'Paste Snowflake Data Here'!$B$3:$B$1048576,'Paste Snowflake Data Here'!$D$3:$D$1048576) -> #N/A | F12: =_xlfn.XLOOKUP($B12,'Paste Snowflake Data Here'!$B$3:$B$1048576,'Paste Snowflake Data Here'!$I$3:$I$1048576) -> #N/A | G12: =_xlfn.XLOOKUP($B12,'Paste Snowflake Data Here'!$B$3:$B$1048576,'Paste Snowflake Data Here'!$J$3:$J$1048576) -> #N/A | K12: =IFERROR(VLOOKUP(LEFT(B12,FIND("County",B12)-2),CaseShiller30,5,0)*0.01,$K$3) -> 0.05 | L12: =$F12*$L$3 -> #N/A | M12: =$G12*$M$3 -> #N/A | N12: =AND(AF12<$AF$3,AG12<$AG$3) -> #N/A | O12: =AND(AP12<$AP$3,AQ12<$AQ$3) -> #N/A | P12: =AND(N12=FALSE,O12) -> #N/A | Q12: =AH12 -> #N/A | R12: =AU12 -> #N/A | S12: =AR12 -> #N/A | T12: =AZ12 -> #N/A | U12: =BA12 -> #N/A | V12: =AX12 -> #N/A | W12: =AY12 -> #N/A | X12: =$X$3*M12 -> #N/A | Y12: =$Y$3 -> 0.0625 | Z12: =M12-X12 -> #N/A | AA12: =Z12*'PMI Rate Est'!$J$6/12 -> #N/A | AB12: =$AB$3*M12/12 -> #N/A | AC12: =$AC$3*M12/12 -> #N/A | AD12: =MAX(J12*Y12/12,0) -> 0 | AE12: =-PMT(Y12/12,360,Z12) -> #N/A | AF12: =SUM(AE12,AC12,AB12,AA12)/(L12/12) -> #N/A | AG12: =SUM(AE12,AC12,AB12,AA12,AD12)/(L12/12) -> #N/A | AH12: =M12*$AH$3 -> #N/A | AI12: =Y12+$AI$3 -> 0.0625 | AJ12: =M12-X12-AH12 -> #N/A | AK12: =AH12*$AK$3/12 -> #N/A | AL12: =$AL$3*M12/12 -> #N/A | AM12: =$AM$3*M12/12 -> #N/A | AN12: =MAX(J12*Y12/12,0) -> 0 | AO12: =-PMT(AI12/12,360,AJ12) -> #N/A | AP12: =SUM(AO12,AM12,AL12)/(L12/12) -> #N/A | AQ12: =SUM(AO12,AM12,AL12,AK12,AN12)/(L12/12) -> #N/A | AR12: =$AR$3*AK12*12 -> #N/A | AS12: =$AS$3*(M12-X12) -> #N/A | AT12: =$AT$3*(AH12) -> #N/A | AU12: =$AU$3*SUM(AR12,AS12,AT12) -> #N/A | AV12: =AU12/M12 -> #N/A | AW12: =POWER(1+K12,10)*M12 -> #N/A | AX12: =POWER(1+K12,10)*AH12 -> #N/A | AY12: =AX12/AH12 -> #N/A | AZ12: =AW12-AX12-FV(AI12/12,(10*12),AO12,-AJ12) -> #N/A | BA12: =AZ12/X12 -> #N/A
B13: 90011 | C13: =IFERROR(VLOOKUP(LEFT(B13,FIND("County",B13)-2),CaseShiller30,2,0),"No Data") -> No Data | D13: =_xlfn.XLOOKUP($B13,'Paste Snowflake Data Here'!$B$3:$B$1048576,'Paste Snowflake Data Here'!$D$3:$D$1048576) -> #N/A | F13: =_xlfn.XLOOKUP($B13,'Paste Snowflake Data Here'!$B$3:$B$1048576,'Paste Snowflake Data Here'!$I$3:$I$1048576) -> #N/A | G13: =_xlfn.XLOOKUP($B13,'Paste Snowflake Data Here'!$B$3:$B$1048576,'Paste Snowflake Data Here'!$J$3:$J$1048576) -> #N/A | K13: =IFERROR(VLOOKUP(LEFT(B13,FIND("County",B13)-2),CaseShiller30,5,0)*0.01,$K$3) -> 0.05 | L13: =$F13*$L$3 -> #N/A | M13: =$G13*$M$3 -> #N/A | N13: =AND(AF13<$AF$3,AG13<$AG$3) -> #N/A | O13: =AND(AP13<$AP$3,AQ13<$AQ$3) -> #N/A | P13: =AND(N13=FALSE,O13) -> #N/A | Q13: =AH13 -> #N/A | R13: =AU13 -> #N/A | S13: =AR13 -> #N/A | T13: =AZ13 -> #N/A | U13: =BA13 -> #N/A | V13: =AX13 -> #N/A | W13: =AY13 -> #N/A | X13: =$X$3*M13 -> #N/A | Y13: =$Y$3 -> 0.0625 | Z13: =M13-X13 -> #N/A | AA13: =Z13*'PMI Rate Est'!$J$6/12 -> #N/A | AB13: =$AB$3*M13/12 -> #N/A | AC13: =$AC$3*M13/12 -> #N/A | AD13: =MAX(J13*Y13/12,0) -> 0 | AE13: =-PMT(Y13/12,360,Z13) -> #N/A | AF13: =SUM(AE13,AC13,AB13,AA13)/(L13/12) -> #N/A | AG13: =SUM(AE13,AC13,AB13,AA13,AD13)/(L13/12) -> #N/A | AH13: =M13*$AH$3 -> #N/A | AI13: =Y13+$AI$3 -> 0.0625 | AJ13: =M13-X13-AH13 -> #N/A | AK13: =AH13*$AK$3/12 -> #N/A | AL13: =$AL$3*M13/12 -> #N/A | AM13: =$AM$3*M13/12 -> #N/A | AN13: =MAX(J13*Y13/12,0) -> 0 | AO13: =-PMT(AI13/12,360,AJ13) -> #N/A | AP13: =SUM(AO13,AM13,AL13)/(L13/12) -> #N/A | AQ13: =SUM(AO13,AM13,AL13,AK13,AN13)/(L13/12) -> #N/A | AR13: =$AR$3*AK13*12 -> #N/A | AS13: =$AS$3*(M13-X13) -> #N/A | AT13: =$AT$3*(AH13) -> #N/A | AU13: =$AU$3*SUM(AR13,AS13,AT13) -> #N/A | AV13: =AU13/M13 -> #N/A | AW13: =POWER(1+K13,10)*M13 -> #N/A | AX13: =POWER(1+K13,10)*AH13 -> #N/A | AY13: =AX13/AH13 -> #N/A | AZ13: =AW13-AX13-FV(AI13/12,(10*12),AO13,-AJ13) -> #N/A | BA13: =AZ13/X13 -> #N/A
B14: 90012 | C14: =IFERROR(VLOOKUP(LEFT(B14,FIND("County",B14)-2),CaseShiller30,2,0),"No Data") -> No Data | D14: =_xlfn.XLOOKUP($B14,'Paste Snowflake Data Here'!$B$3:$B$1048576,'Paste Snowflake Data Here'!$D$3:$D$1048576) -> #N/A | F14: =_xlfn.XLOOKUP($B14,'Paste Snowflake Data Here'!$B$3:$B$1048576,'Paste Snowflake Data Here'!$I$3:$I$1048576) -> #N/A | G14: =_xlfn.XLOOKUP($B14,'Paste Snowflake Data Here'!$B$3:$B$1048576,'Paste Snowflake Data Here'!$J$3:$J$1048576) -> #N/A | K14: =IFERROR(VLOOKUP(LEFT(B14,FIND("County",B14)-2),CaseShiller30,5,0)*0.01,$K$3) -> 0.05 | L14: =$F14*$L$3 -> #N/A | M14: =$G14*$M$3 -> #N/A | N14: =AND(AF14<$AF$3,AG14<$AG$3) -> #N/A | O14: =AND(AP14<$AP$3,AQ14<$AQ$3) -> #N/A | P14: =AND(N14=FALSE,O14) -> #N/A | Q14: =AH14 -> #N/A | R14: =AU14 -> #N/A | S14: =AR14 -> #N/A | T14: =AZ14 -> #N/A | U14: =BA14 -> #N/A | V14: =AX14 -> #N/A | W14: =AY14 -> #N/A | X14: =$X$3*M14 -> #N/A | Y14: =$Y$3 -> 0.0625 | Z14: =M14-X14 -> #N/A | AA14: =Z14*'PMI Rate Est'!$J$6/12 -> #N/A | AB14: =$AB$3*M14/12 -> #N/A | AC14: =$AC$3*M14/12 -> #N/A | AD14: =MAX(J14*Y14/12,0) -> 0 | AE14: =-PMT(Y14/12,360,Z14) -> #N/A | AF14: =SUM(AE14,AC14,AB14,AA14)/(L14/12) -> #N/A | AG14: =SUM(AE14,AC14,AB14,AA14,AD14)/(L14/12) -> #N/A | AH14: =M14*$AH$3 -> #N/A | AI14: =Y14+$AI$3 -> 0.0625 | AJ14: =M14-X14-AH14 -> #N/A | AK14: =AH14*$AK$3/12 -> #N/A | AL14: =$AL$3*M14/12 -> #N/A | AM14: =$AM$3*M14/12 -> #N/A | AN14: =MAX(J14*Y14/12,0) -> 0 | AO14: =-PMT(AI14/12,360,AJ14) -> #N/A | AP14: =SUM(AO14,AM14,AL14)/(L14/12) -> #N/A | AQ14: =SUM(AO14,AM14,AL14,AK14,AN14)/(L14/12) -> #N/A | AR14: =$AR$3*AK14*12 -> #N/A | AS14: =$AS$3*(M14-X14) -> #N/A | AT14: =$AT$3*(AH14) -> #N/A | AU14: =$AU$3*SUM(AR14,AS14,AT14) -> #N/A | AV14: =AU14/M14 -> #N/A | AW14: =POWER(1+K14,10)*M14 -> #N/A | AX14: =POWER(1+K14,10)*AH14 -> #N/A | AY14: =AX14/AH14 -> #N/A | AZ14: =AW14-AX14-FV(AI14/12,(10*12),AO14,-AJ14) -> #N/A | BA14: =AZ14/X14 -> #N/A
B15: 90013 | C15: =IFERROR(VLOOKUP(LEFT(B15,FIND("County",B15)-2),CaseShiller30,2,0),"No Data") -> No Data | D15: =_xlfn.XLOOKUP($B15,'Paste Snowflake Data Here'!$B$3:$B$1048576,'Paste Snowflake Data Here'!$D$3:$D$1048576) -> #N/A | F15: =_xlfn.XLOOKUP($B15,'Paste Snowflake Data Here'!$B$3:$B$1048576,'Paste Snowflake Data Here'!$I$3:$I$1048576) -> #N/A | G15: =_xlfn.XLOOKUP($B15,'Paste Snowflake Data Here'!$B$3:$B$1048576,'Paste Snowflake Data Here'!$J$3:$J$1048576) -> #N/A | K15: =IFERROR(VLOOKUP(LEFT(B15,FIND("County",B15)-2),CaseShiller30,5,0)*0.01,$K$3) -> 0.05 | L15: =$F15*$L$3 -> #N/A | M15: =$G15*$M$3 -> #N/A | N15: =AND(AF15<$AF$3,AG15<$AG$3) -> #N/A | O15: =AND(AP15<$AP$3,AQ15<$AQ$3) -> #N/A | P15: =AND(N15=FALSE,O15) -> #N/A | Q15: =AH15 -> #N/A | R15: =AU15 -> #N/A | S15: =AR15 -> #N/A | T15: =AZ15 -> #N/A | U15: =BA15 -> #N/A | V15: =AX15 -> #N/A | W15: =AY15 -> #N/A | X15: =$X$3*M15 -> #N/A | Y15: =$Y$3 -> 0.0625 | Z15: =M15-X15 -> #N/A | AA15: =Z15*'PMI Rate Est'!$J$6/12 -> #N/A | AB15: =$AB$3*M15/12 -> #N/A | AC15: =$AC$3*M15/12 -> #N/A | AD15: =MAX(J15*Y15/12,0) -> 0 | AE15: =-PMT(Y15/12,360,Z15) -> #N/A | AF15: =SUM(AE15,AC15,AB15,AA15)/(L15/12) -> #N/A | AG15: =SUM(AE15,AC15,AB15,AA15,AD15)/(L15/12) -> #N/A | AH15: =M15*$AH$3 -> #N/A | AI15: =Y15+$AI$3 -> 0.0625 | AJ15: =M15-X15-AH15 -> #N/A | AK15: =AH15*$AK$3/12 -> #N/A | AL15: =$AL$3*M15/12 -> #N/A | AM15: =$AM$3*M15/12 -> #N/A | AN15: =MAX(J15*Y15/12,0) -> 0 | AO15: =-PMT(AI15/12,360,AJ15) -> #N/A | AP15: =SUM(AO15,AM15,AL15)/(L15/12) -> #N/A | AQ15: =SUM(AO15,AM15,AL15,AK15,AN15)/(L15/12) -> #N/A | AR15: =$AR$3*AK15*12 -> #N/A | AS15: =$AS$3*(M15-X15) -> #N/A | AT15: =$AT$3*(AH15) -> #N/A | AU15: =$AU$3*SUM(AR15,AS15,AT15) -> #N/A | AV15: =AU15/M15 -> #N/A | AW15: =POWER(1+K15,10)*M15 -> #N/A | AX15: =POWER(1+K15,10)*AH15 -> #N/A | AY15: =AX15/AH15 -> #N/A | AZ15: =AW15-AX15-FV(AI15/12,(10*12),AO15,-AJ15) -> #N/A | BA15: =AZ15/X15 -> #N/A
B16: 90014 | C16: =IFERROR(VLOOKUP(LEFT(B16,FIND("County",B16)-2),CaseShiller30,2,0),"No Data") -> No Data | D16: =_xlfn.XLOOKUP($B16,'Paste Snowflake Data Here'!$B$3:$B$1048576,'Paste Snowflake Data Here'!$D$3:$D$1048576) -> #N/A | F16: =_xlfn.XLOOKUP($B16,'Paste Snowflake Data Here'!$B$3:$B$1048576,'Paste Snowflake Data Here'!$I$3:$I$1048576) -> #N/A | G16: =_xlfn.XLOOKUP($B16,'Paste Snowflake Data Here'!$B$3:$B$1048576,'Paste Snowflake Data Here'!$J$3:$J$1048576) -> #N/A | K16: =IFERROR(VLOOKUP(LEFT(B16,FIND("County",B16)-2),CaseShiller30,5,0)*0.01,$K$3) -> 0.05 | L16: =$F16*$L$3 -> #N/A | M16: =$G16*$M$3 -> #N/A | N16: =AND(AF16<$AF$3,AG16<$AG$3) -> #N/A | O16: =AND(AP16<$AP$3,AQ16<$AQ$3) -> #N/A | P16: =AND(N16=FALSE,O16) -> #N/A | Q16: =AH16 -> #N/A | R16: =AU16 -> #N/A | S16: =AR16 -> #N/A | T16: =AZ16 -> #N/A | U16: =BA16 -> #N/A | V16: =AX16 -> #N/A | W16: =AY16 -> #N/A | X16: =$X$3*M16 -> #N/A | Y16: =$Y$3 -> 0.0625 | Z16: =M16-X16 -> #N/A | AA16: =Z16*'PMI Rate Est'!$J$6/12 -> #N/A | AB16: =$AB$3*M16/12 -> #N/A | AC16: =$AC$3*M16/12 -> #N/A | AD16: =MAX(J16*Y16/12,0) -> 0 | AE16: =-PMT(Y16/12,360,Z16) -> #N/A | AF16: =SUM(AE16,AC16,AB16,AA16)/(L16/12) -> #N/A | AG16: =SUM(AE16,AC16,AB16,AA16,AD16)/(L16/12) -> #N/A | AH16: =M16*$AH$3 -> #N/A | AI16: =Y16+$AI$3 -> 0.0625 | AJ16: =M16-X16-AH16 -> #N/A | AK16: =AH16*$AK$3/12 -> #N/A | AL16: =$AL$3*M16/12 -> #N/A | AM16: =$AM$3*M16/12 -> #N/A | AN16: =MAX(J16*Y16/12,0) -> 0 | AO16: =-PMT(AI16/12,360,AJ16) -> #N/A | AP16: =SUM(AO16,AM16,AL16)/(L16/12) -> #N/A | AQ16: =SUM(AO16,AM16,AL16,AK16,AN16)/(L16/12) -> #N/A | AR16: =$AR$3*AK16*12 -> #N/A | AS16: =$AS$3*(M16-X16) -> #N/A | AT16: =$AT$3*(AH16) -> #N/A | AU16: =$AU$3*SUM(AR16,AS16,AT16) -> #N/A | AV16: =AU16/M16 -> #N/A | AW16: =POWER(1+K16,10)*M16 -> #N/A | AX16: =POWER(1+K16,10)*AH16 -> #N/A | AY16: =AX16/AH16 -> #N/A | AZ16: =AW16-AX16-FV(AI16/12,(10*12),AO16,-AJ16) -> #N/A | BA16: =AZ16/X16 -> #N/A
... B19: 90017 | C19: =IFERROR(VLOOKUP(LEFT(B19,FIND("County",B19)-2),CaseShiller30,2,0),"No Data") -> No Data | D19: =_xlfn.XLOOKUP($B19,'Paste Snowflake Data Here'!$B$3:$B$1048576,'Paste Snowflake Data Here'!$D$3:$D$1048576) -> #N/A | F19: =_xlfn.XLOOKUP($B19,'Paste Snowflake Data Here'!$B$3:$B$1048576,'Paste Snowflake Data Here'!$I$3:$I$1048576) -> #N/A | G19: =_xlfn.XLOOKUP($B19,'Paste Snowflake Data Here'!$B$3:$B$1048576,'Paste Snowflake Data Here'!$J$3:$J$1048576) -> #N/A | K19: =IFERROR(VLOOKUP(LEFT(B19,FIND("County",B19)-2),CaseShiller30,5,0)*0.01,$K$3) -> 0.05 | L19: =$F19*$L$3 -> #N/A | M19: =$G19*$M$3 -> #N/A | N19: =AND(AF19<$AF$3,AG19<$AG$3) -> #N/A | O19: =AND(AP19<$AP$3,AQ19<$AQ$3) -> #N/A | P19: =AND(N19=FALSE,O19) -> #N/A | Q19: =AH19 -> #N/A | R19: =AU19 -> #N/A | S19: =AR19 -> #N/A | T19: =AZ19 -> #N/A | U19: =BA19 -> #N/A | V19: =AX19 -> #N/A | W19: =AY19 -> #N/A | X19: =$X$3*M19 -> #N/A | Y19: =$Y$3 -> 0.0625 | Z19: =M19-X19 -> #N/A | AA19: =Z19*'PMI Rate Est'!$J$6/12 -> #N/A | AB19: =$AB$3*M19/12 -> #N/A | AC19: =$AC$3*M19/12 -> #N/A | AD19: =MAX(J19*Y19/12,0) -> 0 | AE19: =-PMT(Y19/12,360,Z19) -> #N/A | AF19: =SUM(AE19,AC19,AB19,AA19)/(L19/12) -> #N/A | AG19: =SUM(AE19,AC19,AB19,AA19,AD19)/(L19/12) -> #N/A | AH19: =M19*$AH$3 -> #N/A | AI19: =Y19+$AI$3 -> 0.0625 | AJ19: =M19-X19-AH19 -> #N/A | AK19: =AH19*$AK$3/12 -> #N/A | AL19: =$AL$3*M19/12 -> #N/A | AM19: =$AM$3*M19/12 -> #N/A | AN19: =MAX(J19*Y19/12,0) -> 0 | AO19: =-PMT(AI19/12,360,AJ19) -> #N/A | AP19: =SUM(AO19,AM19,AL19)/(L19/12) -> #N/A | AQ19: =SUM(AO19,AM19,AL19,AK19,AN19)/(L19/12) -> #N/A | AR19: =$AR$3*AK19*12 -> #N/A | AS19: =$AS$3*(M19-X19) -> #N/A | AT19: =$AT$3*(AH19) -> #N/A | AU19: =$AU$3*SUM(AR19,AS19,AT19) -> #N/A | AV19: =AU19/M19 -> #N/A | AW19: =POWER(1+K19,10)*M19 -> #N/A | AX19: =POWER(1+K19,10)*AH19 -> #N/A | AY19: =AX19/AH19 -> #N/A | AZ19: =AW19-AX19-FV(AI19/12,(10*12),AO19,-AJ19) -> #N/A | BA19: =AZ19/X19 -> #N/A
B20: 90018
B21: 90019
B22: 90020
B23: 90021
B24: 90022
B25: 90023
B26: 90024
B27: 90025
B28: 90026
B29: 90027
B30: 90028
B31: 90029
... B1739: 96162

Sheet Harper - Aggregate Model
B3: Key Assumptions: | K3: ='Assumptions & Borrower Profiles'!$C$11 -> 0.05 | L3: ='Assumptions & Borrower Profiles'!N5 -> 1.2 | M3: ='Assumptions & Borrower Profiles'!N8 -> 1.4 | Q3: ='Assumptions & Borrower Profiles'!N27 -> 0.25 | R3: 1 | X3: ='Assumptions & Borrower Profiles'!N11 -> 0.03 | Y3: ='Assumptions & Borrower Profiles'!$C$7 -> 0.0625 | AA3: ='Assumptions & Borrower Profiles'!$C$6 -> 620 | AB3: ='Assumptions & Borrower Profiles'!$C$17 -> 0.0135 | AC3: ='Assumptions & Borrower Profiles'!$C$18 -> 0.004 | AF3: ='Assumptions & Borrower Profiles'!$C$25 -> 0.35 | AG3: =AF3+0.1 -> 0.45 | AH3: =Q3 -> 0.25 | AI3: ='Assumptions & Borrower Profiles'!C7-'Assumptions & Borrower Profiles'!C8 -> 0 | AK3: 0 | AL3: =AB3 -> 0.0135 | AM3: =AC3 -> 0.004 | AP3: =AF3 -> 0.35 | AQ3: =AG3 -> 0.45 | AR3: 0 | AS3: ='Assumptions & Borrower Profiles'!$C$13 -> 0.02 | AT3: 0.03 | AU3: 0
B4: ZIP Code | C4: Code | D4: Population | E4: % African American | F4: Area Median Household Income | G4: Median Home Values | H4: Median Contract Rent | I4: DTI Avg | J4: Estimated Household Debt (incl mortgage) | K4: 30 Year Case Shiller Return / ann | L4: % AMI for calc | M4: % Median Home Value | N4: Passed DTI without HOM? | O4: Passed DTI with HOM? | P4: Threshold? | Q4: HOM Investment | R4: Grant for Fees/PMI | S4: Annual PMI | T4: Homeowner Equity after 10 Years | U4: % Gain from Downpayment | V4: HOM Investment after 10 Years | W4: % Gain on HOM Investment | X4: Downpayment | Y4: 30 Year Fixed Rate for 640 | Z4: 1st Principal Without Homium | AA4: PMI / Month | AB4: Tax / mo | AC4: Insurance / mo | AD4: Household Debt Service / mo | AE4: Monthly Payment | AF4: Front Ratio | AG4: Back Ratio | AH4: SAN Principal | AI4: 30 Year Fixed Rate for 640 WITH HOMIUM | AJ4: 1st Principal WITH Homium | AK4: PMI / Month | AL4: Tax / mo | AM4: Insurance / mo | AN4: Household Debt Service / mo | AO4: New Monthly Payment on 1st | AP4: Front Ratio with HOM | AQ4: Back Ratio with HOM | AR4: PMI Total (yrs) | AS4: Closing Fees | AT4: Origination Fees | AU4: Total Grant | AV4: % Total Grant of Home Value | AW4: Home Value after 10 years at X apprec | AX4: Homium SAN Value after 10 years | AY4: % Gain on HOM investment | AZ4: Homeowner Equity after 10 years | BA4: % Gain from Downpayment
B5: 90001 | C5: =IFERROR(VLOOKUP(LEFT(B5,FIND("County",B5)-2),CaseShiller30,2,0),"No Data") -> No Data | D5: =_xlfn.XLOOKUP($B5,'Paste Snowflake Data Here'!$B$3:$B$1048576,'Paste Snowflake Data Here'!$D$3:$D$1048576) -> #N/A | F5: =_xlfn.XLOOKUP($B5,'Paste Snowflake Data Here'!$B$3:$B$1048576,'Paste Snowflake Data Here'!$I$3:$I$1048576) -> #N/A | G5: =_xlfn.XLOOKUP($B5,'Paste Snowflake Data Here'!$B$3:$B$1048576,'Paste Snowflake Data Here'!$J$3:$J$1048576) -> #N/A | K5: =IFERROR(VLOOKUP(LEFT(B5,FIND("County",B5)-2),CaseShiller30,5,0)*0.01,$K$3) -> 0.05 | L5: =$F5*$L$3 -> #N/A | M5: =$G5*$M$3 -> #N/A | N5: =AND(AF5<$AF$3,AG5<$AG$3) -> #N/A | O5: =AND(AP5<$AP$3,AQ5<$AQ$3) -> #N/A | P5: =AND(N5=FALSE,O5) -> #N/A | Q5: =AH5 -> #N/A | R5: =AU5 -> #N/A | S5: =AR5 -> #N/A | T5: =AZ5 -> #N/A | U5: =BA5 -> #N/A | V5: =AX5 -> #N/A | W5: =AY5 -> #N/A | X5: =$X$3*M5 -> #N/A | Y5: =$Y$3 -> 0.0625 | Z5: =M5-X5 -> #N/A | AA5: =Z5*'PMI Rate Est'!$J$6/12 -> #N/A | AB5: =$AB$3*M5/12 -> #N/A | AC5: =$AC$3*M5/12 -> #N/A | AD5: =MAX(J5*Y5/12,0) -> 0 | AE5: =-PMT(Y5/12,360,Z5) -> #N/A | AF5: =SUM(AE5,AC5,AB5,AA5)/(L5/12) -> #N/A | AG5: =SUM(AE5,AC5,AB5,AA5,AD5)/(L5/12) -> #N/A | AH5: =M5*$AH$3 -> #N/A | AI5: =Y5+$AI$3 -> 0.0625 | AJ5: =M5-X5-AH5 -> #N/A | AK5: =AH5*$AK$3/12 -> #N/A | AL5: =$AL$3*M5/12 -> #N/A | AM5: =$AM$3*M5/12 -> #N/A | AN5: =MAX(J5*Y5/12,0) -> 0 | AO5: =-PMT(AI5/12,360,AJ5) -> #N/A | AP5: =SUM(AO5,AM5,AL5)/(L5/12) -> #N/A | AQ5: =SUM(AO5,AM5,AL5,AK5,AN5)/(L5/12) -> #N/A | AR5: =$AR$3*AK5*12 -> #N/A | AS5: =$AS$3*(M5-X5) -> #N/A | AT5: =$AT$3*(AH5) -> #N/A | AU5: =$AU$3*SUM(AR5,AS5,AT5) -> #N/A | AV5: =AU5/M5 -> #N/A | AW5: =POWER(1+K5,10)*M5 -> #N/A | AX5: =POWER(1+K5,10)*AH5 -> #N/A | AY5: =AX5/AH5 -> #N/A | AZ5: =AW5-AX5-FV(AI5/12,(10*12),AO5,-AJ5) -> #N/A | BA5: =AZ5/X5 -> #N/A
B6: 90002 | C6: =IFERROR(VLOOKUP(LEFT(B6,FIND("County",B6)-2),CaseShiller30,2,0),"No Data") -> No Data | D6: =_xlfn.XLOOKUP($B6,'Paste Snowflake Data Here'!$B$3:$B$1048576,'Paste Snowflake Data Here'!$D$3:$D$1048576) -> #N/A | F6: =_xlfn.XLOOKUP($B6,'Paste Snowflake Data Here'!$B$3:$B$1048576,'Paste Snowflake Data Here'!$I$3:$I$1048576) -> #N/A | G6: =_xlfn.XLOOKUP($B6,'Paste Snowflake Data Here'!$B$3:$B$1048576,'Paste Snowflake Data Here'!$J$3:$J$1048576) -> #N/A | K6: =IFERROR(VLOOKUP(LEFT(B6,FIND("County",B6)-2),CaseShiller30,5,0)*0.01,$K$3) -> 0.05 | L6: =$F6*$L$3 -> #N/A | M6: =$G6*$M$3 -> #N/A | N6: =AND(AF6<$AF$3,AG6<$AG$3) -> #N/A | O6: =AND(AP6<$AP$3,AQ6<$AQ$3) -> #N/A | P6: =AND(N6=FALSE,O6) -> #N/A | Q6: =AH6 -> #N/A | R6: =AU6 -> #N/A | S6: =AR6 -> #N/A | T6: =AZ6 -> #N/A | U6: =BA6 -> #N/A | V6: =AX6 -> #N/A | W6: =AY6 -> #N/A | X6: =$X$3*M6 -> #N/A | Y6: =$Y$3 -> 0.0625 | Z6: =M6-X6 -> #N/A | AA6: =Z6*'PMI Rate Est'!$J$6/12 -> #N/A | AB6: =$AB$3*M6/12 -> #N/A | AC6: =$AC$3*M6/12 -> #N/A | AD6: =MAX(J6*Y6/12,0) -> 0 | AE6: =-PMT(Y6/12,360,Z6) -> #N/A | AF6: =SUM(AE6,AC6,AB6,AA6)/(L6/12) -> #N/A | AG6: =SUM(AE6,AC6,AB6,AA6,AD6)/(L6/12) -> #N/A | AH6: =M6*$AH$3 -> #N/A | AI6: =Y6+$AI$3 -> 0.0625 | AJ6: =M6-X6-AH6 -> #N/A | AK6: =AH6*$AK$3/12 -> #N/A | AL6: =$AL$3*M6/12 -> #N/A | AM6: =$AM$3*M6/12 -> #N/A | AN6: =MAX(J6*Y6/12,0) -> 0 | AO6: =-PMT(AI6/12,360,AJ6) -> #N/A | AP6: =SUM(AO6,AM6,AL6)/(L6/12) -> #N/A | AQ6: =SUM(AO6,AM6,AL6,AK6,AN6)/(L6/12) -> #N/A | AR6: =$AR$3*AK6*12 -> #N/A | AS6: =$AS$3*(M6-X6) -> #N/A | AT6: =$AT$3*(AH6) -> #N/A | AU6: =$AU$3*SUM(AR6,AS6,AT6) -> #N/A | AV6: =AU6/M6 -> #N/A | AW6: =POWER(1+K6,10)*M6 -> #N/A | AX6: =POWER(1+K6,10)*AH6 -> #N/A | AY6: =AX6/AH6 -> #N/A | AZ6: =AW6-AX6-FV(AI6/12,(10*12),AO6,-AJ6) -> #N/A | BA6: =AZ6/X6 -> #N/A
B7: 90003 | C7: =IFERROR(VLOOKUP(LEFT(B7,FIND("County",B7)-2),CaseShiller30,2,0),"No Data") -> No Data | D7: =_xlfn.XLOOKUP($B7,'Paste Snowflake Data Here'!$B$3:$B$1048576,'Paste Snowflake Data Here'!$D$3:$D$1048576) -> #N/A | F7: =_xlfn.XLOOKUP($B7,'Paste Snowflake Data Here'!$B$3:$B$1048576,'Paste Snowflake Data Here'!$I$3:$I$1048576) -> #N/A | G7: =_xlfn.XLOOKUP($B7,'Paste Snowflake Data Here'!$B$3:$B$1048576,'Paste Snowflake Data Here'!$J$3:$J$1048576) -> #N/A | K7: =IFERROR(VLOOKUP(LEFT(B7,FIND("County",B7)-2),CaseShiller30,5,0)*0.01,$K$3) -> 0.05 | L7: =$F7*$L$3 -> #N/A | M7: =$G7*$M$3 -> #N/A | N7: =AND(AF7<$AF$3,AG7<$AG$3) -> #N/A | O7: =AND(AP7<$AP$3,AQ7<$AQ$3) -> #N/A | P7: =AND(N7=FALSE,O7) -> #N/A | Q7: =AH7 -> #N/A | R7: =AU7 -> #N/A | S7: =AR7 -> #N/A | T7: =AZ7 -> #N/A | U7: =BA7 -> #N/A | V7: =AX7 -> #N/A | W7: =AY7 -> #N/A | X7: =$X$3*M7 -> #N/A | Y7: =$Y$3 -> 0.0625 | Z7: =M7-X7 -> #N/A | AA7: =Z7*'PMI Rate Est'!$J$6/12 -> #N/A | AB7: =$AB$3*M7/12 -> #N/A | AC7: =$AC$3*M7/12 -> #N/A | AD7: =MAX(J7*Y7/12,0) -> 0 | AE7: =-PMT(Y7/12,360,Z7) -> #N/A | AF7: =SUM(AE7,AC7,AB7,AA7)/(L7/12) -> #N/A | AG7: =SUM(AE7,AC7,AB7,AA7,AD7)/(L7/12) -> #N/A | AH7: =M7*$AH$3 -> #N/A | AI7: =Y7+$AI$3 -> 0.0625 | AJ7: =M7-X7-AH7 -> #N/A | AK7: =AH7*$AK$3/12 -> #N/A | AL7: =$AL$3*M7/12 -> #N/A | AM7: =$AM$3*M7/12 -> #N/A | AN7: =MAX(J7*Y7/12,0) -> 0 | AO7: =-PMT(AI7/12,360,AJ7) -> #N/A | AP7: =SUM(AO7,AM7,AL7)/(L7/12) -> #N/A | AQ7: =SUM(AO7,AM7,AL7,AK7,AN7)/(L7/12) -> #N/A | AR7: =$AR$3*AK7*12 -> #N/A | AS7: =$AS$3*(M7-X7) -> #N/A | AT7: =$AT$3*(AH7) -> #N/A | AU7: =$AU$3*SUM(AR7,AS7,AT7) -> #N/A | AV7: =AU7/M7 -> #N/A | AW7: =POWER(1+K7,10)*M7 -> #N/A | AX7: =POWER(1+K7,10)*AH7 -> #N/A | AY7: =AX7/AH7 -> #N/A | AZ7: =AW7-AX7-FV(AI7/12,(10*12),AO7,-AJ7) -> #N/A | BA7: =AZ7/X7 -> #N/A
B8: 90004 | C8: =IFERROR(VLOOKUP(LEFT(B8,FIND("County",B8)-2),CaseShiller30,2,0),"No Data") -> No Data | D8: =_xlfn.XLOOKUP($B8,'Paste Snowflake Data Here'!$B$3:$B$1048576,'Paste Snowflake Data Here'!$D$3:$D$1048576) -> #N/A | F8: =_xlfn.XLOOKUP($B8,'Paste Snowflake Data Here'!$B$3:$B$1048576,'Paste Snowflake Data Here'!$I$3:$I$1048576) -> #N/A | G8: =_xlfn.XLOOKUP($B8,'Paste Snowflake Data Here'!$B$3:$B$1048576,'Paste Snowflake Data Here'!$J$3:$J$1048576) -> #N/A | K8: =IFERROR(VLOOKUP(LEFT(B8,FIND("County",B8)-2),CaseShiller30,5,0)*0.01,$K$3) -> 0.05 | L8: =$F8*$L$3 -> #N/A | M8: =$G8*$M$3 -> #N/A | N8: =AND(AF8<$AF$3,AG8<$AG$3) -> #N/A | O8: =AND(AP8<$AP$3,AQ8<$AQ$3) -> #N/A | P8: =AND(N8=FALSE,O8) -> #N/A | Q8: =AH8 -> #N/A | R8: =AU8 -> #N/A | S8: =AR8 -> #N/A | T8: =AZ8 -> #N/A | U8: =BA8 -> #N/A | V8: =AX8 -> #N/A | W8: =AY8 -> #N/A | X8: =$X$3*M8 -> #N/A | Y8: =$Y$3 -> 0.0625 | Z8: =M8-X8 -> #N/A | AA8: =Z8*'PMI Rate Est'!$J$6/12 -> #N/A | AB8: =$AB$3*M8/12 -> #N/A | AC8: =$AC$3*M8/12 -> #N/A | AD8: =MAX(J8*Y8/12,0) -> 0 | AE8: =-PMT(Y8/12,360,Z8) -> #N/A | AF8: =SUM(AE8,AC8,AB8,AA8)/(L8/12) -> #N/A | AG8: =SUM(AE8,AC8,AB8,AA8,AD8)/(L8/12) -> #N/A | AH8: =M8*$AH$3 -> #N/A | AI8: =Y8+$AI$3 -> 0.0625 | AJ8: =M8-X8-AH8 -> #N/A | AK8: =AH8*$AK$3/12 -> #N/A | AL8: =$AL$3*M8/12 -> #N/A | AM8: =$AM$3*M8/12 -> #N/A | AN8: =MAX(J8*Y8/12,0) -> 0 | AO8: =-PMT(AI8/12,360,AJ8) -> #N/A | AP8: =SUM(AO8,AM8,AL8)/(L8/12) -> #N/A | AQ8: =SUM(AO8,AM8,AL8,AK8,AN8)/(L8/12) -> #N/A | AR8: =$AR$3*AK8*12 -> #N/A | AS8: =$AS$3*(M8-X8) -> #N/A | AT8: =$AT$3*(AH8) -> #N/A | AU8: =$AU$3*SUM(AR8,AS8,AT8) -> #N/A | AV8: =AU8/M8 -> #N/A | AW8: =POWER(1+K8,10)*M8 -> #N/A | AX8: =POWER(1+K8,10)*AH8 -> #N/A | AY8: =AX8/AH8 -> #N/A | AZ8: =AW8-AX8-FV(AI8/12,(10*12),AO8,-AJ8) -> #N/A | BA8: =AZ8/X8 -> #N/A
B9: 90005 | C9: =IFERROR(VLOOKUP(LEFT(B9,FIND("County",B9)-2),CaseShiller30,2,0),"No Data") -> No Data | D9: =_xlfn.XLOOKUP($B9,'Paste Snowflake Data Here'!$B$3:$B$1048576,'Paste Snowflake Data Here'!$D$3:$D$1048576) -> #N/A | F9: =_xlfn.XLOOKUP($B9,'Paste Snowflake Data Here'!$B$3:$B$1048576,'Paste Snowflake Data Here'!$I$3:$I$1048576) -> #N/A | G9: =_xlfn.XLOOKUP($B9,'Paste Snowflake Data Here'!$B$3:$B$1048576,'Paste Snowflake Data Here'!$J$3:$J$1048576) -> #N/A | K9: =IFERROR(VLOOKUP(LEFT(B9,FIND("County",B9)-2),CaseShiller30,5,0)*0.01,$K$3) -> 0.05 | L9: =$F9*$L$3 -> #N/A | M9: =$G9*$M$3 -> #N/A | N9: =AND(AF9<$AF$3,AG9<$AG$3) -> #N/A | O9: =AND(AP9<$AP$3,AQ9<$AQ$3) -> #N/A | P9: =AND(N9=FALSE,O9) -> #N/A | Q9: =AH9 -> #N/A | R9: =AU9 -> #N/A | S9: =AR9 -> #N/A | T9: =AZ9 -> #N/A | U9: =BA9 -> #N/A | V9: =AX9 -> #N/A | W9: =AY9 -> #N/A | X9: =$X$3*M9 -> #N/A | Y9: =$Y$3 -> 0.0625 | Z9: =M9-X9 -> #N/A | AA9: =Z9*'PMI Rate Est'!$J$6/12 -> #N/A | AB9: =$AB$3*M9/12 -> #N/A | AC9: =$AC$3*M9/12 -> #N/A | AD9: =MAX(J9*Y9/12,0) -> 0 | AE9: =-PMT(Y9/12,360,Z9) -> #N/A | AF9: =SUM(AE9,AC9,AB9,AA9)/(L9/12) -> #N/A | AG9: =SUM(AE9,AC9,AB9,AA9,AD9)/(L9/12) -> #N/A | AH9: =M9*$AH$3 -> #N/A | AI9: =Y9+$AI$3 -> 0.0625 | AJ9: =M9-X9-AH9 -> #N/A | AK9: =AH9*$AK$3/12 -> #N/A | AL9: =$AL$3*M9/12 -> #N/A | AM9: =$AM$3*M9/12 -> #N/A | AN9: =MAX(J9*Y9/12,0) -> 0 | AO9: =-PMT(AI9/12,360,AJ9) -> #N/A | AP9: =SUM(AO9,AM9,AL9)/(L9/12) -> #N/A | AQ9: =SUM(AO9,AM9,AL9,AK9,AN9)/(L9/12) -> #N/A | AR9: =$AR$3*AK9*12 -> #N/A | AS9: =$AS$3*(M9-X9) -> #N/A | AT9: =$AT$3*(AH9) -> #N/A | AU9: =$AU$3*SUM(AR9,AS9,AT9) -> #N/A | AV9: =AU9/M9 -> #N/A | AW9: =POWER(1+K9,10)*M9 -> #N/A | AX9: =POWER(1+K9,10)*AH9 -> #N/A | AY9: =AX9/AH9 -> #N/A | AZ9: =AW9-AX9-FV(AI9/12,(10*12),AO9,-AJ9) -> #N/A | BA9: =AZ9/X9 -> #N/A
B10: 90006 | C10: =IFERROR(VLOOKUP(LEFT(B10,FIND("County",B10)-2),CaseShiller30,2,0),"No Data") -> No Data | D10: =_xlfn.XLOOKUP($B10,'Paste Snowflake Data Here'!$B$3:$B$1048576,'Paste Snowflake Data Here'!$D$3:$D$1048576) -> #N/A | F10: =_xlfn.XLOOKUP($B10,'Paste Snowflake Data Here'!$B$3:$B$1048576,'Paste Snowflake Data Here'!$I$3:$I$1048576) -> #N/A | G10: =_xlfn.XLOOKUP($B10,'Paste Snowflake Data Here'!$B$3:$B$1048576,'Paste Snowflake Data Here'!$J$3:$J$1048576) -> #N/A | K10: =IFERROR(VLOOKUP(LEFT(B10,FIND("County",B10)-2),CaseShiller30,5,0)*0.01,$K$3) -> 0.05 | L10: =$F10*$L$3 -> #N/A | M10: =$G10*$M$3 -> #N/A | N10: =AND(AF10<$AF$3,AG10<$AG$3) -> #N/A | O10: =AND(AP10<$AP$3,AQ10<$AQ$3) -> #N/A | P10: =AND(N10=FALSE,O10) -> #N/A | Q10: =AH10 -> #N/A | R10: =AU10 -> #N/A | S10: =AR10 -> #N/A | T10: =AZ10 -> #N/A | U10: =BA10 -> #N/A | V10: =AX10 -> #N/A | W10: =AY10 -> #N/A | X10: =$X$3*M10 -> #N/A | Y10: =$Y$3 -> 0.0625 | Z10: =M10-X10 -> #N/A | AA10: =Z10*'PMI Rate Est'!$J$6/12 -> #N/A | AB10: =$AB$3*M10/12 -> #N/A | AC10: =$AC$3*M10/12 -> #N/A | AD10: =MAX(J10*Y10/12,0) -> 0 | AE10: =-PMT(Y10/12,360,Z10) -> #N/A | AF10: =SUM(AE10,AC10,AB10,AA10)/(L10/12) -> #N/A | AG10: =SUM(AE10,AC10,AB10,AA10,AD10)/(L10/12) -> #N/A | AH10: =M10*$AH$3 -> #N/A | AI10: =Y10+$AI$3 -> 0.0625 | AJ10: =M10-X10-AH10 -> #N/A | AK10: =AH10*$AK$3/12 -> #N/A | AL10: =$AL$3*M10/12 -> #N/A | AM10: =$AM$3*M10/12 -> #N/A | AN10: =MAX(J10*Y10/12,0) -> 0 | AO10: =-PMT(AI10/12,360,AJ10) -> #N/A | AP10: =SUM(AO10,AM10,AL10)/(L10/12) -> #N/A | AQ10: =SUM(AO10,AM10,AL10,AK10,AN10)/(L10/12) -> #N/A | AR10: =$AR$3*AK10*12 -> #N/A | AS10: =$AS$3*(M10-X10) -> #N/A | AT10: =$AT$3*(AH10) -> #N/A | AU10: =$AU$3*SUM(AR10,AS10,AT10) -> #N/A | AV10: =AU10/M10 -> #N/A | AW10: =POWER(1+K10,10)*M10 -> #N/A | AX10: =POWER(1+K10,10)*AH10 -> #N/A | AY10: =AX10/AH10 -> #N/A | AZ10: =AW10-AX10-FV(AI10/12,(10*12),AO10,-AJ10) -> #N/A | BA10: =AZ10/X10 -> #N/A
B11: 90007 | C11: =IFERROR(VLOOKUP(LEFT(B11,FIND("County",B11)-2),CaseShiller30,2,0),"No Data") -> No Data | D11: =_xlfn.XLOOKUP($B11,'Paste Snowflake Data Here'!$B$3:$B$1048576,'Paste Snowflake Data Here'!$D$3:$D$1048576) -> #N/A | F11: =_xlfn.XLOOKUP($B11,'Paste Snowflake Data Here'!$B$3:$B$1048576,'Paste Snowflake Data Here'!$I$3:$I$1048576) -> #N/A | G11: =_xlfn.XLOOKUP($B11,'Paste Snowflake Data Here'!$B$3:$B$1048576,'Paste Snowflake Data Here'!$J$3:$J$1048576) -> #N/A | K11: =IFERROR(VLOOKUP(LEFT(B11,FIND("County",B11)-2),CaseShiller30,5,0)*0.01,$K$3) -> 0.05 | L11: =$F11*$L$3 -> #N/A | M11: =$G11*$M$3 -> #N/A | N11: =AND(AF11<$AF$3,AG11<$AG$3) -> #N/A | O11: =AND(AP11<$AP$3,AQ11<$AQ$3) -> #N/A | P11: =AND(N11=FALSE,O11) -> #N/A | Q11: =AH11 -> #N/A | R11: =AU11 -> #N/A | S11: =AR11 -> #N/A | T11: =AZ11 -> #N/A | U11: =BA11 -> #N/A | V11: =AX11 -> #N/A | W11: =AY11 -> #N/A | X11: =$X$3*M11 -> #N/A | Y11: =$Y$3 -> 0.0625 | Z11: =M11-X11 -> #N/A | AA11: =Z11*'PMI Rate Est'!$J$6/12 -> #N/A | AB11: =$AB$3*M11/12 -> #N/A | AC11: =$AC$3*M11/12 -> #N/A | AD11: =MAX(J11*Y11/12,0) -> 0 | AE11: =-PMT(Y11/12,360,Z11) -> #N/A | AF11: =SUM(AE11,AC11,AB11,AA11)/(L11/12) -> #N/A | AG11: =SUM(AE11,AC11,AB11,AA11,AD11)/(L11/12) -> #N/A | AH11: =M11*$AH$3 -> #N/A | AI11: =Y11+$AI$3 -> 0.0625 | AJ11: =M11-X11-AH11 -> #N/A | AK11: =AH11*$AK$3/12 -> #N/A | AL11: =$AL$3*M11/12 -> #N/A | AM11: =$AM$3*M11/12 -> #N/A | AN11: =MAX(J11*Y11/12,0) -> 0 | AO11: =-PMT(AI11/12,360,AJ11) -> #N/A | AP11: =SUM(AO11,AM11,AL11)/(L11/12) -> #N/A | AQ11: =SUM(AO11,AM11,AL11,AK11,AN11)/(L11/12) -> #N/A | AR11: =$AR$3*AK11*12 -> #N/A | AS11: =$AS$3*(M11-X11) -> #N/A | AT11: =$AT$3*(AH11) -> #N/A | AU11: =$AU$3*SUM(AR11,AS11,AT11) -> #N/A | AV11: =AU11/M11 -> #N/A | AW11: =POWER(1+K11,10)*M11 -> #N/A | AX11: =POWER(1+K11,10)*AH11 -> #N/A | AY11: =AX11/AH11 -> #N/A | AZ11: =AW11-AX11-FV(AI11/12,(10*12),AO11,-AJ11) -> #N/A | BA11: =AZ11/X11 -> #N/A
B12: 90008 | C12: =IFERROR(VLOOKUP(LEFT(B12,FIND("County",B12)-2),CaseShiller30,2,0),"No Data") -> No Data | D12: =_xlfn.XLOOKUP($B12,'Paste Snowflake Data Here'!$B$3:$B$1048576,'Paste Snowflake Data Here'!$D$3:$D$1048576) -> #N/A | F12: =_xlfn.XLOOKUP($B12,'Paste Snowflake Data Here'!$B$3:$B$1048576,'Paste Snowflake Data Here'!$I$3:$I$1048576) -> #N/A | G12: =_xlfn.XLOOKUP($B12,'Paste Snowflake Data Here'!$B$3:$B$1048576,'Paste Snowflake Data Here'!$J$3:$J$1048576) -> #N/A | K12: =IFERROR(VLOOKUP(LEFT(B12,FIND("County",B12)-2),CaseShiller30,5,0)*0.01,$K$3) -> 0.05 | L12: =$F12*$L$3 -> #N/A | M12: =$G12*$M$3 -> #N/A | N12: =AND(AF12<$AF$3,AG12<$AG$3) -> #N/A | O12: =AND(AP12<$AP$3,AQ12<$AQ$3) -> #N/A | P12: =AND(N12=FALSE,O12) -> #N/A | Q12: =AH12 -> #N/A | R12: =AU12 -> #N/A | S12: =AR12 -> #N/A | T12: =AZ12 -> #N/A | U12: =BA12 -> #N/A | V12: =AX12 -> #N/A | W12: =AY12 -> #N/A | X12: =$X$3*M12 -> #N/A | Y12: =$Y$3 -> 0.0625 | Z12: =M12-X12 -> #N/A | AA12: =Z12*'PMI Rate Est'!$J$6/12 -> #N/A | AB12: =$AB$3*M12/12 -> #N/A | AC12: =$AC$3*M12/12 -> #N/A | AD12: =MAX(J12*Y12/12,0) -> 0 | AE12: =-PMT(Y12/12,360,Z12) -> #N/A | AF12: =SUM(AE12,AC12,AB12,AA12)/(L12/12) -> #N/A | AG12: =SUM(AE12,AC12,AB12,AA12,AD12)/(L12/12) -> #N/A | AH12: =M12*$AH$3 -> #N/A | AI12: =Y12+$AI$3 -> 0.0625 | AJ12: =M12-X12-AH12 -> #N/A | AK12: =AH12*$AK$3/12 -> #N/A | AL12: =$AL$3*M12/12 -> #N/A | AM12: =$AM$3*M12/12 -> #N/A | AN12: =MAX(J12*Y12/12,0) -> 0 | AO12: =-PMT(AI12/12,360,AJ12) -> #N/A | AP12: =SUM(AO12,AM12,AL12)/(L12/12) -> #N/A | AQ12: =SUM(AO12,AM12,AL12,AK12,AN12)/(L12/12) -> #N/A | AR12: =$AR$3*AK12*12 -> #N/A | AS12: =$AS$3*(M12-X12) -> #N/A | AT12: =$AT$3*(AH12) -> #N/A | AU12: =$AU$3*SUM(AR12,AS12,AT12) -> #N/A | AV12: =AU12/M12 -> #N/A | AW12: =POWER(1+K12,10)*M12 -> #N/A | AX12: =POWER(1+K12,10)*AH12 -> #N/A | AY12: =AX12/AH12 -> #N/A | AZ12: =AW12-AX12-FV(AI12/12,(10*12),AO12,-AJ12) -> #N/A | BA12: =AZ12/X12 -> #N/A
B13: 90011 | C13: =IFERROR(VLOOKUP(LEFT(B13,FIND("County",B13)-2),CaseShiller30,2,0),"No Data") -> No Data | D13: =_xlfn.XLOOKUP($B13,'Paste Snowflake Data Here'!$B$3:$B$1048576,'Paste Snowflake Data Here'!$D$3:$D$1048576) -> #N/A | F13: =_xlfn.XLOOKUP($B13,'Paste Snowflake Data Here'!$B$3:$B$1048576,'Paste Snowflake Data Here'!$I$3:$I$1048576) -> #N/A | G13: =_xlfn.XLOOKUP($B13,'Paste Snowflake Data Here'!$B$3:$B$1048576,'Paste Snowflake Data Here'!$J$3:$J$1048576) -> #N/A | K13: =IFERROR(VLOOKUP(LEFT(B13,FIND("County",B13)-2),CaseShiller30,5,0)*0.01,$K$3) -> 0.05 | L13: =$F13*$L$3 -> #N/A | M13: =$G13*$M$3 -> #N/A | N13: =AND(AF13<$AF$3,AG13<$AG$3) -> #N/A | O13: =AND(AP13<$AP$3,AQ13<$AQ$3) -> #N/A | P13: =AND(N13=FALSE,O13) -> #N/A | Q13: =AH13 -> #N/A | R13: =AU13 -> #N/A | S13: =AR13 -> #N/A | T13: =AZ13 -> #N/A | U13: =BA13 -> #N/A | V13: =AX13 -> #N/A | W13: =AY13 -> #N/A | X13: =$X$3*M13 -> #N/A | Y13: =$Y$3 -> 0.0625 | Z13: =M13-X13 -> #N/A | AA13: =Z13*'PMI Rate Est'!$J$6/12 -> #N/A | AB13: =$AB$3*M13/12 -> #N/A | AC13: =$AC$3*M13/12 -> #N/A | AD13: =MAX(J13*Y13/12,0) -> 0 | AE13: =-PMT(Y13/12,360,Z13) -> #N/A | AF13: =SUM(AE13,AC13,AB13,AA13)/(L13/12) -> #N/A | AG13: =SUM(AE13,AC13,AB13,AA13,AD13)/(L13/12) -> #N/A | AH13: =M13*$AH$3 -> #N/A | AI13: =Y13+$AI$3 -> 0.0625 | AJ13: =M13-X13-AH13 -> #N/A | AK13: =AH13*$AK$3/12 -> #N/A | AL13: =$AL$3*M13/12 -> #N/A | AM13: =$AM$3*M13/12 -> #N/A | AN13: =MAX(J13*Y13/12,0) -> 0 | AO13: =-PMT(AI13/12,360,AJ13) -> #N/A | AP13: =SUM(AO13,AM13,AL13)/(L13/12) -> #N/A | AQ13: =SUM(AO13,AM13,AL13,AK13,AN13)/(L13/12) -> #N/A | AR13: =$AR$3*AK13*12 -> #N/A | AS13: =$AS$3*(M13-X13) -> #N/A | AT13: =$AT$3*(AH13) -> #N/A | AU13: =$AU$3*SUM(AR13,AS13,AT13) -> #N/A | AV13: =AU13/M13 -> #N/A | AW13: =POWER(1+K13,10)*M13 -> #N/A | AX13: =POWER(1+K13,10)*AH13 -> #N/A | AY13: =AX13/AH13 -> #N/A | AZ13: =AW13-AX13-FV(AI13/12,(10*12),AO13,-AJ13) -> #N/A | BA13: =AZ13/X13 -> #N/A
B14: 90012 | C14: =IFERROR(VLOOKUP(LEFT(B14,FIND("County",B14)-2),CaseShiller30,2,0),"No Data") -> No Data | D14: =_xlfn.XLOOKUP($B14,'Paste Snowflake Data Here'!$B$3:$B$1048576,'Paste Snowflake Data Here'!$D$3:$D$1048576) -> #N/A | F14: =_xlfn.XLOOKUP($B14,'Paste Snowflake Data Here'!$B$3:$B$1048576,'Paste Snowflake Data Here'!$I$3:$I$1048576) -> #N/A | G14: =_xlfn.XLOOKUP($B14,'Paste Snowflake Data Here'!$B$3:$B$1048576,'Paste Snowflake Data Here'!$J$3:$J$1048576) -> #N/A | K14: =IFERROR(VLOOKUP(LEFT(B14,FIND("County",B14)-2),CaseShiller30,5,0)*0.01,$K$3) -> 0.05 | L14: =$F14*$L$3 -> #N/A | M14: =$G14*$M$3 -> #N/A | N14: =AND(AF14<$AF$3,AG14<$AG$3) -> #N/A | O14: =AND(AP14<$AP$3,AQ14<$AQ$3) -> #N/A | P14: =AND(N14=FALSE,O14) -> #N/A | Q14: =AH14 -> #N/A | R14: =AU14 -> #N/A | S14: =AR14 -> #N/A | T14: =AZ14 -> #N/A | U14: =BA14 -> #N/A | V14: =AX14 -> #N/A | W14: =AY14 -> #N/A | X14: =$X$3*M14 -> #N/A | Y14: =$Y$3 -> 0.0625 | Z14: =M14-X14 -> #N/A | AA14: =Z14*'PMI Rate Est'!$J$6/12 -> #N/A | AB14: =$AB$3*M14/12 -> #N/A | AC14: =$AC$3*M14/12 -> #N/A | AD14: =MAX(J14*Y14/12,0) -> 0 | AE14: =-PMT(Y14/12,360,Z14) -> #N/A | AF14: =SUM(AE14,AC14,AB14,AA14)/(L14/12) -> #N/A | AG14: =SUM(AE14,AC14,AB14,AA14,AD14)/(L14/12) -> #N/A | AH14: =M14*$AH$3 -> #N/A | AI14: =Y14+$AI$3 -> 0.0625 | AJ14: =M14-X14-AH14 -> #N/A | AK14: =AH14*$AK$3/12 -> #N/A | AL14: =$AL$3*M14/12 -> #N/A | AM14: =$AM$3*M14/12 -> #N/A | AN14: =MAX(J14*Y14/12,0) -> 0 | AO14: =-PMT(AI14/12,360,AJ14) -> #N/A | AP14: =SUM(AO14,AM14,AL14)/(L14/12) -> #N/A | AQ14: =SUM(AO14,AM14,AL14,AK14,AN14)/(L14/12) -> #N/A | AR14: =$AR$3*AK14*12 -> #N/A | AS14: =$AS$3*(M14-X14) -> #N/A | AT14: =$AT$3*(AH14) -> #N/A | AU14: =$AU$3*SUM(AR14,AS14,AT14) -> #N/A | AV14: =AU14/M14 -> #N/A | AW14: =POWER(1+K14,10)*M14 -> #N/A | AX14: =POWER(1+K14,10)*AH14 -> #N/A | AY14: =AX14/AH14 -> #N/A | AZ14: =AW14-AX14-FV(AI14/12,(10*12),AO14,-AJ14) -> #N/A | BA14: =AZ14/X14 -> #N/A
B15: 90013 | C15: =IFERROR(VLOOKUP(LEFT(B15,FIND("County",B15)-2),CaseShiller30,2,0),"No Data") -> No Data | D15: =_xlfn.XLOOKUP($B15,'Paste Snowflake Data Here'!$B$3:$B$1048576,'Paste Snowflake Data Here'!$D$3:$D$1048576) -> #N/A | F15: =_xlfn.XLOOKUP($B15,'Paste Snowflake Data Here'!$B$3:$B$1048576,'Paste Snowflake Data Here'!$I$3:$I$1048576) -> #N/A | G15: =_xlfn.XLOOKUP($B15,'Paste Snowflake Data Here'!$B$3:$B$1048576,'Paste Snowflake Data Here'!$J$3:$J$1048576) -> #N/A | K15: =IFERROR(VLOOKUP(LEFT(B15,FIND("County",B15)-2),CaseShiller30,5,0)*0.01,$K$3) -> 0.05 | L15: =$F15*$L$3 -> #N/A | M15: =$G15*$M$3 -> #N/A | N15: =AND(AF15<$AF$3,AG15<$AG$3) -> #N/A | O15: =AND(AP15<$AP$3,AQ15<$AQ$3) -> #N/A | P15: =AND(N15=FALSE,O15) -> #N/A | Q15: =AH15 -> #N/A | R15: =AU15 -> #N/A | S15: =AR15 -> #N/A | T15: =AZ15 -> #N/A | U15: =BA15 -> #N/A | V15: =AX15 -> #N/A | W15: =AY15 -> #N/A | X15: =$X$3*M15 -> #N/A | Y15: =$Y$3 -> 0.0625 | Z15: =M15-X15 -> #N/A | AA15: =Z15*'PMI Rate Est'!$J$6/12 -> #N/A | AB15: =$AB$3*M15/12 -> #N/A | AC15: =$AC$3*M15/12 -> #N/A | AD15: =MAX(J15*Y15/12,0) -> 0 | AE15: =-PMT(Y15/12,360,Z15) -> #N/A | AF15: =SUM(AE15,AC15,AB15,AA15)/(L15/12) -> #N/A | AG15: =SUM(AE15,AC15,AB15,AA15,AD15)/(L15/12) -> #N/A | AH15: =M15*$AH$3 -> #N/A | AI15: =Y15+$AI$3 -> 0.0625 | AJ15: =M15-X15-AH15 -> #N/A | AK15: =AH15*$AK$3/12 -> #N/A | AL15: =$AL$3*M15/12 -> #N/A | AM15: =$AM$3*M15/12 -> #N/A | AN15: =MAX(J15*Y15/12,0) -> 0 | AO15: =-PMT(AI15/12,360,AJ15) -> #N/A | AP15: =SUM(AO15,AM15,AL15)/(L15/12) -> #N/A | AQ15: =SUM(AO15,AM15,AL15,AK15,AN15)/(L15/12) -> #N/A | AR15: =$AR$3*AK15*12 -> #N/A | AS15: =$AS$3*(M15-X15) -> #N/A | AT15: =$AT$3*(AH15) -> #N/A | AU15: =$AU$3*SUM(AR15,AS15,AT15) -> #N/A | AV15: =AU15/M15 -> #N/A | AW15: =POWER(1+K15,10)*M15 -> #N/A | AX15: =POWER(1+K15,10)*AH15 -> #N/A | AY15: =AX15/AH15 -> #N/A | AZ15: =AW15-AX15-FV(AI15/12,(10*12),AO15,-AJ15) -> #N/A | BA15: =AZ15/X15 -> #N/A
B16: 90014 | C16: =IFERROR(VLOOKUP(LEFT(B16,FIND("County",B16)-2),CaseShiller30,2,0),"No Data") -> No Data | D16: =_xlfn.XLOOKUP($B16,'Paste Snowflake Data Here'!$B$3:$B$1048576,'Paste Snowflake Data Here'!$D$3:$D$1048576) -> #N/A | F16: =_xlfn.XLOOKUP($B16,'Paste Snowflake Data Here'!$B$3:$B$1048576,'Paste Snowflake Data Here'!$I$3:$I$1048576) -> #N/A | G16: =_xlfn.XLOOKUP($B16,'Paste Snowflake Data Here'!$B$3:$B$1048576,'Paste Snowflake Data Here'!$J$3:$J$1048576) -> #N/A | K16: =IFERROR(VLOOKUP(LEFT(B16,FIND("County",B16)-2),CaseShiller30,5,0)*0.01,$K$3) -> 0.05 | L16: =$F16*$L$3 -> #N/A | M16: =$G16*$M$3 -> #N/A | N16: =AND(AF16<$AF$3,AG16<$AG$3) -> #N/A | O16: =AND(AP16<$AP$3,AQ16<$AQ$3) -> #N/A | P16: =AND(N16=FALSE,O16) -> #N/A | Q16: =AH16 -> #N/A | R16: =AU16 -> #N/A | S16: =AR16 -> #N/A | T16: =AZ16 -> #N/A | U16: =BA16 -> #N/A | V16: =AX16 -> #N/A | W16: =AY16 -> #N/A | X16: =$X$3*M16 -> #N/A | Y16: =$Y$3 -> 0.0625 | Z16: =M16-X16 -> #N/A | AA16: =Z16*'PMI Rate Est'!$J$6/12 -> #N/A | AB16: =$AB$3*M16/12 -> #N/A | AC16: =$AC$3*M16/12 -> #N/A | AD16: =MAX(J16*Y16/12,0) -> 0 | AE16: =-PMT(Y16/12,360,Z16) -> #N/A | AF16: =SUM(AE16,AC16,AB16,AA16)/(L16/12) -> #N/A | AG16: =SUM(AE16,AC16,AB16,AA16,AD16)/(L16/12) -> #N/A | AH16: =M16*$AH$3 -> #N/A | AI16: =Y16+$AI$3 -> 0.0625 | AJ16: =M16-X16-AH16 -> #N/A | AK16: =AH16*$AK$3/12 -> #N/A | AL16: =$AL$3*M16/12 -> #N/A | AM16: =$AM$3*M16/12 -> #N/A | AN16: =MAX(J16*Y16/12,0) -> 0 | AO16: =-PMT(AI16/12,360,AJ16) -> #N/A | AP16: =SUM(AO16,AM16,AL16)/(L16/12) -> #N/A | AQ16: =SUM(AO16,AM16,AL16,AK16,AN16)/(L16/12) -> #N/A | AR16: =$AR$3*AK16*12 -> #N/A | AS16: =$AS$3*(M16-X16) -> #N/A | AT16: =$AT$3*(AH16) -> #N/A | AU16: =$AU$3*SUM(AR16,AS16,AT16) -> #N/A | AV16: =AU16/M16 -> #N/A | AW16: =POWER(1+K16,10)*M16 -> #N/A | AX16: =POWER(1+K16,10)*AH16 -> #N/A | AY16: =AX16/AH16 -> #N/A | AZ16: =AW16-AX16-FV(AI16/12,(10*12),AO16,-AJ16) -> #N/A | BA16: =AZ16/X16 -> #N/A
... B19: 90017 | C19: =IFERROR(VLOOKUP(LEFT(B19,FIND("County",B19)-2),CaseShiller30,2,0),"No Data") -> No Data | D19: =_xlfn.XLOOKUP($B19,'Paste Snowflake Data Here'!$B$3:$B$1048576,'Paste Snowflake Data Here'!$D$3:$D$1048576) -> #N/A | F19: =_xlfn.XLOOKUP($B19,'Paste Snowflake Data Here'!$B$3:$B$1048576,'Paste Snowflake Data Here'!$I$3:$I$1048576) -> #N/A | G19: =_xlfn.XLOOKUP($B19,'Paste Snowflake Data Here'!$B$3:$B$1048576,'Paste Snowflake Data Here'!$J$3:$J$1048576) -> #N/A | K19: =IFERROR(VLOOKUP(LEFT(B19,FIND("County",B19)-2),CaseShiller30,5,0)*0.01,$K$3) -> 0.05 | L19: =$F19*$L$3 -> #N/A | M19: =$G19*$M$3 -> #N/A | N19: =AND(AF19<$AF$3,AG19<$AG$3) -> #N/A | O19: =AND(AP19<$AP$3,AQ19<$AQ$3) -> #N/A | P19: =AND(N19=FALSE,O19) -> #N/A | Q19: =AH19 -> #N/A | R19: =AU19 -> #N/A | S19: =AR19 -> #N/A | T19: =AZ19 -> #N/A | U19: =BA19 -> #N/A | V19: =AX19 -> #N/A | W19: =AY19 -> #N/A | X19: =$X$3*M19 -> #N/A | Y19: =$Y$3 -> 0.0625 | Z19: =M19-X19 -> #N/A | AA19: =Z19*'PMI Rate Est'!$J$6/12 -> #N/A | AB19: =$AB$3*M19/12 -> #N/A | AC19: =$AC$3*M19/12 -> #N/A | AD19: =MAX(J19*Y19/12,0) -> 0 | AE19: =-PMT(Y19/12,360,Z19) -> #N/A | AF19: =SUM(AE19,AC19,AB19,AA19)/(L19/12) -> #N/A | AG19: =SUM(AE19,AC19,AB19,AA19,AD19)/(L19/12) -> #N/A | AH19: =M19*$AH$3 -> #N/A | AI19: =Y19+$AI$3 -> 0.0625 | AJ19: =M19-X19-AH19 -> #N/A | AK19: =AH19*$AK$3/12 -> #N/A | AL19: =$AL$3*M19/12 -> #N/A | AM19: =$AM$3*M19/12 -> #N/A | AN19: =MAX(J19*Y19/12,0) -> 0 | AO19: =-PMT(AI19/12,360,AJ19) -> #N/A | AP19: =SUM(AO19,AM19,AL19)/(L19/12) -> #N/A | AQ19: =SUM(AO19,AM19,AL19,AK19,AN19)/(L19/12) -> #N/A | AR19: =$AR$3*AK19*12 -> #N/A | AS19: =$AS$3*(M19-X19) -> #N/A | AT19: =$AT$3*(AH19) -> #N/A | AU19: =$AU$3*SUM(AR19,AS19,AT19) -> #N/A | AV19: =AU19/M19 -> #N/A | AW19: =POWER(1+K19,10)*M19 -> #N/A | AX19: =POWER(1+K19,10)*AH19 -> #N/A | AY19: =AX19/AH19 -> #N/A | AZ19: =AW19-AX19-FV(AI19/12,(10*12),AO19,-AJ19) -> #N/A | BA19: =AZ19/X19 -> #N/A
B20: 90018
B21: 90019
B22: 90020
B23: 90021
B24: 90022
B25: 90023
B26: 90024
B27: 90025
B28: 90026
B29: 90027
B30: 90028
B31: 90029
... B131: 90639
B132: 90640 | Q132: =AVERAGE(N124:P124) -> #DIV/0!
B133: 90650 | Q133: =AVERAGE(N125:P125) -> #DIV/0!
B134: 90660 | Q134: =AVERAGE(N126:P126) -> #DIV/0!
B135: 90670
B136: 90680
B137: 90701
B138: 90703
B139: 90704
B140: 90706
B141: 90710
B142: 90712
B143: 90713
B144: 90715
B145: 90716
B146: 90717
... B1739: 96162

Sheet Remi - Aggregate Model
B3: Key Assumptions: | K3: ='Assumptions & Borrower Profiles'!$C$11 -> 0.05 | L3: ='Assumptions & Borrower Profiles'!#REF! -> #REF! | M3: ='Assumptions & Borrower Profiles'!#REF! -> #REF! | Q3: ='Assumptions & Borrower Profiles'!#REF! -> #REF! | R3: 1 | X3: ='Assumptions & Borrower Profiles'!#REF! -> #REF! | Y3: ='Assumptions & Borrower Profiles'!$C$7 -> 0.0625 | AA3: ='Assumptions & Borrower Profiles'!$C$6 -> 620 | AB3: ='Assumptions & Borrower Profiles'!$C$17 -> 0.0135 | AC3: ='Assumptions & Borrower Profiles'!$C$18 -> 0.004 | AF3: ='Assumptions & Borrower Profiles'!$C$25 -> 0.35 | AG3: =AF3+0.1 -> 0.45 | AH3: =Q3 -> #REF! | AI3: ='Assumptions & Borrower Profiles'!C7-'Assumptions & Borrower Profiles'!C8 -> 0 | AK3: 0 | AL3: =AB3 -> 0.0135 | AM3: =AC3 -> 0.004 | AP3: =AF3 -> 0.35 | AQ3: =AG3 -> 0.45 | AR3: 0 | AS3: ='Assumptions & Borrower Profiles'!$C$13 -> 0.02 | AT3: 0.03 | AU3: 0
B4: ZIP Code | C4: Code | D4: Population | E4: % African American | F4: Area Median Household Income | G4: Median Home Values | H4: Median Contract Rent | I4: DTI Avg | J4: Estimated Household Debt (incl mortgage) | K4: 30 Year Case Shiller Return / ann | L4: % AMI for calc | M4: % Median Home Value | N4: Passed DTI without HOM? | O4: Passed DTI with HOM? | P4: Threshold? | Q4: HOM Investment | R4: Grant for Fees/PMI | S4: Annual PMI | T4: Homeowner Equity after 10 Years | U4: % Gain from Downpayment | V4: HOM Investment after 10 Years | W4: % Gain on HOM Investment | X4: Downpayment | Y4: 30 Year Fixed Rate for 640 | Z4: 1st Principal Without Homium | AA4: PMI / Month | AB4: Tax / mo | AC4: Insurance / mo | AD4: Household Debt Service / mo | AE4: Monthly Payment | AF4: Front Ratio | AG4: Back Ratio | AH4: SAN Principal | AI4: 30 Year Fixed Rate for 640 WITH HOMIUM | AJ4: 1st Principal WITH Homium | AK4: PMI / Month | AL4: Tax / mo | AM4: Insurance / mo | AN4: Household Debt Service / mo | AO4: New Monthly Payment on 1st | AP4: Front Ratio with HOM | AQ4: Back Ratio with HOM | AR4: PMI Total (yrs) | AS4: Closing Fees | AT4: Origination Fees | AU4: Total Grant | AV4: % Total Grant of Home Value | AW4: Home Value after 10 years at X apprec | AX4: Homium SAN Value after 10 years | AY4: % Gain on HOM investment | AZ4: Homeowner Equity after 10 years | BA4: % Gain from Downpayment
B5: 90001 | C5: =IFERROR(VLOOKUP(LEFT(B5,FIND("County",B5)-2),CaseShiller30,2,0),"No Data") -> No Data | D5: =_xlfn.XLOOKUP($B5,'Paste Snowflake Data Here'!$B$3:$B$1048576,'Paste Snowflake Data Here'!$D$3:$D$1048576) -> #N/A | F5: =_xlfn.XLOOKUP($B5,'Paste Snowflake Data Here'!$B$3:$B$1048576,'Paste Snowflake Data Here'!$I$3:$I$1048576) -> #N/A | G5: =_xlfn.XLOOKUP($B5,'Paste Snowflake Data Here'!$B$3:$B$1048576,'Paste Snowflake Data Here'!$J$3:$J$1048576) -> #N/A | K5: =IFERROR(VLOOKUP(LEFT(B5,FIND("County",B5)-2),CaseShiller30,5,0)*0.01,$K$3) -> 0.05 | L5: =$F5*$L$3 -> #N/A | M5: =$G5*$M$3 -> #N/A | N5: =AND(AF5<$AF$3,AG5<$AG$3) -> #N/A | O5: =AND(AP5<$AP$3,AQ5<$AQ$3) -> #N/A | P5: =AND(N5=FALSE,O5) -> #N/A | Q5: =AH5 -> #N/A | R5: =AU5 -> #N/A | S5: =AR5 -> #N/A | T5: =AZ5 -> #N/A | U5: =BA5 -> #N/A | V5: =AX5 -> #N/A | W5: =AY5 -> #N/A | X5: =$X$3*M5 -> #REF! | Y5: =$Y$3 -> 0.0625 | Z5: =M5-X5 -> #N/A | AA5: =Z5*'PMI Rate Est'!$J$6/12 -> #N/A | AB5: =$AB$3*M5/12 -> #N/A | AC5: =$AC$3*M5/12 -> #N/A | AD5: =MAX(J5*Y5/12,0) -> 0 | AE5: =-PMT(Y5/12,360,Z5) -> #N/A | AF5: =SUM(AE5,AC5,AB5,AA5)/(L5/12) -> #N/A | AG5: =SUM(AE5,AC5,AB5,AA5,AD5)/(L5/12) -> #N/A | AH5: =M5*$AH$3 -> #N/A | AI5: =Y5+$AI$3 -> 0.0625 | AJ5: =M5-X5-AH5 -> #N/A | AK5: =AH5*$AK$3/12 -> #N/A | AL5: =$AL$3*M5/12 -> #N/A | AM5: =$AM$3*M5/12 -> #N/A | AN5: =MAX(J5*Y5/12,0) -> 0 | AO5: =-PMT(AI5/12,360,AJ5) -> #N/A | AP5: =SUM(AO5,AM5,AL5)/(L5/12) -> #N/A | AQ5: =SUM(AO5,AM5,AL5,AK5,AN5)/(L5/12) -> #N/A | AR5: =$AR$3*AK5*12 -> #N/A | AS5: =$AS$3*(M5-X5) -> #N/A | AT5: =$AT$3*(AH5) -> #N/A | AU5: =$AU$3*SUM(AR5,AS5,AT5) -> #N/A | AV5: =AU5/M5 -> #N/A | AW5: =POWER(1+K5,10)*M5 -> #N/A | AX5: =POWER(1+K5,10)*AH5 -> #N/A | AY5: =AX5/AH5 -> #N/A | AZ5: =AW5-AX5-FV(AI5/12,(10*12),AO5,-AJ5) -> #N/A | BA5: =AZ5/X5 -> #N/A
B6: 90002 | C6: =IFERROR(VLOOKUP(LEFT(B6,FIND("County",B6)-2),CaseShiller30,2,0),"No Data") -> No Data | D6: =_xlfn.XLOOKUP($B6,'Paste Snowflake Data Here'!$B$3:$B$1048576,'Paste Snowflake Data Here'!$D$3:$D$1048576) -> #N/A | F6: =_xlfn.XLOOKUP($B6,'Paste Snowflake Data Here'!$B$3:$B$1048576,'Paste Snowflake Data Here'!$I$3:$I$1048576) -> #N/A | G6: =_xlfn.XLOOKUP($B6,'Paste Snowflake Data Here'!$B$3:$B$1048576,'Paste Snowflake Data Here'!$J$3:$J$1048576) -> #N/A | K6: =IFERROR(VLOOKUP(LEFT(B6,FIND("County",B6)-2),CaseShiller30,5,0)*0.01,$K$3) -> 0.05 | L6: =$F6*$L$3 -> #N/A | M6: =$G6*$M$3 -> #N/A | N6: =AND(AF6<$AF$3,AG6<$AG$3) -> #N/A | O6: =AND(AP6<$AP$3,AQ6<$AQ$3) -> #N/A | P6: =AND(N6=FALSE,O6) -> #N/A | Q6: =AH6 -> #N/A | R6: =AU6 -> #N/A | S6: =AR6 -> #N/A | T6: =AZ6 -> #N/A | U6: =BA6 -> #N/A | V6: =AX6 -> #N/A | W6: =AY6 -> #N/A | X6: =$X$3*M6 -> #REF! | Y6: =$Y$3 -> 0.0625 | Z6: =M6-X6 -> #N/A | AA6: =Z6*'PMI Rate Est'!$J$6/12 -> #N/A | AB6: =$AB$3*M6/12 -> #N/A | AC6: =$AC$3*M6/12 -> #N/A | AD6: =MAX(J6*Y6/12,0) -> 0 | AE6: =-PMT(Y6/12,360,Z6) -> #N/A | AF6: =SUM(AE6,AC6,AB6,AA6)/(L6/12) -> #N/A | AG6: =SUM(AE6,AC6,AB6,AA6,AD6)/(L6/12) -> #N/A | AH6: =M6*$AH$3 -> #N/A | AI6: =Y6+$AI$3 -> 0.0625 | AJ6: =M6-X6-AH6 -> #N/A | AK6: =AH6*$AK$3/12 -> #N/A | AL6: =$AL$3*M6/12 -> #N/A | AM6: =$AM$3*M6/12 -> #N/A | AN6: =MAX(J6*Y6/12,0) -> 0 | AO6: =-PMT(AI6/12,360,AJ6) -> #N/A | AP6: =SUM(AO6,AM6,AL6)/(L6/12) -> #N/A | AQ6: =SUM(AO6,AM6,AL6,AK6,AN6)/(L6/12) -> #N/A | AR6: =$AR$3*AK6*12 -> #N/A | AS6: =$AS$3*(M6-X6) -> #N/A | AT6: =$AT$3*(AH6) -> #N/A | AU6: =$AU$3*SUM(AR6,AS6,AT6) -> #N/A | AV6: =AU6/M6 -> #N/A | AW6: =POWER(1+K6,10)*M6 -> #N/A | AX6: =POWER(1+K6,10)*AH6 -> #N/A | AY6: =AX6/AH6 -> #N/A | AZ6: =AW6-AX6-FV(AI6/12,(10*12),AO6,-AJ6) -> #N/A | BA6: =AZ6/X6 -> #N/A
B7: 90003 | C7: =IFERROR(VLOOKUP(LEFT(B7,FIND("County",B7)-2),CaseShiller30,2,0),"No Data") -> No Data | D7: =_xlfn.XLOOKUP($B7,'Paste Snowflake Data Here'!$B$3:$B$1048576,'Paste Snowflake Data Here'!$D$3:$D$1048576) -> #N/A | F7: =_xlfn.XLOOKUP($B7,'Paste Snowflake Data Here'!$B$3:$B$1048576,'Paste Snowflake Data Here'!$I$3:$I$1048576) -> #N/A | G7: =_xlfn.XLOOKUP($B7,'Paste Snowflake Data Here'!$B$3:$B$1048576,'Paste Snowflake Data Here'!$J$3:$J$1048576) -> #N/A | K7: =IFERROR(VLOOKUP(LEFT(B7,FIND("County",B7)-2),CaseShiller30,5,0)*0.01,$K$3) -> 0.05 | L7: =$F7*$L$3 -> #N/A | M7: =$G7*$M$3 -> #N/A | N7: =AND(AF7<$AF$3,AG7<$AG$3) -> #N/A | O7: =AND(AP7<$AP$3,AQ7<$AQ$3) -> #N/A | P7: =AND(N7=FALSE,O7) -> #N/A | Q7: =AH7 -> #N/A | R7: =AU7 -> #N/A | S7: =AR7 -> #N/A | T7: =AZ7 -> #N/A | U7: =BA7 -> #N/A | V7: =AX7 -> #N/A | W7: =AY7 -> #N/A | X7: =$X$3*M7 -> #REF! | Y7: =$Y$3 -> 0.0625 | Z7: =M7-X7 -> #N/A | AA7: =Z7*'PMI Rate Est'!$J$6/12 -> #N/A | AB7: =$AB$3*M7/12 -> #N/A | AC7: =$AC$3*M7/12 -> #N/A | AD7: =MAX(J7*Y7/12,0) -> 0 | AE7: =-PMT(Y7/12,360,Z7) -> #N/A | AF7: =SUM(AE7,AC7,AB7,AA7)/(L7/12) -> #N/A | AG7: =SUM(AE7,AC7,AB7,AA7,AD7)/(L7/12) -> #N/A | AH7: =M7*$AH$3 -> #N/A | AI7: =Y7+$AI$3 -> 0.0625 | AJ7: =M7-X7-AH7 -> #N/A | AK7: =AH7*$AK$3/12 -> #N/A | AL7: =$AL$3*M7/12 -> #N/A | AM7: =$AM$3*M7/12 -> #N/A | AN7: =MAX(J7*Y7/12,0) -> 0 | AO7: =-PMT(AI7/12,360,AJ7) -> #N/A | AP7: =SUM(AO7,AM7,AL7)/(L7/12) -> #N/A | AQ7: =SUM(AO7,AM7,AL7,AK7,AN7)/(L7/12) -> #N/A | AR7: =$AR$3*AK7*12 -> #N/A | AS7: =$AS$3*(M7-X7) -> #N/A | AT7: =$AT$3*(AH7) -> #N/A | AU7: =$AU$3*SUM(AR7,AS7,AT7) -> #N/A | AV7: =AU7/M7 -> #N/A | AW7: =POWER(1+K7,10)*M7 -> #N/A | AX7: =POWER(1+K7,10)*AH7 -> #N/A | AY7: =AX7/AH7 -> #N/A | AZ7: =AW7-AX7-FV(AI7/12,(10*12),AO7,-AJ7) -> #N/A | BA7: =AZ7/X7 -> #N/A
B8: 90004 | C8: =IFERROR(VLOOKUP(LEFT(B8,FIND("County",B8)-2),CaseShiller30,2,0),"No Data") -> No Data | D8: =_xlfn.XLOOKUP($B8,'Paste Snowflake Data Here'!$B$3:$B$1048576,'Paste Snowflake Data Here'!$D$3:$D$1048576) -> #N/A | F8: =_xlfn.XLOOKUP($B8,'Paste Snowflake Data Here'!$B$3:$B$1048576,'Paste Snowflake Data Here'!$I$3:$I$1048576) -> #N/A | G8: =_xlfn.XLOOKUP($B8,'Paste Snowflake Data Here'!$B$3:$B$1048576,'Paste Snowflake Data Here'!$J$3:$J$1048576) -> #N/A | K8: =IFERROR(VLOOKUP(LEFT(B8,FIND("County",B8)-2),CaseShiller30,5,0)*0.01,$K$3) -> 0.05 | L8: =$F8*$L$3 -> #N/A | M8: =$G8*$M$3 -> #N/A | N8: =AND(AF8<$AF$3,AG8<$AG$3) -> #N/A | O8: =AND(AP8<$AP$3,AQ8<$AQ$3) -> #N/A | P8: =AND(N8=FALSE,O8) -> #N/A | Q8: =AH8 -> #N/A | R8: =AU8 -> #N/A | S8: =AR8 -> #N/A | T8: =AZ8 -> #N/A | U8: =BA8 -> #N/A | V8: =AX8 -> #N/A | W8: =AY8 -> #N/A | X8: =$X$3*M8 -> #REF! | Y8: =$Y$3 -> 0.0625 | Z8: =M8-X8 -> #N/A | AA8: =Z8*'PMI Rate Est'!$J$6/12 -> #N/A | AB8: =$AB$3*M8/12 -> #N/A | AC8: =$AC$3*M8/12 -> #N/A | AD8: =MAX(J8*Y8/12,0) -> 0 | AE8: =-PMT(Y8/12,360,Z8) -> #N/A | AF8: =SUM(AE8,AC8,AB8,AA8)/(L8/12) -> #N/A | AG8: =SUM(AE8,AC8,AB8,AA8,AD8)/(L8/12) -> #N/A | AH8: =M8*$AH$3 -> #N/A | AI8: =Y8+$AI$3 -> 0.0625 | AJ8: =M8-X8-AH8 -> #N/A | AK8: =AH8*$AK$3/12 -> #N/A | AL8: =$AL$3*M8/12 -> #N/A | AM8: =$AM$3*M8/12 -> #N/A | AN8: =MAX(J8*Y8/12,0) -> 0 | AO8: =-PMT(AI8/12,360,AJ8) -> #N/A | AP8: =SUM(AO8,AM8,AL8)/(L8/12) -> #N/A | AQ8: =SUM(AO8,AM8,AL8,AK8,AN8)/(L8/12) -> #N/A | AR8: =$AR$3*AK8*12 -> #N/A | AS8: =$AS$3*(M8-X8) -> #N/A | AT8: =$AT$3*(AH8) -> #N/A | AU8: =$AU$3*SUM(AR8,AS8,AT8) -> #N/A | AV8: =AU8/M8 -> #N/A | AW8: =POWER(1+K8,10)*M8 -> #N/A | AX8: =POWER(1+K8,10)*AH8 -> #N/A | AY8: =AX8/AH8 -> #N/A | AZ8: =AW8-AX8-FV(AI8/12,(10*12),AO8,-AJ8) -> #N/A | BA8: =AZ8/X8 -> #N/A
B9: 90005 | C9: =IFERROR(VLOOKUP(LEFT(B9,FIND("County",B9)-2),CaseShiller30,2,0),"No Data") -> No Data | D9: =_xlfn.XLOOKUP($B9,'Paste Snowflake Data Here'!$B$3:$B$1048576,'Paste Snowflake Data Here'!$D$3:$D$1048576) -> #N/A | F9: =_xlfn.XLOOKUP($B9,'Paste Snowflake Data Here'!$B$3:$B$1048576,'Paste Snowflake Data Here'!$I$3:$I$1048576) -> #N/A | G9: =_xlfn.XLOOKUP($B9,'Paste Snowflake Data Here'!$B$3:$B$1048576,'Paste Snowflake Data Here'!$J$3:$J$1048576) -> #N/A | K9: =IFERROR(VLOOKUP(LEFT(B9,FIND("County",B9)-2),CaseShiller30,5,0)*0.01,$K$3) -> 0.05 | L9: =$F9*$L$3 -> #N/A | M9: =$G9*$M$3 -> #N/A | N9: =AND(AF9<$AF$3,AG9<$AG$3) -> #N/A | O9: =AND(AP9<$AP$3,AQ9<$AQ$3) -> #N/A | P9: =AND(N9=FALSE,O9) -> #N/A | Q9: =AH9 -> #N/A | R9: =AU9 -> #N/A | S9: =AR9 -> #N/A | T9: =AZ9 -> #N/A | U9: =BA9 -> #N/A | V9: =AX9 -> #N/A | W9: =AY9 -> #N/A | X9: =$X$3*M9 -> #REF! | Y9: =$Y$3 -> 0.0625 | Z9: =M9-X9 -> #N/A | AA9: =Z9*'PMI Rate Est'!$J$6/12 -> #N/A | AB9: =$AB$3*M9/12 -> #N/A | AC9: =$AC$3*M9/12 -> #N/A | AD9: =MAX(J9*Y9/12,0) -> 0 | AE9: =-PMT(Y9/12,360,Z9) -> #N/A | AF9: =SUM(AE9,AC9,AB9,AA9)/(L9/12) -> #N/A | AG9: =SUM(AE9,AC9,AB9,AA9,AD9)/(L9/12) -> #N/A | AH9: =M9*$AH$3 -> #N/A | AI9: =Y9+$AI$3 -> 0.0625 | AJ9: =M9-X9-AH9 -> #N/A | AK9: =AH9*$AK$3/12 -> #N/A | AL9: =$AL$3*M9/12 -> #N/A | AM9: =$AM$3*M9/12 -> #N/A | AN9: =MAX(J9*Y9/12,0) -> 0 | AO9: =-PMT(AI9/12,360,AJ9) -> #N/A | AP9: =SUM(AO9,AM9,AL9)/(L9/12) -> #N/A | AQ9: =SUM(AO9,AM9,AL9,AK9,AN9)/(L9/12) -> #N/A | AR9: =$AR$3*AK9*12 -> #N/A | AS9: =$AS$3*(M9-X9) -> #N/A | AT9: =$AT$3*(AH9) -> #N/A | AU9: =$AU$3*SUM(AR9,AS9,AT9) -> #N/A | AV9: =AU9/M9 -> #N/A | AW9: =POWER(1+K9,10)*M9 -> #N/A | AX9: =POWER(1+K9,10)*AH9 -> #N/A | AY9: =AX9/AH9 -> #N/A | AZ9: =AW9-AX9-FV(AI9/12,(10*12),AO9,-AJ9) -> #N/A | BA9: =AZ9/X9 -> #N/A
B10: 90006 | C10: =IFERROR(VLOOKUP(LEFT(B10,FIND("County",B10)-2),CaseShiller30,2,0),"No Data") -> No Data | D10: =_xlfn.XLOOKUP($B10,'Paste Snowflake Data Here'!$B$3:$B$1048576,'Paste Snowflake Data Here'!$D$3:$D$1048576) -> #N/A | F10: =_xlfn.XLOOKUP($B10,'Paste Snowflake Data Here'!$B$3:$B$1048576,'Paste Snowflake Data Here'!$I$3:$I$1048576) -> #N/A | G10: =_xlfn.XLOOKUP($B10,'Paste Snowflake Data Here'!$B$3:$B$1048576,'Paste Snowflake Data Here'!$J$3:$J$1048576) -> #N/A | K10: =IFERROR(VLOOKUP(LEFT(B10,FIND("County",B10)-2),CaseShiller30,5,0)*0.01,$K$3) -> 0.05 | L10: =$F10*$L$3 -> #N/A | M10: =$G10*$M$3 -> #N/A | N10: =AND(AF10<$AF$3,AG10<$AG$3) -> #N/A | O10: =AND(AP10<$AP$3,AQ10<$AQ$3) -> #N/A | P10: =AND(N10=FALSE,O10) -> #N/A | Q10: =AH10 -> #N/A | R10: =AU10 -> #N/A | S10: =AR10 -> #N/A | T10: =AZ10 -> #N/A | U10: =BA10 -> #N/A | V10: =AX10 -> #N/A | W10: =AY10 -> #N/A | X10: =$X$3*M10 -> #REF! | Y10: =$Y$3 -> 0.0625 | Z10: =M10-X10 -> #N/A | AA10: =Z10*'PMI Rate Est'!$J$6/12 -> #N/A | AB10: =$AB$3*M10/12 -> #N/A | AC10: =$AC$3*M10/12 -> #N/A | AD10: =MAX(J10*Y10/12,0) -> 0 | AE10: =-PMT(Y10/12,360,Z10) -> #N/A | AF10: =SUM(AE10,AC10,AB10,AA10)/(L10/12) -> #N/A | AG10: =SUM(AE10,AC10,AB10,AA10,AD10)/(L10/12) -> #N/A | AH10: =M10*$AH$3 -> #N/A | AI10: =Y10+$AI$3 -> 0.0625 | AJ10: =M10-X10-AH10 -> #N/A | AK10: =AH10*$AK$3/12 -> #N/A | AL10: =$AL$3*M10/12 -> #N/A | AM10: =$AM$3*M10/12 -> #N/A | AN10: =MAX(J10*Y10/12,0) -> 0 | AO10: =-PMT(AI10/12,360,AJ10) -> #N/A | AP10: =SUM(AO10,AM10,AL10)/(L10/12) -> #N/A | AQ10: =SUM(AO10,AM10,AL10,AK10,AN10)/(L10/12) -> #N/A | AR10: =$AR$3*AK10*12 -> #N/A | AS10: =$AS$3*(M10-X10) -> #N/A | AT10: =$AT$3*(AH10) -> #N/A | AU10: =$AU$3*SUM(AR10,AS10,AT10) -> #N/A | AV10: =AU10/M10 -> #N/A | AW10: =POWER(1+K10,10)*M10 -> #N/A | AX10: =POWER(1+K10,10)*AH10 -> #N/A | AY10: =AX10/AH10 -> #N/A | AZ10: =AW10-AX10-FV(AI10/12,(10*12),AO10,-AJ10) -> #N/A | BA10: =AZ10/X10 -> #N/A
B11: 90007 | C11: =IFERROR(VLOOKUP(LEFT(B11,FIND("County",B11)-2),CaseShiller30,2,0),"No Data") -> No Data | D11: =_xlfn.XLOOKUP($B11,'Paste Snowflake Data Here'!$B$3:$B$1048576,'Paste Snowflake Data Here'!$D$3:$D$1048576) -> #N/A | F11: =_xlfn.XLOOKUP($B11,'Paste Snowflake Data Here'!$B$3:$B$1048576,'Paste Snowflake Data Here'!$I$3:$I$1048576) -> #N/A | G11: =_xlfn.XLOOKUP($B11,'Paste Snowflake Data Here'!$B$3:$B$1048576,'Paste Snowflake Data Here'!$J$3:$J$1048576) -> #N/A | K11: =IFERROR(VLOOKUP(LEFT(B11,FIND("County",B11)-2),CaseShiller30,5,0)*0.01,$K$3) -> 0.05 | L11: =$F11*$L$3 -> #N/A | M11: =$G11*$M$3 -> #N/A | N11: =AND(AF11<$AF$3,AG11<$AG$3) -> #N/A | O11: =AND(AP11<$AP$3,AQ11<$AQ$3) -> #N/A | P11: =AND(N11=FALSE,O11) -> #N/A | Q11: =AH11 -> #N/A | R11: =AU11 -> #N/A | S11: =AR11 -> #N/A | T11: =AZ11 -> #N/A | U11: =BA11 -> #N/A | V11: =AX11 -> #N/A | W11: =AY11 -> #N/A | X11: =$X$3*M11 -> #REF! | Y11: =$Y$3 -> 0.0625 | Z11: =M11-X11 -> #N/A | AA11: =Z11*'PMI Rate Est'!$J$6/12 -> #N/A | AB11: =$AB$3*M11/12 -> #N/A | AC11: =$AC$3*M11/12 -> #N/A | AD11: =MAX(J11*Y11/12,0) -> 0 | AE11: =-PMT(Y11/12,360,Z11) -> #N/A | AF11: =SUM(AE11,AC11,AB11,AA11)/(L11/12) -> #N/A | AG11: =SUM(AE11,AC11,AB11,AA11,AD11)/(L11/12) -> #N/A | AH11: =M11*$AH$3 -> #N/A | AI11: =Y11+$AI$3 -> 0.0625 | AJ11: =M11-X11-AH11 -> #N/A | AK11: =AH11*$AK$3/12 -> #N/A | AL11: =$AL$3*M11/12 -> #N/A | AM11: =$AM$3*M11/12 -> #N/A | AN11: =MAX(J11*Y11/12,0) -> 0 | AO11: =-PMT(AI11/12,360,AJ11) -> #N/A | AP11: =SUM(AO11,AM11,AL11)/(L11/12) -> #N/A | AQ11: =SUM(AO11,AM11,AL11,AK11,AN11)/(L11/12) -> #N/A | AR11: =$AR$3*AK11*12 -> #N/A | AS11: =$AS$3*(M11-X11) -> #N/A | AT11: =$AT$3*(AH11) -> #N/A | AU11: =$AU$3*SUM(AR11,AS11,AT11) -> #N/A | AV11: =AU11/M11 -> #N/A | AW11: =POWER(1+K11,10)*M11 -> #N/A | AX11: =POWER(1+K11,10)*AH11 -> #N/A | AY11: =AX11/AH11 -> #N/A | AZ11: =AW11-AX11-FV(AI11/12,(10*12),AO11,-AJ11) -> #N/A | BA11: =AZ11/X11 -> #N/A
B12: 90008 | C12: =IFERROR(VLOOKUP(LEFT(B12,FIND("County",B12)-2),CaseShiller30,2,0),"No Data") -> No Data | D12: =_xlfn.XLOOKUP($B12,'Paste Snowflake Data Here'!$B$3:$B$1048576,'Paste Snowflake Data Here'!$D$3:$D$1048576) -> #N/A | F12: =_xlfn.XLOOKUP($B12,'Paste Snowflake Data Here'!$B$3:$B$1048576,'Paste Snowflake Data Here'!$I$3:$I$1048576) -> #N/A | G12: =_xlfn.XLOOKUP($B12,'Paste Snowflake Data Here'!$B$3:$B$1048576,'Paste Snowflake Data Here'!$J$3:$J$1048576) -> #N/A | K12: =IFERROR(VLOOKUP(LEFT(B12,FIND("County",B12)-2),CaseShiller30,5,0)*0.01,$K$3) -> 0.05 | L12: =$F12*$L$3 -> #N/A | M12: =$G12*$M$3 -> #N/A | N12: =AND(AF12<$AF$3,AG12<$AG$3) -> #N/A | O12: =AND(AP12<$AP$3,AQ12<$AQ$3) -> #N/A | P12: =AND(N12=FALSE,O12) -> #N/A | Q12: =AH12 -> #N/A | R12: =AU12 -> #N/A | S12: =AR12 -> #N/A | T12: =AZ12 -> #N/A | U12: =BA12 -> #N/A | V12: =AX12 -> #N/A | W12: =AY12 -> #N/A | X12: =$X$3*M12 -> #REF! | Y12: =$Y$3 -> 0.0625 | Z12: =M12-X12 -> #N/A | AA12: =Z12*'PMI Rate Est'!$J$6/12 -> #N/A | AB12: =$AB$3*M12/12 -> #N/A | AC12: =$AC$3*M12/12 -> #N/A | AD12: =MAX(J12*Y12/12,0) -> 0 | AE12: =-PMT(Y12/12,360,Z12) -> #N/A | AF12: =SUM(AE12,AC12,AB12,AA12)/(L12/12) -> #N/A | AG12: =SUM(AE12,AC12,AB12,AA12,AD12)/(L12/12) -> #N/A | AH12: =M12*$AH$3 -> #N/A | AI12: =Y12+$AI$3 -> 0.0625 | AJ12: =M12-X12-AH12 -> #N/A | AK12: =AH12*$AK$3/12 -> #N/A | AL12: =$AL$3*M12/12 -> #N/A | AM12: =$AM$3*M12/12 -> #N/A | AN12: =MAX(J12*Y12/12,0) -> 0 | AO12: =-PMT(AI12/12,360,AJ12) -> #N/A | AP12: =SUM(AO12,AM12,AL12)/(L12/12) -> #N/A | AQ12: =SUM(AO12,AM12,AL12,AK12,AN12)/(L12/12) -> #N/A | AR12: =$AR$3*AK12*12 -> #N/A | AS12: =$AS$3*(M12-X12) -> #N/A | AT12: =$AT$3*(AH12) -> #N/A | AU12: =$AU$3*SUM(AR12,AS12,AT12) -> #N/A | AV12: =AU12/M12 -> #N/A | AW12: =POWER(1+K12,10)*M12 -> #N/A | AX12: =POWER(1+K12,10)*AH12 -> #N/A | AY12: =AX12/AH12 -> #N/A | AZ12: =AW12-AX12-FV(AI12/12,(10*12),AO12,-AJ12) -> #N/A | BA12: =AZ12/X12 -> #N/A
B13: 90011 | C13: =IFERROR(VLOOKUP(LEFT(B13,FIND("County",B13)-2),CaseShiller30,2,0),"No Data") -> No Data | D13: =_xlfn.XLOOKUP($B13,'Paste Snowflake Data Here'!$B$3:$B$1048576,'Paste Snowflake Data Here'!$D$3:$D$1048576) -> #N/A | F13: =_xlfn.XLOOKUP($B13,'Paste Snowflake Data Here'!$B$3:$B$1048576,'Paste Snowflake Data Here'!$I$3:$I$1048576) -> #N/A | G13: =_xlfn.XLOOKUP($B13,'Paste Snowflake Data Here'!$B$3:$B$1048576,'Paste Snowflake Data Here'!$J$3:$J$1048576) -> #N/A | K13: =IFERROR(VLOOKUP(LEFT(B13,FIND("County",B13)-2),CaseShiller30,5,0)*0.01,$K$3) -> 0.05 | L13: =$F13*$L$3 -> #N/A | M13: =$G13*$M$3 -> #N/A | N13: =AND(AF13<$AF$3,AG13<$AG$3) -> #N/A | O13: =AND(AP13<$AP$3,AQ13<$AQ$3) -> #N/A | P13: =AND(N13=FALSE,O13) -> #N/A | Q13: =AH13 -> #N/A | R13: =AU13 -> #N/A | S13: =AR13 -> #N/A | T13: =AZ13 -> #N/A | U13: =BA13 -> #N/A | V13: =AX13 -> #N/A | W13: =AY13 -> #N/A | X13: =$X$3*M13 -> #REF! | Y13: =$Y$3 -> 0.0625 | Z13: =M13-X13 -> #N/A | AA13: =Z13*'PMI Rate Est'!$J$6/12 -> #N/A | AB13: =$AB$3*M13/12 -> #N/A | AC13: =$AC$3*M13/12 -> #N/A | AD13: =MAX(J13*Y13/12,0) -> 0 | AE13: =-PMT(Y13/12,360,Z13) -> #N/A | AF13: =SUM(AE13,AC13,AB13,AA13)/(L13/12) -> #N/A | AG13: =SUM(AE13,AC13,AB13,AA13,AD13)/(L13/12) -> #N/A | AH13: =M13*$AH$3 -> #N/A | AI13: =Y13+$AI$3 -> 0.0625 | AJ13: =M13-X13-AH13 -> #N/A | AK13: =AH13*$AK$3/12 -> #N/A | AL13: =$AL$3*M13/12 -> #N/A | AM13: =$AM$3*M13/12 -> #N/A | AN13: =MAX(J13*Y13/12,0) -> 0 | AO13: =-PMT(AI13/12,360,AJ13) -> #N/A | AP13: =SUM(AO13,AM13,AL13)/(L13/12) -> #N/A | AQ13: =SUM(AO13,AM13,AL13,AK13,AN13)/(L13/12) -> #N/A | AR13: =$AR$3*AK13*12 -> #N/A | AS13: =$AS$3*(M13-X13) -> #N/A | AT13: =$AT$3*(AH13) -> #N/A | AU13: =$AU$3*SUM(AR13,AS13,AT13) -> #N/A | AV13: =AU13/M13 -> #N/A | AW13: =POWER(1+K13,10)*M13 -> #N/A | AX13: =POWER(1+K13,10)*AH13 -> #N/A | AY13: =AX13/AH13 -> #N/A | AZ13: =AW13-AX13-FV(AI13/12,(10*12),AO13,-AJ13) -> #N/A | BA13: =AZ13/X13 -> #N/A
B14: 90012 | C14: =IFERROR(VLOOKUP(LEFT(B14,FIND("County",B14)-2),CaseShiller30,2,0),"No Data") -> No Data | D14: =_xlfn.XLOOKUP($B14,'Paste Snowflake Data Here'!$B$3:$B$1048576,'Paste Snowflake Data Here'!$D$3:$D$1048576) -> #N/A | F14: =_xlfn.XLOOKUP($B14,'Paste Snowflake Data Here'!$B$3:$B$1048576,'Paste Snowflake Data Here'!$I$3:$I$1048576) -> #N/A | G14: =_xlfn.XLOOKUP($B14,'Paste Snowflake Data Here'!$B$3:$B$1048576,'Paste Snowflake Data Here'!$J$3:$J$1048576) -> #N/A | K14: =IFERROR(VLOOKUP(LEFT(B14,FIND("County",B14)-2),CaseShiller30,5,0)*0.01,$K$3) -> 0.05 | L14: =$F14*$L$3 -> #N/A | M14: =$G14*$M$3 -> #N/A | N14: =AND(AF14<$AF$3,AG14<$AG$3) -> #N/A | O14: =AND(AP14<$AP$3,AQ14<$AQ$3) -> #N/A | P14: =AND(N14=FALSE,O14) -> #N/A | Q14: =AH14 -> #N/A | R14: =AU14 -> #N/A | S14: =AR14 -> #N/A | T14: =AZ14 -> #N/A | U14: =BA14 -> #N/A | V14: =AX14 -> #N/A | W14: =AY14 -> #N/A | X14: =$X$3*M14 -> #REF! | Y14: =$Y$3 -> 0.0625 | Z14: =M14-X14 -> #N/A | AA14: =Z14*'PMI Rate Est'!$J$6/12 -> #N/A | AB14: =$AB$3*M14/12 -> #N/A | AC14: =$AC$3*M14/12 -> #N/A | AD14: =MAX(J14*Y14/12,0) -> 0 | AE14: =-PMT(Y14/12,360,Z14) -> #N/A | AF14: =SUM(AE14,AC14,AB14,AA14)/(L14/12) -> #N/A | AG14: =SUM(AE14,AC14,AB14,AA14,AD14)/(L14/12) -> #N/A | AH14: =M14*$AH$3 -> #N/A | AI14: =Y14+$AI$3 -> 0.0625 | AJ14: =M14-X14-AH14 -> #N/A | AK14: =AH14*$AK$3/12 -> #N/A | AL14: =$AL$3*M14/12 -> #N/A | AM14: =$AM$3*M14/12 -> #N/A | AN14: =MAX(J14*Y14/12,0) -> 0 | AO14: =-PMT(AI14/12,360,AJ14) -> #N/A | AP14: =SUM(AO14,AM14,AL14)/(L14/12) -> #N/A | AQ14: =SUM(AO14,AM14,AL14,AK14,AN14)/(L14/12) -> #N/A | AR14: =$AR$3*AK14*12 -> #N/A | AS14: =$AS$3*(M14-X14) -> #N/A | AT14: =$AT$3*(AH14) -> #N/A | AU14: =$AU$3*SUM(AR14,AS14,AT14) -> #N/A | AV14: =AU14/M14 -> #N/A | AW14: =POWER(1+K14,10)*M14 -> #N/A | AX14: =POWER(1+K14,10)*AH14 -> #N/A | AY14: =AX14/AH14 -> #N/A | AZ14: =AW14-AX14-FV(AI14/12,(10*12),AO14,-AJ14) -> #N/A | BA14: =AZ14/X14 -> #N/A
B15: 90013 | C15: =IFERROR(VLOOKUP(LEFT(B15,FIND("County",B15)-2),CaseShiller30,2,0),"No Data") -> No Data | D15: =_xlfn.XLOOKUP($B15,'Paste Snowflake Data Here'!$B$3:$B$1048576,'Paste Snowflake Data Here'!$D$3:$D$1048576) -> #N/A | F15: =_xlfn.XLOOKUP($B15,'Paste Snowflake Data Here'!$B$3:$B$1048576,'Paste Snowflake Data Here'!$I$3:$I$1048576) -> #N/A | G15: =_xlfn.XLOOKUP($B15,'Paste Snowflake Data Here'!$B$3:$B$1048576,'Paste Snowflake Data Here'!$J$3:$J$1048576) -> #N/A | K15: =IFERROR(VLOOKUP(LEFT(B15,FIND("County",B15)-2),CaseShiller30,5,0)*0.01,$K$3) -> 0.05 | L15: =$F15*$L$3 -> #N/A | M15: =$G15*$M$3 -> #N/A | N15: =AND(AF15<$AF$3,AG15<$AG$3) -> #N/A | O15: =AND(AP15<$AP$3,AQ15<$AQ$3) -> #N/A | P15: =AND(N15=FALSE,O15) -> #N/A | Q15: =AH15 -> #N/A | R15: =AU15 -> #N/A | S15: =AR15 -> #N/A | T15: =AZ15 -> #N/A | U15: =BA15 -> #N/A | V15: =AX15 -> #N/A | W15: =AY15 -> #N/A | X15: =$X$3*M15 -> #REF! | Y15: =$Y$3 -> 0.0625 | Z15: =M15-X15 -> #N/A | AA15: =Z15*'PMI Rate Est'!$J$6/12 -> #N/A | AB15: =$AB$3*M15/12 -> #N/A | AC15: =$AC$3*M15/12 -> #N/A | AD15: =MAX(J15*Y15/12,0) -> 0 | AE15: =-PMT(Y15/12,360,Z15) -> #N/A | AF15: =SUM(AE15,AC15,AB15,AA15)/(L15/12) -> #N/A | AG15: =SUM(AE15,AC15,AB15,AA15,AD15)/(L15/12) -> #N/A | AH15: =M15*$AH$3 -> #N/A | AI15: =Y15+$AI$3 -> 0.0625 | AJ15: =M15-X15-AH15 -> #N/A | AK15: =AH15*$AK$3/12 -> #N/A | AL15: =$AL$3*M15/12 -> #N/A | AM15: =$AM$3*M15/12 -> #N/A | AN15: =MAX(J15*Y15/12,0) -> 0 | AO15: =-PMT(AI15/12,360,AJ15) -> #N/A | AP15: =SUM(AO15,AM15,AL15)/(L15/12) -> #N/A | AQ15: =SUM(AO15,AM15,AL15,AK15,AN15)/(L15/12) -> #N/A | AR15: =$AR$3*AK15*12 -> #N/A | AS15: =$AS$3*(M15-X15) -> #N/A | AT15: =$AT$3*(AH15) -> #N/A | AU15: =$AU$3*SUM(AR15,AS15,AT15) -> #N/A | AV15: =AU15/M15 -> #N/A | AW15: =POWER(1+K15,10)*M15 -> #N/A | AX15: =POWER(1+K15,10)*AH15 -> #N/A | AY15: =AX15/AH15 -> #N/A | AZ15: =AW15-AX15-FV(AI15/12,(10*12),AO15,-AJ15) -> #N/A | BA15: =AZ15/X15 -> #N/A
B16: 90014 | C16: =IFERROR(VLOOKUP(LEFT(B16,FIND("County",B16)-2),CaseShiller30,2,0),"No Data") -> No Data | D16: =_xlfn.XLOOKUP($B16,'Paste Snowflake Data Here'!$B$3:$B$1048576,'Paste Snowflake Data Here'!$D$3:$D$1048576) -> #N/A | F16: =_xlfn.XLOOKUP($B16,'Paste Snowflake Data Here'!$B$3:$B$1048576,'Paste Snowflake Data Here'!$I$3:$I$1048576) -> #N/A | G16: =_xlfn.XLOOKUP($B16,'Paste Snowflake Data Here'!$B$3:$B$1048576,'Paste Snowflake Data Here'!$J$3:$J$1048576) -> #N/A | K16: =IFERROR(VLOOKUP(LEFT(B16,FIND("County",B16)-2),CaseShiller30,5,0)*0.01,$K$3) -> 0.05 | L16: =$F16*$L$3 -> #N/A | M16: =$G16*$M$3 -> #N/A | N16: =AND(AF16<$AF$3,AG16<$AG$3) -> #N/A | O16: =AND(AP16<$AP$3,AQ16<$AQ$3) -> #N/A | P16: =AND(N16=FALSE,O16) -> #N/A | Q16: =AH16 -> #N/A | R16: =AU16 -> #N/A | S16: =AR16 -> #N/A | T16: =AZ16 -> #N/A | U16: =BA16 -> #N/A | V16: =AX16 -> #N/A | W16: =AY16 -> #N/A | X16: =$X$3*M16 -> #REF! | Y16: =$Y$3 -> 0.0625 | Z16: =M16-X16 -> #N/A | AA16: =Z16*'PMI Rate Est'!$J$6/12 -> #N/A | AB16: =$AB$3*M16/12 -> #N/A | AC16: =$AC$3*M16/12 -> #N/A | AD16: =MAX(J16*Y16/12,0) -> 0 | AE16: =-PMT(Y16/12,360,Z16) -> #N/A | AF16: =SUM(AE16,AC16,AB16,AA16)/(L16/12) -> #N/A | AG16: =SUM(AE16,AC16,AB16,AA16,AD16)/(L16/12) -> #N/A | AH16: =M16*$AH$3 -> #N/A | AI16: =Y16+$AI$3 -> 0.0625 | AJ16: =M16-X16-AH16 -> #N/A | AK16: =AH16*$AK$3/12 -> #N/A | AL16: =$AL$3*M16/12 -> #N/A | AM16: =$AM$3*M16/12 -> #N/A | AN16: =MAX(J16*Y16/12,0) -> 0 | AO16: =-PMT(AI16/12,360,AJ16) -> #N/A | AP16: =SUM(AO16,AM16,AL16)/(L16/12) -> #N/A | AQ16: =SUM(AO16,AM16,AL16,AK16,AN16)/(L16/12) -> #N/A | AR16: =$AR$3*AK16*12 -> #N/A | AS16: =$AS$3*(M16-X16) -> #N/A | AT16: =$AT$3*(AH16) -> #N/A | AU16: =$AU$3*SUM(AR16,AS16,AT16) -> #N/A | AV16: =AU16/M16 -> #N/A | AW16: =POWER(1+K16,10)*M16 -> #N/A | AX16: =POWER(1+K16,10)*AH16 -> #N/A | AY16: =AX16/AH16 -> #N/A | AZ16: =AW16-AX16-FV(AI16/12,(10*12),AO16,-AJ16) -> #N/A | BA16: =AZ16/X16 -> #N/A
... B19: 90017 | C19: =IFERROR(VLOOKUP(LEFT(B19,FIND("County",B19)-2),CaseShiller30,2,0),"No Data") -> No Data | D19: =_xlfn.XLOOKUP($B19,'Paste Snowflake Data Here'!$B$3:$B$1048576,'Paste Snowflake Data Here'!$D$3:$D$1048576) -> #N/A | F19: =_xlfn.XLOOKUP($B19,'Paste Snowflake Data Here'!$B$3:$B$1048576,'Paste Snowflake Data Here'!$I$3:$I$1048576) -> #N/A | G19: =_xlfn.XLOOKUP($B19,'Paste Snowflake Data Here'!$B$3:$B$1048576,'Paste Snowflake Data Here'!$J$3:$J$1048576) -> #N/A | K19: =IFERROR(VLOOKUP(LEFT(B19,FIND("County",B19)-2),CaseShiller30,5,0)*0.01,$K$3) -> 0.05 | L19: =$F19*$L$3 -> #N/A | M19: =$G19*$M$3 -> #N/A | N19: =AND(AF19<$AF$3,AG19<$AG$3) -> #N/A | O19: =AND(AP19<$AP$3,AQ19<$AQ$3) -> #N/A | P19: =AND(N19=FALSE,O19) -> #N/A | Q19: =AH19 -> #N/A | R19: =AU19 -> #N/A | S19: =AR19 -> #N/A | T19: =AZ19 -> #N/A | U19: =BA19 -> #N/A | V19: =AX19 -> #N/A | W19: =AY19 -> #N/A | X19: =$X$3*M19 -> #REF! | Y19: =$Y$3 -> 0.0625 | Z19: =M19-X19 -> #N/A | AA19: =Z19*'PMI Rate Est'!$J$6/12 -> #N/A | AB19: =$AB$3*M19/12 -> #N/A | AC19: =$AC$3*M19/12 -> #N/A | AD19: =MAX(J19*Y19/12,0) -> 0 | AE19: =-PMT(Y19/12,360,Z19) -> #N/A | AF19: =SUM(AE19,AC19,AB19,AA19)/(L19/12) -> #N/A | AG19: =SUM(AE19,AC19,AB19,AA19,AD19)/(L19/12) -> #N/A | AH19: =M19*$AH$3 -> #N/A | AI19: =Y19+$AI$3 -> 0.0625 | AJ19: =M19-X19-AH19 -> #N/A | AK19: =AH19*$AK$3/12 -> #N/A | AL19: =$AL$3*M19/12 -> #N/A | AM19: =$AM$3*M19/12 -> #N/A | AN19: =MAX(J19*Y19/12,0) -> 0 | AO19: =-PMT(AI19/12,360,AJ19) -> #N/A | AP19: =SUM(AO19,AM19,AL19)/(L19/12) -> #N/A | AQ19: =SUM(AO19,AM19,AL19,AK19,AN19)/(L19/12) -> #N/A | AR19: =$AR$3*AK19*12 -> #N/A | AS19: =$AS$3*(M19-X19) -> #N/A | AT19: =$AT$3*(AH19) -> #N/A | AU19: =$AU$3*SUM(AR19,AS19,AT19) -> #N/A | AV19: =AU19/M19 -> #N/A | AW19: =POWER(1+K19,10)*M19 -> #N/A | AX19: =POWER(1+K19,10)*AH19 -> #N/A | AY19: =AX19/AH19 -> #N/A | AZ19: =AW19-AX19-FV(AI19/12,(10*12),AO19,-AJ19) -> #N/A | BA19: =AZ19/X19 -> #N/A
B20: 90018
B21: 90019
B22: 90020
B23: 90021
B24: 90022
B25: 90023
B26: 90024
B27: 90025
B28: 90026
B29: 90027
B30: 90028
B31: 90029
... B131: 90639
B132: 90640 | Q132: =AVERAGE(N124:P124) -> #DIV/0!
B133: 90650 | Q133: =AVERAGE(N125:P125) -> #DIV/0!
B134: 90660 | Q134: =AVERAGE(N126:P126) -> #DIV/0!
B135: 90670
B136: 90680
B137: 90701
B138: 90703
B139: 90704
B140: 90706
B141: 90710
B142: 90712
B143: 90713
B144: 90715
B145: 90716
B146: 90717
... B1739: 96162

Sheet Map Counties
A1: Wayne County, Michigan (Black & Brown ONLY)
A2: Country | B2: Zip Code | C2: State | D2: Median Income Can't Buy Low/Mid Home | AB2: Zip Codes in Wayne County, MI where % AA > 49.54%
A3: United States | B3: =#REF! -> #REF! | C3: Michigan | D3: =IF(VLOOKUP(B3,#REF!,14,FALSE)=FALSE, "No","Yes") -> #REF!
A4: United States | B4: =#REF! -> #REF! | C4: Michigan | D4: =IF(VLOOKUP(B4,#REF!,14,FALSE)=FALSE, "No","Yes") -> #REF!
A5: United States | B5: =#REF! -> #REF! | C5: Michigan | D5: =IF(VLOOKUP(B5,#REF!,14,FALSE)=FALSE, "No","Yes") -> #REF!
A6: United States | B6: =#REF! -> #REF! | C6: Michigan | D6: =IF(VLOOKUP(B6,#REF!,14,FALSE)=FALSE, "No","Yes") -> #REF!
A7: United States | B7: =#REF! -> #REF! | C7: Michigan | D7: =IF(VLOOKUP(B7,#REF!,14,FALSE)=FALSE, "No","Yes") -> #REF!
A8: United States | B8: =#REF! -> #REF! | C8: Michigan | D8: =IF(VLOOKUP(B8,#REF!,14,FALSE)=FALSE, "No","Yes") -> #REF!
A9: United States | B9: =#REF! -> #REF! | C9: Michigan | D9: =IF(VLOOKUP(B9,#REF!,14,FALSE)=FALSE, "No","Yes") -> #REF!
A10: United States | B10: =#REF! -> #REF! | C10: Michigan | D10: =IF(VLOOKUP(B10,#REF!,14,FALSE)=FALSE, "No","Yes") -> #REF!
A11: United States | B11: =#REF! -> #REF! | C11: Michigan | D11: =IF(VLOOKUP(B11,#REF!,14,FALSE)=FALSE, "No","Yes") -> #REF!
A12: United States | B12: =#REF! -> #REF! | C12: Michigan | D12: =IF(VLOOKUP(B12,#REF!,14,FALSE)=FALSE, "No","Yes") -> #REF!
A13: United States | B13: =#REF! -> #REF! | C13: Michigan | D13: =IF(VLOOKUP(B13,#REF!,14,FALSE)=FALSE, "No","Yes") -> #REF!
A14: United States | B14: =#REF! -> #REF! | C14: Michigan | D14: =IF(VLOOKUP(B14,#REF!,14,FALSE)=FALSE, "No","Yes") -> #REF!
... A26: United States | B26: =#REF! -> #REF! | C26: Michigan | D26: =IF(VLOOKUP(B26,#REF!,14,FALSE)=FALSE, "No","Yes") -> #REF!
A29: Country | B29: Zip Code | C29: State | D29: Median Income CAN Buy Low/Mid Home with Homium
A30: United States | B30: =#REF! -> #REF! | C30: Michigan | D30: =IF(VLOOKUP(B30,#REF!,15,FALSE)=FALSE, "No","Yes") -> #REF!
A31: United States | B31: =#REF! -> #REF! | C31: Michigan | D31: =IF(VLOOKUP(B31,#REF!,15,FALSE)=FALSE, "No","Yes") -> #REF!
A32: United States | B32: =#REF! -> #REF! | C32: Michigan | D32: =IF(VLOOKUP(B32,#REF!,15,FALSE)=FALSE, "No","Yes") -> #REF!
A33: United States | B33: =#REF! -> #REF! | C33: Michigan | D33: =IF(VLOOKUP(B33,#REF!,15,FALSE)=FALSE, "No","Yes") -> #REF!
A34: United States | B34: =#REF! -> #REF! | C34: Michigan | D34: =IF(VLOOKUP(B34,#REF!,15,FALSE)=FALSE, "No","Yes") -> #REF!
A35: United States | B35: =#REF! -> #REF! | C35: Michigan | D35: =IF(VLOOKUP(B35,#REF!,15,FALSE)=FALSE, "No","Yes") -> #REF!
A36: United States | B36: =#REF! -> #REF! | C36: Michigan | D36: =IF(VLOOKUP(B36,#REF!,15,FALSE)=FALSE, "No","Yes") -> #REF!
A37: United States | B37: =#REF! -> #REF! | C37: Michigan | D37: =IF(VLOOKUP(B37,#REF!,15,FALSE)=FALSE, "No","Yes") -> #REF!
A38: United States | B38: =#REF! -> #REF! | C38: Michigan | D38: =IF(VLOOKUP(B38,#REF!,15,FALSE)=FALSE, "No","Yes") -> #REF!
A39: United States | B39: =#REF! -> #REF! | C39: Michigan | D39: =IF(VLOOKUP(B39,#REF!,15,FALSE)=FALSE, "No","Yes") -> #REF!
A40: United States | B40: =#REF! -> #REF! | C40: Michigan | D40: =IF(VLOOKUP(B40,#REF!,15,FALSE)=FALSE, "No","Yes") -> #REF!
A41: United States | B41: =#REF! -> #REF! | C41: Michigan | D41: =IF(VLOOKUP(B41,#REF!,15,FALSE)=FALSE, "No","Yes") -> #REF!
... A53: United States | B53: =#REF! -> #REF! | C53: Michigan | D53: =IF(VLOOKUP(B53,#REF!,15,FALSE)=FALSE, "No","Yes") -> #REF!
A61: Target Zip Codes Converted
A66: Country | B66: County | C66: State | D66: Median Income Can't Buy Low/Mid Home
A67: United States | B67: Alcona | C67: ='Paste Snowflake Data Here'!C3 -> 0 | D67: =IF(VLOOKUP(B67,'Aggregate Model'!$B$4:$BA$23,13,FALSE)=FALSE, "No","Yes") -> #N/A
A68: United States | B68: Alger County | C68: =C67 -> 0 | D68: =IF(VLOOKUP(B68,'Aggregate Model'!$B$4:$BA$23,13,FALSE)=FALSE, "No","Yes") -> #N/A
A69: United States | B69: Allegan | C69: =C68 -> 0 | D69: =IF(VLOOKUP(B69,'Aggregate Model'!$B$4:$BA$23,13,FALSE)=FALSE, "No","Yes") -> #N/A
A70: United States | B70: Alpena County | C70: =C69 -> 0 | D70: =IF(VLOOKUP(B70,'Aggregate Model'!$B$4:$BA$23,13,FALSE)=FALSE, "No","Yes") -> #N/A
A71: United States | B71: Antrim | C71: =C70 -> 0 | D71: =IF(VLOOKUP(B71,'Aggregate Model'!$B$4:$BA$23,13,FALSE)=FALSE, "No","Yes") -> #N/A
A72: United States | B72: Arenac | C72: =C71 -> 0 | D72: =IF(VLOOKUP(B72,'Aggregate Model'!$B$4:$BA$23,13,FALSE)=FALSE, "No","Yes") -> #N/A
A73: United States | B73: Baraga | C73: =C72 -> 0 | D73: =IF(VLOOKUP(B73,'Aggregate Model'!$B$4:$BA$23,13,FALSE)=FALSE, "No","Yes") -> #N/A
A74: United States | B74: Barry | C74: =C73 -> 0 | D74: =IF(VLOOKUP(B74,'Aggregate Model'!$B$4:$BA$23,13,FALSE)=FALSE, "No","Yes") -> #N/A
A75: United States | B75: Bay | C75: =C74 -> 0 | D75: =IF(VLOOKUP(B75,'Aggregate Model'!$B$4:$BA$23,13,FALSE)=FALSE, "No","Yes") -> #N/A
A76: United States | B76: Benzie | C76: =C75 -> 0 | D76: =IF(VLOOKUP(B76,'Aggregate Model'!$B$4:$BA$23,13,FALSE)=FALSE, "No","Yes") -> #N/A
A77: United States | B77: Berrien | C77: =C76 -> 0 | D77: =IF(VLOOKUP(B77,'Aggregate Model'!$B$4:$BA$23,13,FALSE)=FALSE, "No","Yes") -> #N/A
A78: United States | B78: Branch | C78: =C77 -> 0 | D78: =IF(VLOOKUP(B78,'Aggregate Model'!$B$4:$BA$23,13,FALSE)=FALSE, "No","Yes") -> #N/A
A79: United States | B79: Calhoun | C79: =C78 -> 0 | D79: =IF(VLOOKUP(B79,'Aggregate Model'!$B$4:$BA$23,13,FALSE)=FALSE, "No","Yes") -> #N/A
... A149: United States | B149: Wexford County | C149: =C148 -> 0 | D149: =IF(VLOOKUP(B149,'Aggregate Model'!$B$4:$BA$23,13,FALSE)=FALSE, "No","Yes") -> #N/A
A155: Country | B155: County | C155: State | D155: Median Income CAN Buy Low/Mid Home with Homium
A156: United States | B156: Alcona | C156: Michigan | D156: =IF(VLOOKUP(B156,'Aggregate Model'!$B$4:$BA$23,14,FALSE)=FALSE, "No","Yes") -> #N/A
A157: United States | B157: Alger County | C157: Michigan | D157: =IF(VLOOKUP(B157,'Aggregate Model'!$B$4:$BA$23,14,FALSE)=FALSE, "No","Yes") -> #N/A
A158: United States | B158: Allegan | C158: Michigan | D158: =IF(VLOOKUP(B158,'Aggregate Model'!$B$4:$BA$23,14,FALSE)=FALSE, "No","Yes") -> #N/A
A159: United States | B159: Alpena County | C159: Michigan | D159: =IF(VLOOKUP(B159,'Aggregate Model'!$B$4:$BA$23,14,FALSE)=FALSE, "No","Yes") -> #N/A
A160: United States | B160: Antrim | C160: Michigan | D160: =IF(VLOOKUP(B160,'Aggregate Model'!$B$4:$BA$23,14,FALSE)=FALSE, "No","Yes") -> #N/A
A161: United States | B161: Arenac | C161: Michigan | D161: =IF(VLOOKUP(B161,'Aggregate Model'!$B$4:$BA$23,14,FALSE)=FALSE, "No","Yes") -> #N/A
A162: United States | B162: Baraga | C162: Michigan | D162: =IF(VLOOKUP(B162,'Aggregate Model'!$B$4:$BA$23,14,FALSE)=FALSE, "No","Yes") -> #N/A
A163: United States | B163: Barry | C163: Michigan | D163: =IF(VLOOKUP(B163,'Aggregate Model'!$B$4:$BA$23,14,FALSE)=FALSE, "No","Yes") -> #N/A
A164: United States | B164: Bay | C164: Michigan | D164: =IF(VLOOKUP(B164,'Aggregate Model'!$B$4:$BA$23,14,FALSE)=FALSE, "No","Yes") -> #N/A
A165: United States | B165: Benzie | C165: Michigan | D165: =IF(VLOOKUP(B165,'Aggregate Model'!$B$4:$BA$23,14,FALSE)=FALSE, "No","Yes") -> #N/A
A166: United States | B166: Berrien | C166: Michigan | D166: =IF(VLOOKUP(B166,'Aggregate Model'!$B$4:$BA$23,14,FALSE)=FALSE, "No","Yes") -> #N/A
A167: United States | B167: Branch | C167: Michigan | D167: =IF(VLOOKUP(B167,'Aggregate Model'!$B$4:$BA$23,14,FALSE)=FALSE, "No","Yes") -> #N/A
... A238: United States | B238: Wexford County | C238: Michigan | D238: =IF(VLOOKUP(B238,'Aggregate Model'!$B$4:$BA$23,14,FALSE)=FALSE, "No","Yes") -> #N/A

Sheet States
A1: Location | B1: Governor | C1: Party | D1: Eligibility | E1: 2025 Median Home Value | F1: 2025 Median Household Income | G1: 2025 Total Population | H1: 2025 Median Monthly Contract Rent | I1: 2025 Housing Affordability Index | J1: 2025 Median Disposable Income
A2: Delaware | B2: Matt Meyer | C2: Democratic | D2: Eligible | E2: 389964 | F2: 84523 | G2: 1043909 | H2: 1322 | I2: 85 | J2: 69259
A3: Hawaii | B3: Josh Green | C3: Democratic | D3: Eligible/Running | E3: 924013 | F3: 101529 | G3: 1480456 | H3: 1807 | I3: 46 | J3: 80868
A4: Illinois | B4: JB Pritzker | C4: Democratic | D4: Eligible/Running | E4: 286497 | F4: 84176 | G4: 12439592 | H4: 1205 | I4: 95 | J4: 66780
A5: Maryland | B5: Wes Moore | C5: Democratic | D5: Eligible/Running | E5: 468044 | F5: 103503 | G5: 6270068 | H5: 1654 | I5: 82 | J5: 80613
A6: Massachusetts | B6: Maura Healey | C6: Democratic | D6: Eligible/Running | E6: 637329 | F6: 105410 | G6: 7069210 | H6: 1763 | I6: 61 | J6: 82883
A7: New Jersey | B7: Mikie Sherrill | C7: Democratic | D7: Eligible | E7: 513938 | F7: 104287 | G7: 9425430 | H7: 1679 | I7: 66 | J7: 84725
A8: New York | B8: Kathy Hochul | C8: Democratic | D8: Eligible/Running | E8: 485429 | F8: 85744 | G8: 19998175 | H8: 1617 | I8: 62 | J8: 68085
A9: North Carolina | B9: Josh Stein | C9: Democratic | D9: Eligible | E9: 334561 | F9: 74690 | G9: 10995758 | H9: 1180 | I9: 84 | J9: 60103
A10: Oregon | B10: Tina Kotek | C10: Democratic | D10: Eligible/Running | E10: 549301 | F10: 84398 | G10: 4365325 | H10: 1477 | I10: 59 | J10: 64958
A11: Pennsylvania | B11: Josh Shapiro | C11: Democratic | D11: Eligible/Running | E11: 303362 | F11: 77579 | G11: 13074028 | H11: 1159 | I11: 89 | J11: 62289
A12: Rhode Island | B12: Dan McKee | C12: Democratic | D12: Eligible/Running | E12: 447602 | F12: 88514 | G12: 1101918 | H12: 1303 | I12: 70 | J12: 71319
A13: Washington | B13: Bob Ferguson | C13: Democratic | D13: Eligible | E13: 641336 | F13: 100361 | G13: 8076991 | H13: 1701 | I13: 60 | J13: 83530
... A15: Connecticut | B15: Ned Lamont | C15: Democratic | D15: Eligible/Running | E15: 407234 | F15: 95275 | G15: 3608872 | H15: 1394 | I15: 78 | J15: 75670
A16: California | E16: 773228 | F16: 101136 | G16: 39563914 | H16: 1988
A17: Kansas | E17: 243477 | F17: 72975 | G17: 2967337 | H17: 899
A18: Kentucky | E18: 227462 | F18: 63706 | G18: 4584322 | H18: 809
A19: Michigan | E19: 259246 | F19: 72645 | G19: 10042188 | H19: 1004
A20: Minnesota | E20: 370277 | F20: 88297 | G20: 5852943 | H20: 1315

Sheet Paste Snowflake Data Here
A1: ***DELETE OLD DATA THEN paste in B3***
B2: Zip | D2: Total Population | I2: Median household index | J2: Median Household Value | K2: 2025 Median Monthly Contract Rent
A3: 0 | B3: Delaware | D3: 1043909 | I3: 84523 | J3: 389964 | K3: 1322
A4: 1 | B4: Hawaii | D4: 1480456 | I4: 101529 | J4: 924013 | K4: 1807
A5: 2 | B5: Illinois | D5: 12439592 | I5: 84176 | J5: 286497 | K5: 1205
A6: 3 | B6: Maryland | D6: 6270068 | I6: 103503 | J6: 468044 | K6: 1654
A7: 4 | B7: Massachusetts | D7: 7069210 | I7: 105410 | J7: 637329 | K7: 1763
A8: 5 | B8: New Jersey | D8: 9425430 | I8: 104287 | J8: 513938 | K8: 1679
A9: 6 | B9: New York | D9: 19998175 | I9: 85744 | J9: 485429 | K9: 1617
A10: 7 | B10: North Carolina | D10: 10995758 | I10: 74690 | J10: 334561 | K10: 1180
A11: 8 | B11: Oregon | D11: 4365325 | I11: 84398 | J11: 549301 | K11: 1477
A12: 9 | B12: Pennsylvania | D12: 13074028 | I12: 77579 | J12: 303362 | K12: 1159
A13: 10 | B13: Rhode Island | D13: 1101918 | I13: 88514 | J13: 447602 | K13: 1303
A14: 11 | B14: Washington | D14: 8076991 | I14: 100361 | J14: 641336 | K14: 1701
... A21: 18 | B21: Minnesota | D21: 5852943 | I21: 88297 | J21: 370277 | K21: 1315
A22: 19
A23: 20
A24: 21
A25: 22
A26: 23
A27: 24
A28: 25
A29: 26
A30: 27
A31: 28
A32: 29
A33: 30
... A60: 57
B987: 94127 | C987: California | D987: 17436 | E987: 39530491 | F987: 200001 | G987: 1745920 | H987: 5 | I987: 200001 | J987: 1745920 | K987: 52377.6 | L987: 7 | M987: 436480 | N987: 1257062.4 | O987: 8363.2675 | P987: 0.0004 | Q987: 1033.0027 | R987: 872.96 | S987: 0 | T987: 10269.23 | U987: 1693542.4 | V987: 11267.18 | W987: 88.945633 | X987: 1651.2038 | Y987: 1033.0027 | Z987: 872.96 | AA987: 61.615073 | AB987: FALSE | AC987: FALSE | AD987: 2843919.7 | AE987: 710979.93 | AF987: 1078715.2 | AG987: 1054224.6 | AH987: 19.127394 | AI987: 0.62889463 | AJ987: FALSE
B988: 94128 | C988: California | D988: 11 | E988: 39530491 | F988: 175000 | G988: 1750000 | H988: 5 | I988: 175000 | J988: 1750000 | K988: 52500 | L988: 7 | M988: 437500 | N988: 1260000 | O988: 8382.8114 | P988: 0 | Q988: 1035.4167 | R988: 875 | S988: 0 | T988: 10293.228 | U988: 1697500 | V988: 11293.51 | W988: 101.89021 | X988: 1655.0625 | Y988: 1035.4167 | Z988: 875 | AA988: 70.582136 | AB988: FALSE | AC988: FALSE | AD988: 2850565.6 | AE988: 712641.4 | AF988: 1081236 | AG988: 1056688.2 | AH988: 19.127394 | AI988: 0.62889463 | AJ988: FALSE
B989: 94129 | C989: California | D989: 3422 | E989: 39530491 | F989: 200001 | G989: 0 | H989: 5 | I989: 200001 | J989: 0 | K989: 0 | L989: 7 | M989: 0 | N989: 0 | O989: 0 | P989: 0.0001 | Q989: 0 | R989: 0 | S989: 0 | T989: 0 | U989: 0 | V989: 0 | W989: 0 | X989: 0 | Y989: 0 | Z989: 0 | AA989: 0 | AB989: TRUE | AC989: TRUE | AD989: 0 | AE989: 0 | AF989: 0 | AG989: 0 | AJ989: FALSE
B990: 94130 | C990: California | D990: 3351 | E990: 39530491 | F990: 98137 | G990: 1570513 | H990: 5 | I990: 98137 | J990: 1570513 | K990: 47115.39 | L990: 7 | M990: 392628.25 | N990: 1130769.4 | O990: 7523.0368 | P990: 0.0001 | Q990: 929.22019 | R990: 785.2565 | S990: 0 | T990: 9237.5135 | U990: 1523397.6 | V990: 10135.202 | W990: 163.05766 | X990: 1485.3127 | Y990: 929.22019 | Z990: 785.2565 | AA990: 112.9545 | AB990: FALSE | AC990: FALSE | AD990: 2558200.2 | AE990: 639550.05 | AF990: 970340.14 | AG990: 948310 | AH990: 19.127394 | AI990: 0.62889463 | AJ990: FALSE
B991: 94131 | C991: California | D991: 27855 | E991: 39530491 | F991: 200001 | G991: 1656458 | H991: 5 | I991: 200001 | J991: 1656458 | K991: 49693.74 | L991: 7 | M991: 414114.5 | N991: 1192649.8 | O991: 7934.7286 | P991: 0.0007 | Q991: 980.07098 | R991: 828.229 | S991: 0 | T991: 9743.0286 | U991: 1606764.3 | V991: 10689.843 | W991: 84.388005 | X991: 1566.5952 | Y991: 980.07098 | Z991: 828.229 | AA991: 58.457879 | AB991: FALSE | AC991: FALSE | AD991: 2698195.5 | AE991: 674548.88 | AF991: 1023441.2 | AG991: 1000205.5 | AH991: 19.127394 | AI991: 0.62889463 | AJ991: FALSE
B992: 94132 | C992: California | D992: 26395 | E992: 39530491 | F992: 103599 | G992: 1356802 | H992: 5 | I992: 103599 | J992: 1356802 | K992: 40704.06 | L992: 7 | M992: 339200.5 | N992: 976897.44 | O992: 6499.323 | P992: 0.0007 | Q992: 802.77452 | R992: 678.401 | S992: 0 | T992: 7980.4986 | U992: 1316097.9 | V992: 8756.0324 | W992: 133.44225 | X992: 1283.1955 | Y992: 802.77452 | Z992: 678.401 | AA992: 92.4391 | AB992: FALSE | AC992: FALSE | AD992: 2210087.5 | AE992: 552521.87 | AF992: 838298.98 | AG992: 819266.64 | AH992: 19.127394 | AI992: 0.62889463 | AJ992: FALSE
B993: 94133 | C993: California | D993: 24756 | E993: 39530491 | F993: 83854 | G993: 1634698 | H993: 5 | I993: 83854 | J993: 1634698 | K993: 49040.94 | L993: 7 | M993: 408674.5 | N993: 1176982.6 | O993: 7830.4943 | P993: 0.0006 | Q993: 967.19632 | R993: 817.349 | S993: 0 | T993: 9615.0397 | U993: 1585657.1 | V993: 10549.416 | W993: 198.63062 | X993: 1546.0156 | Y993: 967.19632 | Z993: 817.349 | AA993: 137.59687 | AB993: FALSE | AC993: FALSE | AD993: 2662750.8 | AE993: 665687.7 | AF993: 1009996.8 | AG993: 987066.3 | AH993: 19.127394 | AI993: 0.62889463 | AJ993: FALSE
B994: 94134 | C994: California | D994: 39957 | E994: 39530491 | F994: 103343 | G994: 1094647 | H994: 5 | I994: 103343 | J994: 1094647 | K994: 32839.41 | L994: 7 | M994: 273661.75 | N994: 788145.84 | O994: 5243.5539 | P994: 0.001 | Q994: 647.66614 | R994: 547.3235 | S994: 0 | T994: 6438.5436 | U994: 1061807.6 | V994: 7064.2324 | W994: 107.92585 | X994: 1035.2624 | Y994: 647.66614 | Z994: 547.3235 | AA994: 74.76319 | AB994: FALSE | AC994: FALSE | AD994: 1783064.6 | AE994: 445766.15 | AF994: 676326.73 | AG994: 660971.73 | AH994: 19.127394 | AI994: 0.62889463 | AJ994: FALSE
B995: 94143 | C995: California | D995: 949 | E995: 39530491 | F995: 168182 | G995: 2000001 | H995: 5 | I995: 168182 | J995: 2000001 | K995: 60000.03 | L995: 7 | M995: 500000.25 | N995: 1440000.7 | O995: 9580.3607 | P995: 0 | Q995: 1183.3339 | R995: 1000.0005 | S995: 0 | T995: 11763.695 | U995: 1940001 | V995: 12906.875 | W995: 121.16667 | X995: 1891.5009 | Y995: 1183.3339 | Z995: 1000.0005 | AA995: 83.935464 | AB995: FALSE | AC995: FALSE | AD995: 3257790.9 | AE995: 814447.72 | AF995: 1235698.9 | AG995: 1207644.2 | AH995: 19.127394 | AI995: 0.62889463 | AJ995: FALSE
B996: 94158 | C996: California | D996: 9672 | E996: 39530491 | F996: 200001 | G996: 1677235 | H996: 5 | I996: 200001 | J996: 1677235 | K996: 50317.05 | L996: 7 | M996: 419308.75 | N996: 1207609.2 | O996: 8034.2541 | P996: 0.0002 | Q996: 992.36404 | R996: 838.6175 | S996: 0 | T996: 9865.2357 | U996: 1626917.9 | V996: 10823.926 | W996: 85.446486 | X996: 1586.245 | Y996: 992.36404 | Z996: 838.6175 | AA996: 59.191118 | AB996: FALSE | AC996: FALSE | AD996: 2732039.1 | AE996: 683009.77 | AF996: 1036278.2 | AG996: 1012751.1 | AH996: 19.127394 | AI996: 0.62889463 | AJ996: FALSE
B997: 94301 | C997: California | D997: 16886 | E997: 39530491 | F997: 200001 | G997: 2000001 | H997: 5 | I997: 200001 | J997: 2000001 | K997: 60000.03 | L997: 7 | M997: 500000.25 | N997: 1440000.7 | O997: 9580.3607 | P997: 0.0004 | Q997: 1183.3339 | R997: 1000.0005 | S997: 0 | T997: 11763.695 | U997: 1940001 | V997: 12906.875 | W997: 101.88975 | X997: 1891.5009 | Y997: 1183.3339 | Z997: 1000.0005 | AA997: 70.581818 | AB997: FALSE | AC997: FALSE | AD997: 3257790.9 | AE997: 814447.72 | AF997: 1235698.9 | AG997: 1207644.2 | AH997: 19.127394 | AI997: 0.62889463 | AJ997: FALSE
B998: 94303 | C998: California | D998: 47189 | E998: 39530491 | F998: 157373 | G998: 2000001 | H998: 5 | I998: 157373 | J998: 2000001 | K998: 60000.03 | L998: 7 | M998: 500000.25 | N998: 1440000.7 | O998: 9580.3607 | P998: 0.0012 | Q998: 1183.3339 | R998: 1000.0005 | S998: 0 | T998: 11763.695 | U998: 1940001 | V998: 12906.875 | W998: 129.48887 | X998: 1891.5009 | Y998: 1183.3339 | Z998: 1000.0005 | AA998: 89.700483 | AB998: FALSE | AC998: FALSE | AD998: 3257790.9 | AE998: 814447.72 | AF998: 1235698.9 | AG998: 1207644.2 | AH998: 19.127394 | AI998: 0.62889463 | AJ998: FALSE
B999: 94304 | C999: California | D999: 4414 | E999: 39530491 | F999: 178712 | G999: 2000001 | H999: 5 | I999: 178712 | J999: 2000001 | K999: 60000.03 | L999: 7 | M999: 500000.25 | N999: 1440000.7 | O999: 9580.3607 | P999: 0.0001 | Q999: 1183.3339 | R999: 1000.0005 | S999: 0 | T999: 11763.695 | U999: 1940001 | V999: 12906.875 | W999: 114.02733 | X999: 1891.5009 | Y999: 1183.3339 | Z999: 1000.0005 | AA999: 78.989851 | AB999: FALSE | AC999: FALSE | AD999: 3257790.9 | AE999: 814447.72 | AF999: 1235698.9 | AG999: 1207644.2 | AH999: 19.127394 | AI999: 0.62889463 | AJ999: FALSE
B1000: 94305 | C1000: California | D1000: 20782 | E1000: 39530491 | F1000: 62231 | G1000: 2000001 | H1000: 5 | I1000: 62231 | J1000: 2000001 | K1000: 60000.03 | L1000: 7 | M1000: 500000.25 | N1000: 1440000.7 | O1000: 9580.3607 | P1000: 0.0005 | Q1000: 1183.3339 | R1000: 1000.0005 | S1000: 0 | T1000: 11763.695 | U1000: 1940001 | V1000: 12906.875 | W1000: 327.45822 | X1000: 1891.5009 | Y1000: 1183.3339 | Z1000: 1000.0005 | AA1000: 226.83926 | AB1000: FALSE | AC1000: FALSE | AD1000: 3257790.9 | AE1000: 814447.72 | AF1000: 1235698.9 | AG1000: 1207644.2 | AH1000: 19.127394 | AI1000: 0.62889463 | AJ1000: FALSE
B1001: 94306 | C1001: California | D1001: 27392 | E1001: 39530491 | F1001: 200001 | G1001: 2000001 | H1001: 5 | I1001: 200001 | J1001: 2000001 | K1001: 60000.03 | L1001: 7 | M1001: 500000.25 | N1001: 1440000.7 | O1001: 9580.3607 | P1001: 0.0007 | Q1001: 1183.3339 | R1001: 1000.0005 | S1001: 0 | T1001: 11763.695 | U1001: 1940001 | V1001: 12906.875 | W1001: 101.88975 | X1001: 1891.5009 | Y1001: 1183.3339 | Z1001: 1000.0005 | AA1001: 70.581818 | AB1001: FALSE | AC1001: FALSE | AD1001: 3257790.9 | AE1001: 814447.72 | AF1001: 1235698.9 | AG1001: 1207644.2 | AH1001: 19.127394 | AI1001: 0.62889463 | AJ1001: FALSE
... B1216: 95140 | C1216: California | D1216: 392 | E1216: 39530491 | F1216: 156721 | G1216: 1705882 | H1216: 5 | I1216: 156721 | J1216: 1705882 | K1216: 51176.46 | L1216: 7 | M1216: 426470.5 | N1216: 1228235 | O1216: 8171.4784 | P1216: 0 | Q1216: 1009.3135 | R1216: 852.941 | S1216: 0 | T1216: 10033.733 | U1216: 1654705.5 | V1216: 11008.797 | W1216: 110.9058 | X1216: 1613.3379 | Y1216: 1009.3135 | Z1216: 852.941 | AA1216: 76.82748 | AB1216: FALSE | AC1216: FALSE | AD1216: 2778702 | AE1216: 694675.51 | AF1216: 1053977.8 | AG1216: 1030048.8 | AH1216: 19.127394 | AI1216: 0.62889463 | AJ1216: FALSE
B1217: 95141 | C1217: California | D1217: 8 | E1217: 39530491 | F1217: 200001 | G1217: 0 | H1217: 5 | I1217: 200001 | J1217: 0 | K1217: 0 | L1217: 7 | M1217: 0 | N1217: 0 | O1217: 0 | P1217: 0 | Q1217: 0 | R1217: 0 | S1217: 0 | T1217: 0 | U1217: 0 | V1217: 0 | W1217: 0 | X1217: 0 | Y1217: 0 | Z1217: 0 | AA1217: 0 | AB1217: TRUE | AC1217: TRUE | AD1217: 0 | AE1217: 0 | AF1217: 0 | AG1217: 0 | AJ1217: FALSE
B1218: 95148 | C1218: California | D1218: 44685 | E1218: 39530491 | F1218: 168192 | G1218: 1322129 | H1218: 5 | I1218: 168192 | J1218: 1322129 | K1218: 39663.87 | L1218: 7 | M1218: 330532.25 | N1218: 951932.88 | O1218: 6333.2332 | P1218: 0.0011 | Q1218: 782.25966 | R1218: 661.0645 | S1218: 0 | T1218: 7776.5574 | U1218: 1282465.1 | V1218: 8532.2725 | W1218: 80.094179 | X1218: 1250.4035 | Y1218: 782.25966 | Z1218: 661.0645 | AA1218: 55.483429 | AB1218: FALSE | AC1218: FALSE | AD1218: 2153608.8 | AE1218: 538402.21 | AF1218: 816876.29 | AG1218: 798330.33 | AH1218: 19.127394 | AI1218: 0.62889463 | AJ1218: FALSE
B1219: 95192 | C1219: California | D1219: 3421 | E1219: 39530491 | F1219: 29725 | G1219: 0 | H1219: 5 | I1219: 29725 | J1219: 0 | K1219: 0 | L1219: 7 | M1219: 0 | N1219: 0 | O1219: 0 | P1219: 0.0001 | Q1219: 0 | R1219: 0 | S1219: 0 | T1219: 0 | U1219: 0 | V1219: 0 | W1219: 0 | X1219: 0 | Y1219: 0 | Z1219: 0 | AA1219: 0 | AB1219: TRUE | AC1219: TRUE | AD1219: 0 | AE1219: 0 | AF1219: 0 | AG1219: 0 | AJ1219: FALSE
B1220: 95202 | C1220: California | D1220: 6653 | E1220: 39530491 | F1220: 23094 | G1220: 359211 | H1220: 5 | I1220: 23094 | J1220: 359211 | K1220: 10776.33 | L1220: 7 | M1220: 89802.75 | N1220: 258631.92 | O1220: 1720.6846 | P1220: 0.0002 | Q1220: 212.53317 | R1220: 179.6055 | S1220: 0 | T1220: 2112.8233 | U1220: 348434.67 | V1220: 2318.1446 | W1220: 158.48309 | X1220: 339.7238 | Y1220: 212.53317 | Z1220: 179.6055 | AA1220: 109.78557 | AB1220: FALSE | AC1220: FALSE | AD1220: 585116.87 | AE1220: 146279.22 | AF1220: 221938.21 | AG1220: 216899.44 | AH1220: 19.127394 | AI1220: 0.62889463 | AJ1220: FALSE
B1221: 95203 | C1221: California | D1221: 18174 | E1221: 39530491 | F1221: 53714 | G1221: 370201 | H1221: 5 | I1221: 53714 | J1221: 370201 | K1221: 11106.03 | L1221: 7 | M1221: 92550.25 | N1221: 266544.72 | O1221: 1773.3287 | P1221: 0.0005 | Q1221: 219.03559 | R1221: 185.1005 | S1221: 0 | T1221: 2177.4648 | U1221: 359094.97 | V1221: 2389.0678 | W1221: 70.223513 | X1221: 350.1176 | Y1221: 219.03559 | Z1221: 185.1005 | AA1221: 48.645748 | AB1221: FALSE | AC1221: FALSE | AD1221: 603018.42 | AE1221: 150754.6 | AF1221: 228728.38 | AG1221: 223535.44 | AH1221: 19.127394 | AI1221: 0.62889463 | AJ1221: FALSE
B1222: 95204 | C1222: California | D1222: 30163 | E1222: 39530491 | F1222: 72574 | G1222: 424097 | H1222: 5 | I1222: 72574 | J1222: 424097 | K1222: 12722.91 | L1222: 7 | M1222: 106024.25 | N1222: 305349.84 | O1222: 2031.5001 | P1222: 0.0008 | Q1222: 250.92406 | R1222: 212.0485 | S1222: 0 | T1222: 2494.4727 | U1222: 411374.09 | V1222: 2736.8821 | W1222: 59.541065 | X1222: 401.08974 | Y1222: 250.92406 | Z1222: 212.0485 | AA1222: 41.245724 | AB1222: FALSE | AC1222: FALSE | AD1222: 690809.32 | AE1222: 172702.33 | AF1222: 262027.98 | AG1222: 256079.02 | AH1222: 19.127394 | AI1222: 0.62889463 | AJ1222: FALSE
B1223: 95205 | C1223: California | D1223: 39839 | E1223: 39530491 | F1223: 55987 | G1223: 281050 | H1223: 5 | I1223: 55987 | J1223: 281050 | K1223: 8431.5 | L1223: 7 | M1223: 70262.5 | N1223: 202356 | O1223: 1346.2795 | P1223: 0.001 | Q1223: 166.28792 | R1223: 140.525 | S1223: 0 | T1223: 1653.0924 | U1223: 272618.5 | V1223: 1813.7377 | W1223: 51.148023 | X1223: 265.80304 | Y1223: 166.28792 | Z1223: 140.525 | AA1223: 35.431634 | AB1223: FALSE | AC1223: FALSE | AD1223: 457800.83 | AE1223: 114450.21 | AF1223: 173646.51 | AG1223: 169704.12 | AH1223: 19.127394 | AI1223: 0.62889463 | AJ1223: FALSE
B1224: 95206 | C1224: California | D1224: 70806 | E1224: 39530491 | F1224: 72482 | G1224: 421229 | H1224: 5 | I1224: 72482 | J1224: 421229 | K1224: 12636.87 | L1224: 7 | M1224: 105307.25 | N1224: 303284.88 | O1224: 2017.7619 | P1224: 0.0018 | Q1224: 249.22716 | R1224: 210.6145 | S1224: 0 | T1224: 2477.6035 | U1224: 408592.13 | V1224: 2718.3736 | W1224: 59.213476 | X1224: 398.37733 | Y1224: 249.22716 | Z1224: 210.6145 | AA1224: 41.018794 | AB1224: FALSE | AC1224: FALSE | AD1224: 686137.65 | AE1224: 171534.41 | AF1224: 260255.98 | AG1224: 254347.26 | AH1224: 19.127394 | AI1224: 0.62889463 | AJ1224: FALSE
B1225: 95207 | C1225: California | D1225: 51701 | E1225: 39530491 | F1225: 67974 | G1225: 453568 | H1225: 5 | I1225: 67974 | J1225: 453568 | K1225: 13607.04 | L1225: 7 | M1225: 113392 | N1225: 326568.96 | O1225: 2172.6714 | P1225: 0.0013 | Q1225: 268.36107 | R1225: 226.784 | S1225: 0 | T1225: 2667.8165 | U1225: 439960.96 | V1225: 2927.0712 | W1225: 67.987964 | X1225: 428.96194 | Y1225: 268.36107 | Z1225: 226.784 | AA1225: 47.097123 | AB1225: FALSE | AC1225: FALSE | AD1225: 738814.48 | AE1225: 184703.62 | AF1225: 280236.61 | AG1225: 273874.25 | AH1225: 19.127394 | AI1225: 0.62889463 | AJ1225: FALSE
B1226: 95209 | C1226: California | D1226: 43855 | E1226: 39530491 | F1226: 102810 | G1226: 499140 | H1226: 5 | I1226: 102810 | J1226: 499140 | K1226: 14974.2 | L1226: 7 | M1226: 124785 | N1226: 359380.8 | O1226: 2390.9694 | P1226: 0.0011 | Q1226: 295.3245 | R1226: 249.57 | S1226: 0 | T1226: 2935.8639 | U1226: 484165.8 | V1226: 3221.1671 | W1226: 49.467444 | X1226: 472.06165 | Y1226: 295.3245 | Z1226: 249.57 | AA1226: 34.267452 | AB1226: FALSE | AC1226: TRUE | AD1226: 813046.46 | AE1226: 203261.62 | AF1226: 308393.23 | AG1226: 301391.62 | AH1226: 19.127394 | AI1226: 0.62889463 | AJ1226: TRUE
B1227: 95210 | C1227: California | D1227: 41567 | E1227: 39530491 | F1227: 61105 | G1227: 384087 | H1227: 5 | I1227: 61105 | J1227: 384087 | K1227: 11522.61 | L1227: 7 | M1227: 96021.75 | N1227: 276542.64 | O1227: 1839.8451 | P1227: 0.0011 | Q1227: 227.25147 | R1227: 192.0435 | S1227: 0 | T1227: 2259.1401 | U1227: 372564.39 | V1227: 2478.6802 | W1227: 64.045013 | X1227: 363.25028 | Y1227: 227.25147 | Z1227: 192.0435 | AA1227: 44.365732 | AB1227: FALSE | AC1227: FALSE | AD1227: 625637.25 | AE1227: 156409.31 | AF1227: 237307.83 | AG1227: 231920.11 | AH1227: 19.127394 | AI1227: 0.62889463 | AJ1227: FALSE
B1228: 95211 | C1228: California | D1228: 1567 | E1228: 39530491 | F1228: 75000 | G1228: 750000 | H1228: 5 | I1228: 75000 | J1228: 750000 | K1228: 22500 | L1228: 7 | M1228: 187500 | N1228: 540000 | O1228: 3592.6335 | P1228: 0 | Q1228: 443.75 | R1228: 375 | S1228: 0 | T1228: 4411.3835 | U1228: 727500 | V1228: 4840.0757 | W1228: 101.89021 | X1228: 709.3125 | Y1228: 443.75 | Z1228: 375 | AA1228: 70.582136 | AB1228: FALSE | AC1228: FALSE | AD1228: 1221671 | AE1228: 305417.74 | AF1228: 463386.87 | AG1228: 452866.36 | AH1228: 19.127394 | AI1228: 0.62889463 | AJ1228: FALSE
B1229: 95212 | C1229: California | D1229: 32251 | E1229: 39530491 | F1229: 110468 | G1229: 575716 | H1229: 5 | I1229: 110468 | J1229: 575716 | K1229: 17271.48 | L1229: 7 | M1229: 143929 | N1229: 414515.52 | O1229: 2757.7821 | P1229: 0.0008 | Q1229: 340.63197 | R1229: 287.858 | S1229: 0 | T1229: 3386.2721 | U1229: 558444.52 | V1229: 3715.3453 | W1229: 53.101192 | X1229: 544.48341 | Y1229: 340.63197 | Z1229: 287.858 | AA1229: 36.784648 | AB1229: FALSE | AC1229: FALSE | AD1229: 937780.7 | AE1229: 234445.17 | AF1229: 355705.65 | AG1229: 347629.88 | AH1229: 19.127394 | AI1229: 0.62889463 | AJ1229: FALSE
B1230: 95215 | C1230: California | D1230: 26776 | E1230: 39530491 | F1230: 61998 | G1230: 519092 | H1230: 5 | I1230: 61998 | J1230: 519092 | K1230: 15572.76 | L1230: 7 | M1230: 129773 | N1230: 373746.24 | O1230: 2486.5431 | P1230: 0.0007 | Q1230: 307.12943 | R1230: 259.546 | S1230: 0 | T1230: 3053.2185 | U1230: 503519.24 | V1230: 3349.9261 | W1230: 85.309838 | X1230: 490.93126 | Y1230: 307.12943 | Z1230: 259.546 | AA1230: 59.096458 | AB1230: FALSE | AC1230: FALSE | AD1230: 845546.17 | AE1230: 211386.54 | AF1230: 320720.56 | AG1230: 313439.07 | AH1230: 19.127394 | AI1230: 0.62889463 | AJ1230: FALSE
B1231: 95219 | C1231: California | D1231: 31189 | E1231: 39530491 | F1231: 103071 | G1231: 621811 | H1231: 5 | I1231: 103071 | J1231: 621811 | K1231: 18654.33 | L1231: 7 | M1231: 155452.75 | N1231: 447703.92 | O1231: 2978.5854 | P1231: 0.0008 | Q1231: 367.90484 | R1231: 310.9055 | S1231: 0 | T1231: 3657.3957 | U1231: 603156.67 | V1231: 4012.8164 | W1231: 61.468748 | X1231: 588.07775 | Y1231: 367.90484 | Z1231: 310.9055 | AA1231: 42.581083 | AB1231: FALSE | AC1231: FALSE | AD1231: 1012864.6 | AE1231: 253216.15 | AF1231: 384185.4 | AG1231: 375463.04 | AH1231: 19.127394 | AI1231: 0.62889463 | AJ1231: FALSE
... B1739: 19 | C1739: California | D1739: 10 | E1739: 39530491 | F1739: 58333 | G1739: 350000 | H1739: 5 | I1739: 58333 | J1739: 350000 | K1739: 10500 | L1739: 7 | M1739: 87500 | N1739: 252000 | O1739: 1676.5623 | P1739: 0 | Q1739: 207.08333 | R1739: 175 | S1739: 0 | T1739: 2058.6456 | U1739: 339500 | V1739: 2258.702 | W1739: 61.134476 | X1739: 331.0125 | Y1739: 207.08333 | Z1739: 175 | AA1739: 42.349523 | AB1739: FALSE | AC1739: FALSE | AD1739: 570113.12 | AE1739: 142528.28 | AF1739: 216247.21 | AG1739: 211337.63 | AH1739: 19.127394 | AI1739: 0.62889463 | AJ1739: FALSE
B1740: 22 | C1740: California | D1740: 62 | E1740: 39530491 | F1740: 175000 | G1740: 0 | H1740: 5 | I1740: 175000 | J1740: 0 | K1740: 0 | L1740: 7 | M1740: 0 | N1740: 0 | O1740: 0 | P1740: 0 | Q1740: 0 | R1740: 0 | S1740: 0 | T1740: 0 | U1740: 0 | V1740: 0 | W1740: 0 | X1740: 0 | Y1740: 0 | Z1740: 0 | AA1740: 0 | AB1740: TRUE | AC1740: TRUE | AD1740: 0 | AE1740: 0 | AF1740: 0 | AG1740: 0 | AJ1740: FALSE
B1741: 26 | C1741: California | D1741: 37 | E1741: 39530491 | F1741: 25000 | G1741: 346875 | H1741: 5 | I1741: 25000 | J1741: 346875 | K1741: 10406.25 | L1741: 7 | M1741: 86718.75 | N1741: 249750 | O1741: 1661.593 | P1741: 0 | Q1741: 205.23438 | R1741: 173.4375 | S1741: 0 | T1741: 2040.2649 | U1741: 336468.75 | V1741: 2238.535 | W1741: 141.37267 | X1741: 328.05703 | Y1741: 205.23438 | Z1741: 173.4375 | AA1741: 97.932713 | AB1741: FALSE | AC1741: FALSE | AD1741: 565022.82 | AE1741: 141255.71 | AF1741: 214316.43 | AG1741: 209450.69 | AH1741: 19.127394 | AI1741: 0.62889463 | AJ1741: FALSE
B1742: 29 | C1742: California | D1742: 5 | E1742: 39530491 | F1742: 87500 | G1742: 625000 | H1742: 5 | I1742: 87500 | J1742: 625000 | K1742: 18750 | L1742: 7 | M1742: 156250 | N1742: 450000 | O1742: 2993.8612 | P1742: 0 | Q1742: 369.79167 | R1742: 312.5 | S1742: 0 | T1742: 3676.1529 | U1742: 606250 | V1742: 4033.3964 | W1742: 72.778722 | X1742: 591.09375 | Y1742: 369.79167 | Z1742: 312.5 | AA1742: 50.415811 | AB1742: FALSE | AC1742: FALSE | AD1742: 1018059.1 | AE1742: 254514.79 | AF1742: 386155.73 | AG1742: 377388.63 | AH1742: 19.127394 | AI1742: 0.62889463 | AJ1742: FALSE
B1743: 32 | C1743: California | D1743: 6 | E1743: 39530491 | F1743: 200000 | G1743: 0 | H1743: 5 | I1743: 200000 | J1743: 0 | K1743: 0 | L1743: 7 | M1743: 0 | N1743: 0 | O1743: 0 | P1743: 0 | Q1743: 0 | R1743: 0 | S1743: 0 | T1743: 0 | U1743: 0 | V1743: 0 | W1743: 0 | X1743: 0 | Y1743: 0 | Z1743: 0 | AA1743: 0 | AB1743: TRUE | AC1743: TRUE | AD1743: 0 | AE1743: 0 | AF1743: 0 | AG1743: 0 | AJ1743: FALSE
B1744: 33 | C1744: California | D1744: 13 | E1744: 39530491 | F1744: 58071 | G1744: 275000 | H1744: 5 | I1744: 58071 | J1744: 275000 | K1744: 8250 | L1744: 7 | M1744: 68750 | N1744: 198000 | O1744: 1317.2989 | P1744: 0 | Q1744: 162.70833 | R1744: 137.5 | S1744: 0 | T1744: 1617.5073 | U1744: 266750 | V1744: 1774.6944 | W1744: 48.250948 | X1744: 260.08125 | Y1744: 162.70833 | Z1744: 137.5 | AA1744: 33.424751 | AB1744: FALSE | AC1744: TRUE | AD1744: 447946.02 | AE1744: 111986.51 | AF1744: 169908.52 | AG1744: 166051 | AH1744: 19.127394 | AI1744: 0.62889463 | AJ1744: TRUE
B1745: 34 | C1745: California | D1745: 64 | E1745: 39530491 | F1745: 35000 | G1745: 340000 | H1745: 5 | I1745: 35000 | J1745: 340000 | K1745: 10200 | L1745: 7 | M1745: 85000 | N1745: 244800 | O1745: 1628.6605 | P1745: 0 | Q1745: 201.16667 | R1745: 170 | S1745: 0 | T1745: 1999.8272 | U1745: 329800 | V1745: 2194.1676 | W1745: 98.979062 | X1745: 321.555 | Y1745: 201.16667 | Z1745: 170 | AA1745: 68.565503 | AB1745: FALSE | AC1745: FALSE | AD1745: 553824.17 | AE1745: 138456.04 | AF1745: 210068.71 | AG1745: 205299.42 | AH1745: 19.127394 | AI1745: 0.62889463 | AJ1745: FALSE
B1746: 35 | C1746: California | D1746: 7 | E1746: 39530491 | F1746: 59164 | G1746: 450000 | H1746: 5 | I1746: 59164 | J1746: 450000 | K1746: 13500 | L1746: 7 | M1746: 112500 | N1746: 324000 | O1746: 2155.5801 | P1746: 0 | Q1746: 266.25 | R1746: 225 | S1746: 0 | T1746: 2646.8301 | U1746: 436500 | V1746: 2904.0454 | W1746: 77.497456 | X1746: 425.5875 | Y1746: 266.25 | Z1746: 225 | AA1746: 53.684607 | AB1746: FALSE | AC1746: FALSE | AD1746: 733002.58 | AE1746: 183250.65 | AF1746: 278032.12 | AG1746: 271719.81 | AH1746: 19.127394 | AI1746: 0.62889463 | AJ1746: FALSE
B1747: 38 | C1747: California | D1747: 37 | E1747: 39530491 | F1747: 80443 | G1747: 625000 | H1747: 5 | I1747: 80443 | J1747: 625000 | K1747: 18750 | L1747: 7 | M1747: 156250 | N1747: 450000 | O1747: 2993.8612 | P1747: 0 | Q1747: 369.79167 | R1747: 312.5 | S1747: 0 | T1747: 3676.1529 | U1747: 606250 | V1747: 4033.3964 | W1747: 79.16336 | X1747: 591.09375 | Y1747: 369.79167 | Z1747: 312.5 | AA1747: 54.838625 | AB1747: FALSE | AC1747: FALSE | AD1747: 1018059.1 | AE1747: 254514.79 | AF1747: 386155.73 | AG1747: 377388.63 | AH1747: 19.127394 | AI1747: 0.62889463 | AJ1747: FALSE
B1748: 39 | C1748: California | D1748: 161 | E1748: 39530491 | F1748: 33186 | G1748: 363889 | H1748: 5 | I1748: 33186 | J1748: 363889 | K1748: 10916.67 | L1748: 7 | M1748: 90972.25 | N1748: 262000.08 | O1748: 1743.0931 | P1748: 0 | Q1748: 215.30099 | R1748: 181.9445 | S1748: 0 | T1748: 2140.3386 | U1748: 352972.33 | V1748: 2348.3337 | W1748: 111.724 | X1748: 344.14802 | Y1748: 215.30099 | Z1748: 181.9445 | AA1748: 77.394271 | AB1748: FALSE | AC1748: FALSE | AD1748: 592736.84 | AE1748: 148184.21 | AF1748: 224828.51 | AG1748: 219724.11 | AH1748: 19.127394 | AI1748: 0.62889463 | AJ1748: FALSE
B1749: 40 | C1749: California | D1749: 10 | E1749: 39530491 | F1749: 175000 | G1749: 0 | H1749: 5 | I1749: 175000 | J1749: 0 | K1749: 0 | L1749: 7 | M1749: 0 | N1749: 0 | O1749: 0 | P1749: 0 | Q1749: 0 | R1749: 0 | S1749: 0 | T1749: 0 | U1749: 0 | V1749: 0 | W1749: 0 | X1749: 0 | Y1749: 0 | Z1749: 0 | AA1749: 0 | AB1749: TRUE | AC1749: TRUE | AD1749: 0 | AE1749: 0 | AF1749: 0 | AG1749: 0 | AJ1749: FALSE
B1750: 44 | C1750: California | D1750: 12 | E1750: 39530491 | F1750: 65822 | G1750: 562500 | H1750: 5 | I1750: 65822 | J1750: 562500 | K1750: 16875 | L1750: 7 | M1750: 140625 | N1750: 405000 | O1750: 2694.4751 | P1750: 0 | Q1750: 332.8125 | R1750: 281.25 | S1750: 0 | T1750: 3308.5376 | U1750: 545625 | V1750: 3630.0567 | W1750: 87.073081 | X1750: 531.98438 | Y1750: 332.8125 | Z1750: 281.25 | AA1750: 60.317905 | AB1750: FALSE | AC1750: FALSE | AD1750: 916253.23 | AE1750: 229063.31 | AF1750: 347540.15 | AG1750: 339649.77 | AH1750: 19.127394 | AI1750: 0.62889463 | AJ1750: FALSE
B1751: 47 | C1751: California | D1751: 2 | E1751: 39530491 | F1751: 87500 | G1751: 625000 | H1751: 5 | I1751: 87500 | J1751: 625000 | K1751: 18750 | L1751: 7 | M1751: 156250 | N1751: 450000 | O1751: 2993.8612 | P1751: 0 | Q1751: 369.79167 | R1751: 312.5 | S1751: 0 | T1751: 3676.1529 | U1751: 606250 | V1751: 4033.3964 | W1751: 72.778722 | X1751: 591.09375 | Y1751: 369.79167 | Z1751: 312.5 | AA1751: 50.415811 | AB1751: FALSE | AC1751: FALSE | AD1751: 1018059.1 | AE1751: 254514.79 | AF1751: 386155.73 | AG1751: 377388.63 | AH1751: 19.127394 | AI1751: 0.62889463 | AJ1751: FALSE
B1752: 48 | C1752: California | D1752: 12 | E1752: 39530491 | F1752: 84511 | G1752: 562500 | H1752: 5 | I1752: 84511 | J1752: 562500 | K1752: 16875 | L1752: 7 | M1752: 140625 | N1752: 405000 | O1752: 2694.4751 | P1752: 0 | Q1752: 332.8125 | R1752: 281.25 | S1752: 0 | T1752: 3308.5376 | U1752: 545625 | V1752: 3630.0567 | W1752: 67.817495 | X1752: 531.98438 | Y1752: 332.8125 | Z1752: 281.25 | AA1752: 46.979034 | AB1752: FALSE | AC1752: FALSE | AD1752: 916253.23 | AE1752: 229063.31 | AF1752: 347540.15 | AG1752: 339649.77 | AH1752: 19.127394 | AI1752: 0.62889463 | AJ1752: FALSE
B1753: 50 | C1753: California | D1753: 3 | E1753: 39530491 | F1753: 7500 | G1753: 0 | H1753: 5 | I1753: 7500 | J1753: 0 | K1753: 0 | L1753: 7 | M1753: 0 | N1753: 0 | O1753: 0 | P1753: 0 | Q1753: 0 | R1753: 0 | S1753: 0 | T1753: 0 | U1753: 0 | V1753: 0 | W1753: 0 | X1753: 0 | Y1753: 0 | Z1753: 0 | AA1753: 0 | AB1753: TRUE | AC1753: TRUE | AD1753: 0 | AE1753: 0 | AF1753: 0 | AG1753: 0 | AJ1753: FALSE
B1754: 51 | C1754: California | D1754: 22 | E1754: 39530491 | F1754: 150000 | G1754: 350000 | H1754: 5 | I1754: 150000 | J1754: 350000 | K1754: 10500 | L1754: 7 | M1754: 87500 | N1754: 252000 | O1754: 1676.5623 | P1754: 0 | Q1754: 207.08333 | R1754: 175 | S1754: 0 | T1754: 2058.6456 | U1754: 339500 | V1754: 2258.702 | W1754: 23.774382 | X1754: 331.0125 | Y1754: 207.08333 | Z1754: 175 | AA1754: 16.469165 | AB1754: TRUE | AC1754: TRUE | AD1754: 570113.12 | AE1754: 142528.28 | AF1754: 216247.21 | AG1754: 211337.63 | AH1754: 19.127394 | AI1754: 0.62889463 | AJ1754: FALSE
B1755: 54 | C1755: California | D1755: 2 | E1755: 39530491 | F1755: 20000 | G1755: 625000 | H1755: 5 | I1755: 20000 | J1755: 625000 | K1755: 18750 | L1755: 7 | M1755: 156250 | N1755: 450000 | O1755: 2993.8612 | P1755: 0 | Q1755: 369.79167 | R1755: 312.5 | S1755: 0 | T1755: 3676.1529 | U1755: 606250 | V1755: 4033.3964 | W1755: 318.40691 | X1755: 591.09375 | Y1755: 369.79167 | Z1755: 312.5 | AA1755: 220.56917 | AB1755: FALSE | AC1755: FALSE | AD1755: 1018059.1 | AE1755: 254514.79 | AF1755: 386155.73 | AG1755: 377388.63 | AH1755: 19.127394 | AI1755: 0.62889463 | AJ1755: FALSE
B1756: 55 | C1756: California | D1756: 76 | E1756: 39530491 | F1756: 57490 | G1756: 536765 | H1756: 5 | I1756: 57490 | J1756: 536765 | K1756: 16102.95 | L1756: 7 | M1756: 134191.25 | N1756: 386470.8 | O1756: 2571.1999 | P1756: 0 | Q1756: 317.58596 | R1756: 268.3825 | S1756: 0 | T1756: 3157.1683 | U1756: 520662.05 | V1756: 3463.9776 | W1756: 95.131499 | X1756: 507.6455 | Y1756: 317.58596 | Z1756: 268.3825 | AA1756: 65.900191 | AB1756: FALSE | AC1756: FALSE | AD1756: 874333.62 | AE1756: 218583.41 | AF1756: 331639.8 | AG1756: 324110.41 | AH1756: 19.127394 | AI1756: 0.62889463 | AJ1756: FALSE
B1757: 65 | C1757: California | D1757: 14 | E1757: 39530491 | F1757: 89927 | G1757: 1250000 | H1757: 5 | I1757: 89927 | J1757: 1250000 | K1757: 37500 | L1757: 7 | M1757: 312500 | N1757: 900000 | O1757: 5987.7225 | P1757: 0 | Q1757: 739.58333 | R1757: 625 | S1757: 0 | T1757: 7352.3058 | U1757: 1212500 | V1757: 8066.7928 | W1757: 141.62906 | X1757: 1182.1875 | Y1757: 739.58333 | Z1757: 625 | AA1757: 98.110322 | AB1757: FALSE | AC1757: FALSE | AD1757: 2036118.3 | AE1757: 509029.57 | AF1757: 772311.45 | AG1757: 754777.26 | AH1757: 19.127394 | AI1757: 0.62889463 | AJ1757: FALSE

Sheet Wealth Creation Calc
D2: Borrower (**INSERT NAME**):
D3: Tiana | E3: =_xlfn.XLOOKUP(D3,'Assumptions & Borrower Profiles'!L2:N2,'Assumptions & Borrower Profiles'!L34:N34)*12 -> #N/A
D5: 0.25 | E5: =D5*$E$3 -> #N/A | J5: 0.5 | K5: =J5*$E$3 -> #N/A | P5: 1 | Q5: =P5*$E$3 -> #N/A
E7: Conservative | F7: Moderate | G7: Growth | H7: Private | K7: Conservative | L7: Moderate | M7: Growth | N7: Private | Q7: Conservative | R7: Moderate | S7: Growth | T7: Private
